Workbook

Sheet Tổng hợp
A1: TỔNG HỢP KẾT QUẢ KIỂM THỬ HỆ THỐNG TIGER SHOP
A2: Học phần: Đánh giá và Kiểm định chất lượng phần mềm
A3: Bộ kịch bản tự động chạy ngày 25/09/2026 trên cơ sở dữ liệu ecommerce_test. Trạng thái ghi theo bốn trạng thái của Bảng 2.25; tỉ lệ đạt tính trên số test case đã thực hiện. Mọi số liệu dưới đây là công thức đếm từ cột Trạng thái của các sheet test case.
A5: 1. KẾT QUẢ THEO NHÓM CHỨC NĂNG (Bảng 3.34)
A6: STT | B6: Mã nhóm | C6: Nhóm chức năng | D6: Số TC | E6: Đã thực hiện | F6: Pass | G6: Fail | H6: Blocked | I6: Chưa thực hiện | J6: Tỉ lệ đạt trên số đã thực hiện
A7: 1 | B7: AUTH | C7: Xác thực và phân quyền | D7: =COUNTA(AUTH!A:A)-1 -> 25 | E7: =F7+G7 -> 20 | F7: =COUNTIF(AUTH!M:M,"Pass") -> 19 | G7: =COUNTIF(AUTH!M:M,"Fail") -> 1 | H7: =COUNTIF(AUTH!M:M,"Blocked") -> 0 | I7: =COUNTIF(AUTH!M:M,"Chưa thực hiện") -> 5 | J7: =IF(E7=0,0,F7/E7) -> 0.95
A8: 2 | B8: PROD | C8: Quản lý sản phẩm và tồn kho | D8: =COUNTA(PROD!A:A)-1 -> 22 | E8: =F8+G8 -> 19 | F8: =COUNTIF(PROD!M:M,"Pass") -> 18 | G8: =COUNTIF(PROD!M:M,"Fail") -> 1 | H8: =COUNTIF(PROD!M:M,"Blocked") -> 0 | I8: =COUNTIF(PROD!M:M,"Chưa thực hiện") -> 3 | J8: =IF(E8=0,0,F8/E8) -> 0.94736842
A9: 3 | B9: ORD | C9: Giỏ hàng và đơn hàng | D9: =COUNTA(ORD!A:A)-1 -> 22 | E9: =F9+G9 -> 15 | F9: =COUNTIF(ORD!M:M,"Pass") -> 14 | G9: =COUNTIF(ORD!M:M,"Fail") -> 1 | H9: =COUNTIF(ORD!M:M,"Blocked") -> 0 | I9: =COUNTIF(ORD!M:M,"Chưa thực hiện") -> 7 | J9: =IF(E9=0,0,F9/E9) -> 0.93333333
A10: 4 | B10: VOUC | C10: Voucher và ví voucher | D10: =COUNTA(VOUC!A:A)-1 -> 12 | E10: =F10+G10 -> 12 | F10: =COUNTIF(VOUC!M:M,"Pass") -> 12 | G10: =COUNTIF(VOUC!M:M,"Fail") -> 0 | H10: =COUNTIF(VOUC!M:M,"Blocked") -> 0 | I10: =COUNTIF(VOUC!M:M,"Chưa thực hiện") -> 0 | J10: =IF(E10=0,0,F10/E10) -> 1
A11: 5 | B11: REV | C11: Đánh giá sản phẩm | D11: =COUNTA(REV!A:A)-1 -> 8 | E11: =F11+G11 -> 8 | F11: =COUNTIF(REV!M:M,"Pass") -> 8 | G11: =COUNTIF(REV!M:M,"Fail") -> 0 | H11: =COUNTIF(REV!M:M,"Blocked") -> 0 | I11: =COUNTIF(REV!M:M,"Chưa thực hiện") -> 0 | J11: =IF(E11=0,0,F11/E11) -> 1
A12: 6 | B12: CHAT | C12: Chat hỗ trợ thời gian thực | D12: =COUNTA(CHAT!A:A)-1 -> 11 | E12: =F12+G12 -> 6 | F12: =COUNTIF(CHAT!M:M,"Pass") -> 5 | G12: =COUNTIF(CHAT!M:M,"Fail") -> 1 | H12: =COUNTIF(CHAT!M:M,"Blocked") -> 0 | I12: =COUNTIF(CHAT!M:M,"Chưa thực hiện") -> 5 | J12: =IF(E12=0,0,F12/E12) -> 0.83333333
A13: 7 | B13: AI | C13: Trợ lý ảo Tiger AI | D13: =COUNTA(AI!A:A)-1 -> 10 | E13: =F13+G13 -> 9 | F13: =COUNTIF(AI!M:M,"Pass") -> 8 | G13: =COUNTIF(AI!M:M,"Fail") -> 1 | H13: =COUNTIF(AI!M:M,"Blocked") -> 0 | I13: =COUNTIF(AI!M:M,"Chưa thực hiện") -> 1 | J13: =IF(E13=0,0,F13/E13) -> 0.88888889
A14: 8 | B14: HR | C14: Ca làm, chấm công và lương | D14: =COUNTA(HR!A:A)-1 -> 15 | E14: =F14+G14 -> 14 | F14: =COUNTIF(HR!M:M,"Pass") -> 14 | G14: =COUNTIF(HR!M:M,"Fail") -> 0 | H14: =COUNTIF(HR!M:M,"Blocked") -> 0 | I14: =COUNTIF(HR!M:M,"Chưa thực hiện") -> 1 | J14: =IF(E14=0,0,F14/E14) -> 1
A15: 9 | B15: ADM | C15: Quản trị hệ thống | D15: =COUNTA(ADM!A:A)-1 -> 10 | E15: =F15+G15 -> 10 | F15: =COUNTIF(ADM!M:M,"Pass") -> 9 | G15: =COUNTIF(ADM!M:M,"Fail") -> 1 | H15: =COUNTIF(ADM!M:M,"Blocked") -> 0 | I15: =COUNTIF(ADM!M:M,"Chưa thực hiện") -> 0 | J15: =IF(E15=0,0,F15/E15) -> 0.9
C16: TỔNG CỘNG | D16: =SUM(D7:D15) -> 135 | E16: =SUM(E7:E15) -> 113 | F16: =SUM(F7:F15) -> 107 | G16: =SUM(G7:G15) -> 6 | H16: =SUM(H7:H15) -> 0 | I16: =SUM(I7:I15) -> 22 | J16: =IF(E16=0,0,F16/E16) -> 0.94690265
C17: Kiểm tra: Số TC bằng tổng bốn trạng thái | D17: =IF(D16=F16+G16+H16+I16,"Khớp","Lệch") -> Khớp
A19: 2. ĐỐI CHIẾU VỚI TIÊU CHÍ KẾT THÚC KIỂM THỬ (Bảng 2.27)
A20: STT | B20: Chỉ số | D20: Giá trị | E20: Ngưỡng | F20: Kết luận
A21: 1 | B21: Tỉ lệ test case đã thực thi | D21: =IF(D16=0,0,E16/D16) -> 0.83703704 | E21: 1 | F21: =IF(ROUND(D21,4)>=E21,"Đạt","Chưa đạt") -> Chưa đạt
A22: 2 | B22: Tỉ lệ đạt trên số test case đã thực thi | D22: =J16 -> 0.94690265 | E22: 0.95 | F22: =IF(ROUND(D22,4)>=E22,"Đạt","Chưa đạt") -> Chưa đạt
A23: 3 | B23: Tỉ lệ Use Case có test case | D23: =COUNTIF('Truy vết UC và TC'!B4:B28,">0")/COUNTA('Truy vết UC và TC'!A4:A28) -> 1 | E23: 1 | F23: =IF(ROUND(D23,4)>=E23,"Đạt","Chưa đạt") -> Đạt
B24: Ngưỡng lấy theo tiêu chí kết thúc ở Bảng 2.27 của Chương II.
A26: 3. KẾT QUẢ THEO LOẠI KIỂM THỬ VÀ MỨC ƯU TIÊN (Bảng 3.3 và Bảng 3.35)
A27: STT | B27: Phân loại | D27: Số TC | E27: Tỉ lệ trên tổng số TC | F27: Pass | G27: Fail | H27: Đã thực hiện | I27: Chưa thực hiện | J27: Tỉ lệ đạt trên số đã thực hiện
A28: 1 | B28: Positive | D28: =COUNTIF('Toàn bộ Test Case'!I:I,"Positive") -> 70 | E28: =IF($D$16=0,0,D28/$D$16) -> 0.51851852 | F28: =COUNTIFS('Toàn bộ Test Case'!I:I,"Positive",'Toàn bộ Test Case'!M:M,"Pass") -> 55 | G28: =COUNTIFS('Toàn bộ Test Case'!I:I,"Positive",'Toàn bộ Test Case'!M:M,"Fail") -> 3 | H28: =F28+G28 -> 58 | I28: =COUNTIFS('Toàn bộ Test Case'!I:I,"Positive",'Toàn bộ Test Case'!M:M,"Chưa thực hiện") -> 12 | J28: =IF(H28=0,0,F28/H28) -> 0.94827586
A29: 2 | B29: Negative | D29: =COUNTIF('Toàn bộ Test Case'!I:I,"Negative") -> 34 | E29: =IF($D$16=0,0,D29/$D$16) -> 0.25185185 | F29: =COUNTIFS('Toàn bộ Test Case'!I:I,"Negative",'Toàn bộ Test Case'!M:M,"Pass") -> 26 | G29: =COUNTIFS('Toàn bộ Test Case'!I:I,"Negative",'Toàn bộ Test Case'!M:M,"Fail") -> 1 | H29: =F29+G29 -> 27 | I29: =COUNTIFS('Toàn bộ Test Case'!I:I,"Negative",'Toàn bộ Test Case'!M:M,"Chưa thực hiện") -> 7 | J29: =IF(H29=0,0,F29/H29) -> 0.96296296
A30: 3 | B30: Boundary | D30: =COUNTIF('Toàn bộ Test Case'!I:I,"Boundary") -> 9 | E30: =IF($D$16=0,0,D30/$D$16) -> 0.066666667 | F30: =COUNTIFS('Toàn bộ Test Case'!I:I,"Boundary",'Toàn bộ Test Case'!M:M,"Pass") -> 7 | G30: =COUNTIFS('Toàn bộ Test Case'!I:I,"Boundary",'Toàn bộ Test Case'!M:M,"Fail") -> 0 | H30: =F30+G30 -> 7 | I30: =COUNTIFS('Toàn bộ Test Case'!I:I,"Boundary",'Toàn bộ Test Case'!M:M,"Chưa thực hiện") -> 2 | J30: =IF(H30=0,0,F30/H30) -> 1
A31: 4 | B31: Security | D31: =COUNTIF('Toàn bộ Test Case'!I:I,"Security") -> 22 | E31: =IF($D$16=0,0,D31/$D$16) -> 0.16296296 | F31: =COUNTIFS('Toàn bộ Test Case'!I:I,"Security",'Toàn bộ Test Case'!M:M,"Pass") -> 19 | G31: =COUNTIFS('Toàn bộ Test Case'!I:I,"Security",'Toàn bộ Test Case'!M:M,"Fail") -> 2 | H31: =F31+G31 -> 21 | I31: =COUNTIFS('Toàn bộ Test Case'!I:I,"Security",'Toàn bộ Test Case'!M:M,"Chưa thực hiện") -> 1 | J31: =IF(H31=0,0,F31/H31) -> 0.9047619
A32: 5 | B32: Ưu tiên Cao | D32: =COUNTIF('Toàn bộ Test Case'!J:J,"Cao") -> 110 | E32: =IF($D$16=0,0,D32/$D$16) -> 0.81481481 | F32: =COUNTIFS('Toàn bộ Test Case'!J:J,"Cao",'Toàn bộ Test Case'!M:M,"Pass") -> 92 | G32: =COUNTIFS('Toàn bộ Test Case'!J:J,"Cao",'Toàn bộ Test Case'!M:M,"Fail") -> 6 | H32: =F32+G32 -> 98 | I32: =COUNTIFS('Toàn bộ Test Case'!J:J,"Cao",'Toàn bộ Test Case'!M:M,"Chưa thực hiện") -> 12 | J32: =IF(H32=0,0,F32/H32) -> 0.93877551
A33: 6 | B33: Ưu tiên Trung bình | D33: =COUNTIF('Toàn bộ Test Case'!J:J,"Trung bình") -> 25 | E33: =IF($D$16=0,0,D33/$D$16) -> 0.18518519 | F33: =COUNTIFS('Toàn bộ Test Case'!J:J,"Trung bình",'Toàn bộ Test Case'!M:M,"Pass") -> 15 | G33: =COUNTIFS('Toàn bộ Test Case'!J:J,"Trung bình",'Toàn bộ Test Case'!M:M,"Fail") -> 0 | H33: =F33+G33 -> 15 | I33: =COUNTIFS('Toàn bộ Test Case'!J:J,"Trung bình",'Toàn bộ Test Case'!M:M,"Chưa thực hiện") -> 10 | J33: =IF(H33=0,0,F33/H33) -> 1
A35: 4. PHƯƠNG PHÁP THỰC HIỆN THEO THIẾT KẾ VÀ THEO THỰC TẾ (Bảng 3.4)
A36: STT | B36: Phương pháp theo thiết kế | D36: Số TC | E36: Tỉ lệ trên tổng số TC | F36: Kịch bản Jest | G36: Phép đo riêng | H36: Chưa thực hiện
A37: 1 | B37: Thực thi bằng mã | D37: =COUNTIF('Toàn bộ Test Case'!K:K,"Tự động") -> 119 | E37: =IF($D$16=0,0,D37/$D$16) -> 0.88148148 | F37: =COUNTIFS('Toàn bộ Test Case'!K:K,"Tự động",'Toàn bộ Test Case'!N:N,"Jest + Supertest") -> 105 | G37: =COUNTIFS('Toàn bộ Test Case'!K:K,"Tự động",'Toàn bộ Test Case'!N:N,"Đo trực tiếp với Gemini thật") -> 0 | H37: =COUNTIFS('Toàn bộ Test Case'!K:K,"Tự động",'Toàn bộ Test Case'!M:M,"Chưa thực hiện") -> 14
A38: 2 | B38: Thủ công | D38: =COUNTIF('Toàn bộ Test Case'!K:K,"Thủ công") -> 16 | E38: =IF($D$16=0,0,D38/$D$16) -> 0.11851852 | F38: =COUNTIFS('Toàn bộ Test Case'!K:K,"Thủ công",'Toàn bộ Test Case'!N:N,"Jest + Supertest") -> 7 | G38: =COUNTIFS('Toàn bộ Test Case'!K:K,"Thủ công",'Toàn bộ Test Case'!N:N,"Đo trực tiếp với Gemini thật") -> 1 | H38: =COUNTIFS('Toàn bộ Test Case'!K:K,"Thủ công",'Toàn bộ Test Case'!M:M,"Chưa thực hiện") -> 8
B39: TỔNG CỘNG | D39: =SUM(D37:D38) -> 135 | E39: =IF($D$16=0,0,D39/$D$16) -> 1 | F39: =SUM(F37:F38) -> 112 | G39: =SUM(G37:G38) -> 1 | H39: =SUM(H37:H38) -> 22
B40: Bảy test case thiết kế thủ công đã được chuyển thành kịch bản Jest: ORD-014, REV-008, AI-001, AI-005, AI-007, HR-013, ADM-008; AI-008 thực hiện bằng phép đo riêng (mục 5.4.5).
A42: 5. TEST CASE KHÔNG ĐẠT VÀ KHIẾM KHUYẾT LIÊN QUAN (Bảng 3.36)
A43: STT | B43: Mã TC | C43: Use Case và bước bị vi phạm | D43: Mã khiếm khuyết | F43: Mức độ | H43: Vị trí trong mã nguồn
A44: 1 | B44: CHAT-009 | C44: UC21, ngoại lệ 5c | D44: DEF-08 (trùng VUL-01) | F44: Nghiêm trọng | H44: routes/chatRoutes.js, tuyến GET /messages/:threadId
A45: 2 | B45: ADM-005 | C45: UC23, ngoại lệ 3b | D45: DEF-06 (trùng VUL-02) | F45: Nghiêm trọng | H45: userController.resetUserPassword
A46: 3 | B46: PROD-008 | C46: UC12, bước 5 và hậu điều kiện | D46: DEF-02 | F46: Cao | H46: productController.createProduct
A47: 4 | B47: ORD-022 | C47: UC11, ngoại lệ 4a | D47: DEF-11 | F47: Trung bình | H47: orderController.updateOrderStatus
A48: 5 | B48: AI-008 | C48: Bảng 1.31, chỉ tiêu 3 | D48: PERF-03 | F48: Trung bình | H48: aiChatController.chatWithAi
A49: 6 | B49: AUTH-006 | C49: UC01, ngoại lệ 6a | D49: DEF-12 (mới) | F49: Thấp | H49: authController.register
B50: =COUNTIF('Toàn bộ Test Case'!M:M,"Fail") -> 6 | C50: test case không đạt (đếm từ sheet Toàn bộ Test Case)

Sheet Toàn bộ Test Case
A1: Mã TC | B1: Nhóm chức năng | C1: UC liên quan | D1: Tiêu đề kiểm thử | E1: Điều kiện tiên quyết | F1: Dữ liệu đầu vào | G1: Các bước thực hiện | H1: Kết quả mong đợi | I1: Loại KT | J1: Mức ưu tiên | K1: Phương pháp | L1: Kết quả thực tế | M1: Trạng thái | N1: Người thực hiện | O1: Ngày thực hiện | P1: Ghi chú
A2: AUTH-001 | B2: Xác thực và phân quyền | C2: UC01 | D2: Đăng ký với dữ liệu hợp lệ | E2: Email chưa tồn tại | F2: name = Nguoi dung moi; email = new.user.[thời điểm]@tigershop.test; password = Test@123; phone = 0912345678; birthday = 2000-05-20 | G2: 1. Gửi POST /api/auth/register 2. Truy vấn bảng users theo email 3. Truy vấn user_vouchers của tài khoản mới | H2: Mã 200, thông báo Register successful; users có role_id = 5, status = active; ví có một voucher chào mừng giảm 50% (hậu điều kiện UC01) | I2: Positive | J2: Cao | K2: Tự động | L2: Mã 200, Register successful; role_id = 5, status = active; ví có đúng một voucher value = 50. Voucher được ghi sau khi phản hồi đã trả về nên kịch bản phải chờ tối đa 3 giây mới thấy bản ghi (liên quan DEF-01) | M2: Pass | N2: Jest + Supertest | O2: 25/09/2026 | P2: Quan sát được DEF-01: voucher chào mừng ghi sau phản hồi, không cùng giao dịch
A3: AUTH-002 | B3: Xác thực và phân quyền | C3: UC01 | D3: Đăng ký khi bỏ trống họ tên | E3: Máy chủ đang chạy; không cần đăng nhập | F3: name rỗng; các trường khác hợp lệ | G3: 1. Gửi POST /api/auth/register | H3: Mã 400, thông báo Thiếu thông tin đăng ký (ngoại lệ 5a) | I3: Negative | J3: Cao | K3: Tự động | L3: Mã 400, Thiếu thông tin đăng ký | M3: Pass | N3: Jest + Supertest | O3: 25/09/2026
A4: AUTH-003 | B4: Xác thực và phân quyền | C4: UC01 | D4: Đăng ký khi bỏ trống email | E4: Máy chủ đang chạy; không cần đăng nhập | F4: email rỗng; các trường khác hợp lệ | G4: 1. Gửi POST /api/auth/register | H4: Mã 400, thông báo Thiếu thông tin đăng ký (ngoại lệ 5a) | I4: Negative | J4: Cao | K4: Tự động | L4: Mã 400, Thiếu thông tin đăng ký | M4: Pass | N4: Jest + Supertest | O4: 25/09/2026
A5: AUTH-004 | B5: Xác thực và phân quyền | C5: UC01 | D5: Đăng ký khi bỏ trống mật khẩu | E5: Máy chủ đang chạy; không cần đăng nhập | F5: password rỗng; các trường khác hợp lệ | G5: 1. Gửi POST /api/auth/register | H5: Mã 400, thông báo Thiếu thông tin đăng ký (ngoại lệ 5a) | I5: Negative | J5: Cao | K5: Tự động | L5: Mã 400, Thiếu thông tin đăng ký | M5: Pass | N5: Jest + Supertest | O5: 25/09/2026
A6: AUTH-005 | B6: Xác thực và phân quyền | C6: UC01 | D6: Đăng ký khi bỏ trống số điện thoại | E6: Máy chủ đang chạy; không cần đăng nhập | F6: phone rỗng; các trường khác hợp lệ | G6: 1. Gửi POST /api/auth/register | H6: Mã 400, thông báo Thiếu thông tin đăng ký (ngoại lệ 5a) | I6: Negative | J6: Trung bình | K6: Tự động | L6: Mã 400, Thiếu thông tin đăng ký | M6: Pass | N6: Jest + Supertest | O6: 25/09/2026
A7: AUTH-006 | B7: Xác thực và phân quyền | C7: UC01 | D7: Đăng ký với email đã tồn tại | E7: customer1@tigershop.test có sẵn trong dữ liệu mẫu | F7: email = customer1@tigershop.test; các trường khác hợp lệ | G7: 1. Gửi POST /api/auth/register 2. Đếm bản ghi users có email này | H7: Từ chối đăng ký, mã 409 kèm thông báo thư điện tử đã được sử dụng; không phát sinh bản ghi trùng (ngoại lệ 6a) | I7: Negative | J7: Cao | K7: Tự động | L7: Mã 500, thông báo Email đã tồn tại; số bản ghi vẫn là 1 nhờ ràng buộc UNIQUE | M7: Fail | N7: Jest + Supertest | O7: 25/09/2026 | P7: Khiếm khuyết DEF-12, mức Thấp (Bảng 3.36)
A8: AUTH-007 | B8: Xác thực và phân quyền | C8: UC01 | D8: Mật khẩu xác nhận không khớp | E8: Đang ở trang /register | F8: password = Test@123; confirmPassword = Test@456 | G8: 1. Nhập hai mật khẩu khác nhau 2. Nhấn Đăng ký | H8: Giao diện báo lỗi xác nhận mật khẩu và không gửi yêu cầu tới máy chủ (Hình 1.7) | I8: Negative | J8: Cao | K8: Tự động | L8: Chưa có kết quả; kiểm tra này nằm hoàn toàn trong Register.js | M8: Chưa thực hiện | P8: Lý do: chức năng nằm hoàn toàn ở giao diện, thuộc giai đoạn 6 chưa triển khai (Bảng 3.38, dòng 1)
A9: AUTH-008 | B9: Xác thực và phân quyền | C9: UC01 | D9: Đăng ký với email sai định dạng | E9: Đang ở trang /register | F9: email = abc@@test | G9: 1. Nhập email sai định dạng 2. Nhấn Đăng ký | H9: Giao diện chặn gửi biểu mẫu và cảnh báo định dạng email (Hình 1.7) | I9: Negative | J9: Trung bình | K9: Tự động | L9: Chưa có kết quả; kiểm tra này nằm hoàn toàn trong Register.js | M9: Chưa thực hiện | P9: Lý do: chức năng nằm hoàn toàn ở giao diện, thuộc giai đoạn 6 chưa triển khai (Bảng 3.38, dòng 1)
A10: AUTH-009 | B10: Xác thực và phân quyền | C10: UC01 | D10: Mật khẩu được băm trước khi lưu | E10: Đăng ký thành công một tài khoản mới | F10: email = hash.check.[thời điểm]@tigershop.test; password = Test@123 | G10: 1. Đăng ký tài khoản 2. Đọc cột password theo email 3. So khớp bằng bcrypt.compare | H10: Cột password là chuỗi băm bcrypt, khác mật khẩu gốc (bước 6; mục 1.3.3) | I10: Security | J10: Cao | K10: Tự động | L10: Giá trị lưu khác mật khẩu gốc, khớp mẫu chuỗi băm bcrypt; bcrypt.compare với mật khẩu gốc trả về true | M10: Pass | N10: Jest + Supertest | O10: 25/09/2026
A11: AUTH-010 | B11: Xác thực và phân quyền | C11: UC01 | D11: Voucher chào mừng được phát tự động | E11: Vừa đăng ký tài khoản mới | F11: tài khoản tạo ở AUTH-001 | G11: 1. Đăng nhập tài khoản mới 2. Mở trang Voucher của tôi | H11: Ví có đúng một voucher giảm 50%, áp dụng cho đơn từ 50.000 đ, giảm tối đa 100.000 đ, hiệu lực 30 ngày (bước 7) | I11: Positive | J11: Trung bình | K11: Thủ công | L11: Chưa kiểm tra trên giao diện. Kịch bản AUTH-001 mới xác nhận giá trị giảm 50%; đơn tối thiểu, mức giảm tối đa và hạn dùng chưa được đối chiếu | M11: Chưa thực hiện | P11: Lý do: kịch bản hiện có chưa đủ tin cậy làm bằng chứng (Bảng 3.38, dòng 2)
A12: AUTH-011 | B12: Xác thực và phân quyền | C12: UC01 | D12: Giới hạn tần suất trên nhóm API xác thực | E12: Bộ giới hạn thật, không giả lập | F12: 13 yêu cầu POST /api/auth/login liên tiếp từ cùng một địa chỉ | G12: 1. Gửi liên tiếp 13 yêu cầu 2. Ghi mã trạng thái của từng yêu cầu | H12: Mười yêu cầu đầu được xử lý bình thường; từ yêu cầu thứ 11 trả mã 429 (ngoại lệ 4a) | I12: Security | J12: Cao | K12: Tự động | L12: Yêu cầu 1 đến 10 được xử lý (mã 401 vì email không tồn tại); yêu cầu 11 đến 13 trả mã 429. Kịch bản AUTH-011b xác nhận thông báo tiếng Việt có cụm từ quá nhanh | M12: Pass | N12: Jest + Supertest | O12: 25/09/2026
A13: AUTH-012 | B13: Xác thực và phân quyền | C13: UC02 | D13: Đăng nhập tài khoản Quản trị viên | E13: Tài khoản đang hoạt động | F13: admin@tigershop.test; Test@123 | G13: 1. Gửi POST /api/auth/login | H13: Mã 200, trả về token và role = ADMIN; giao diện chuyển tới /admin/dashboard (bước 8) | I13: Positive | J13: Cao | K13: Tự động | L13: Mã 200, token là chuỗi JWT, role = ADMIN. Phần chuyển trang trên giao diện chưa kiểm chứng | M13: Pass | N13: Jest + Supertest | O13: 25/09/2026 | P13: Mức kiểm chứng hạn chế: phần giao diện hoặc thời gian thực chưa kiểm chứng (Bảng 3.37, dòng 4)
A14: AUTH-013 | B14: Xác thực và phân quyền | C14: UC02 | D14: Đăng nhập tài khoản Quản lý | E14: Tài khoản đang hoạt động | F14: manager@tigershop.test; Test@123 | G14: 1. Gửi POST /api/auth/login | H14: Mã 200, role = MANAGER; giao diện chuyển tới /manager/workspace | I14: Positive | J14: Cao | K14: Tự động | L14: Mã 200, token là chuỗi JWT, role = MANAGER. Phần chuyển trang chưa kiểm chứng | M14: Pass | N14: Jest + Supertest | O14: 25/09/2026 | P14: Mức kiểm chứng hạn chế: phần giao diện hoặc thời gian thực chưa kiểm chứng (Bảng 3.37, dòng 4)
A15: AUTH-014 | B15: Xác thực và phân quyền | C15: UC02 | D15: Đăng nhập tài khoản Nhân viên | E15: status = active | F15: staff@tigershop.test; Test@123 | G15: 1. Gửi POST /api/auth/login | H15: Mã 200, role = STAFF; giao diện chuyển tới /staff/workspace | I15: Positive | J15: Cao | K15: Tự động | L15: Mã 200, token là chuỗi JWT, role = STAFF. Phần chuyển trang chưa kiểm chứng | M15: Pass | N15: Jest + Supertest | O15: 25/09/2026 | P15: Mức kiểm chứng hạn chế: phần giao diện hoặc thời gian thực chưa kiểm chứng (Bảng 3.37, dòng 4)
A16: AUTH-015 | B16: Xác thực và phân quyền | C16: UC02 | D16: Đăng nhập tài khoản Khách hàng | E16: Tài khoản đang hoạt động | F16: customer1@tigershop.test; Test@123 | G16: 1. Gửi POST /api/auth/login | H16: Mã 200, role = CUSTOMER; giao diện chuyển tới /home | I16: Positive | J16: Cao | K16: Tự động | L16: Mã 200, token là chuỗi JWT, role = CUSTOMER. Phần chuyển trang chưa kiểm chứng | M16: Pass | N16: Jest + Supertest | O16: 25/09/2026 | P16: Mức kiểm chứng hạn chế: phần giao diện hoặc thời gian thực chưa kiểm chứng (Bảng 3.37, dòng 4)
A17: AUTH-016 | B17: Xác thực và phân quyền | C17: UC02 | D17: Đăng nhập với mật khẩu sai | E17: Tài khoản tồn tại trong hệ thống | F17: customer1@tigershop.test; SaiMatKhau123 | G17: 1. Gửi POST /api/auth/login | H17: Mã 401, thông báo Wrong password; không cấp token (ngoại lệ 6a) | I17: Negative | J17: Cao | K17: Tự động | L17: Mã 401, Wrong password; phản hồi không có trường token | M17: Pass | N17: Jest + Supertest | O17: 25/09/2026 | P17: Hai thông báo khác nhau cho phép dò email (VUL-10, Chương VI)
A18: AUTH-017 | B18: Xác thực và phân quyền | C18: UC02 | D18: Đăng nhập với email không tồn tại | E18: Email khongtontai@tigershop.test chưa từng đăng ký | F18: khongtontai@tigershop.test; Test@123 | G18: 1. Gửi POST /api/auth/login | H18: Mã 401, thông báo User not found (ngoại lệ 4a) | I18: Negative | J18: Cao | K18: Tự động | L18: Mã 401, User not found | M18: Pass | N18: Jest + Supertest | O18: 25/09/2026 | P18: Hai thông báo khác nhau cho phép dò email (VUL-10, Chương VI)
A19: AUTH-018 | B19: Xác thực và phân quyền | C19: UC02 | D19: Bỏ trống email và mật khẩu | E19: Máy chủ đang chạy; không cần đăng nhập | F19: email rỗng; password rỗng | G19: 1. Gửi POST /api/auth/login | H19: Mã 400, thông báo Thiếu email hoặc mật khẩu (ngoại lệ 2a) | I19: Negative | J19: Trung bình | K19: Tự động | L19: Mã 400, Thiếu email hoặc mật khẩu | M19: Pass | N19: Jest + Supertest | O19: 25/09/2026
A20: AUTH-019 | B20: Xác thực và phân quyền | C20: UC02 | D20: Token cấp trước khi tài khoản bị khóa | E20: customer2 đang hoạt động | F20: token của customer2 | G20: 1. Đăng nhập customer2 và gọi GET /api/users/me 2. Đặt is_active = 0 3. Gọi lại GET /api/users/me bằng token cũ | H20: Lần gọi sau khi khóa trả mã 403, thông báo Tài khoản của bạn đã bị khóa. (UC23 ngoại lệ 3a) | I20: Security | J20: Cao | K20: Tự động | L20: Trước khi khóa mã 200; sau khi khóa mã 403 với đúng thông báo. Kịch bản AUTH-019b xác nhận thêm tài khoản customer.locked bị chặn ngay ở bước đăng nhập (mã 403, không cấp token, ngoại lệ 5c) | M20: Pass | N20: Jest + Supertest | O20: 25/09/2026
A21: AUTH-020 | B21: Xác thực và phân quyền | C21: UC03 | D21: Gọi API được bảo vệ khi không gửi token | E21: Máy chủ đang chạy | F21: Yêu cầu GET /api/users/me không có header Authorization | G21: 1. Gửi yêu cầu | H21: Mã 401, thông báo Token không tồn tại | I21: Security | J21: Cao | K21: Tự động | L21: Mã 401, Token không tồn tại | M21: Pass | N21: Jest + Supertest | O21: 25/09/2026
A22: AUTH-021 | B22: Xác thực và phân quyền | C22: UC03 | D22: Gọi API với token sai định dạng hoặc đã hết hạn | E22: Máy chủ đang chạy | F22: Bearer abc.def.ghi; token hợp lệ về chữ ký nhưng hết hạn từ 1 giờ trước | G22: 1. Gửi yêu cầu kèm token sai định dạng 2. Gửi yêu cầu kèm token hết hạn | H22: Cả hai trường hợp trả mã 401, thông báo Token không hợp lệ (ngoại lệ 1a) | I22: Security | J22: Cao | K22: Tự động | L22: Cả hai trả mã 401, Token không hợp lệ (trường hợp hết hạn chạy ở kịch bản AUTH-021b) | M22: Pass | N22: Jest + Supertest | O22: 25/09/2026
A23: AUTH-022 | B23: Xác thực và phân quyền | C23: UC03 | D23: Đăng xuất và xác nhận phiên đã kết thúc | E23: Đang đăng nhập trên trình duyệt | F23: Không | G23: 1. Nhấn Đăng xuất 2. Kiểm tra localStorage 3. Truy cập lại trang cần đăng nhập | H23: Dữ liệu xác thực trong localStorage bị xóa, trình duyệt chuyển về /login và không vào lại được trang bảo vệ (hậu điều kiện UC03) | I23: Positive | J23: Cao | K23: Tự động | L23: Chưa có kết quả; UC03 không có điểm cuối API, toàn bộ xử lý nằm ở giao diện | M23: Chưa thực hiện | P23: Lý do: chức năng nằm hoàn toàn ở giao diện, thuộc giai đoạn 6 chưa triển khai (Bảng 3.38, dòng 1)
A24: AUTH-023 | B24: Xác thực và phân quyền | C24: UC04 | D24: Xem và cập nhật hồ sơ cá nhân | E24: customer1 đã đăng nhập | F24: name = Khach hang mot da doi ten; phone = 0987654321 | G24: 1. Gửi GET /api/users/me 2. Gửi PUT /api/users/me 3. Truy vấn bảng users | H24: Mã 200 ở cả hai yêu cầu; họ tên và số điện thoại mới được lưu (bước 5) | I24: Positive | J24: Cao | K24: Tự động | L24: Cả hai yêu cầu trả mã 200; cột name và phone mang đúng giá trị mới. Phần hiển thị sau khi tải lại trang chưa kiểm chứng | M24: Pass | N24: Jest + Supertest | O24: 25/09/2026 | P24: Mức kiểm chứng hạn chế: phần giao diện hoặc thời gian thực chưa kiểm chứng (Bảng 3.37, dòng 4)
A25: AUTH-024 | B25: Xác thực và phân quyền | C25: UC04 | D25: Đổi mật khẩu với mật khẩu hiện tại không đúng | E25: customer2 đã đăng nhập | F25: currentPassword = SaiMatKhauCu; newPassword = MatKhauMoi@123 | G25: 1. Gửi PUT /api/users/me/change-password 2. So sánh cột password trước và sau | H25: Mã 401, thông báo Mật khẩu hiện tại không đúng; cột password không thay đổi (ngoại lệ 3a) | I25: Security | J25: Cao | K25: Tự động | L25: Yêu cầu bị từ chối (kịch bản kiểm tra mã từ 400 trở lên); cột password giữ nguyên. Kịch bản AUTH-024b xác nhận mật khẩu mới dưới 6 ký tự bị từ chối với mã 400 | M25: Pass | N25: Jest + Supertest | O25: 25/09/2026 | P25: Mức kiểm chứng hạn chế: chỉ kiểm tra mã trạng thái (Bảng 3.37, dòng 1)
A26: AUTH-025 | B26: Xác thực và phân quyền | C26: UC04 | D26: Cập nhật ảnh đại diện | E26: Người dùng đã đăng nhập | F26: avatar.png dung lượng 500 KB | G26: 1. Mở trang Hồ sơ 2. Chọn ảnh mới 3. Nhấn Tải lên | H26: Ảnh được lưu vào thư mục uploads, cột avatar được cập nhật, ảnh mới hiển thị trên thanh điều hướng | I26: Positive | J26: Trung bình | K26: Tự động | L26: Chưa có kết quả đủ tin cậy; kịch bản USR-007 có gọi POST /api/users/me/avatar nhưng tự bỏ qua bước kiểm tra khi máy chủ trả lỗi | M26: Chưa thực hiện | P26: Lý do: kịch bản hiện có chưa đủ tin cậy làm bằng chứng (Bảng 3.38, dòng 2)
A27: PROD-001 | B27: Quản lý sản phẩm và tồn kho | C27: UC05 | D27: Xem danh sách sản phẩm khi chưa đăng nhập | E27: Dữ liệu mẫu có 18 sản phẩm active và 3 sản phẩm pending | F27: Không gửi token | G27: 1. Gửi GET /api/products 2. Đối chiếu với các sản phẩm có status khác active hoặc đã xóa mềm | H27: Mã 200; chỉ có sản phẩm status = active và chưa bị xóa mềm (bước 2) | I27: Positive | J27: Cao | K27: Tự động | L27: Mã 200; không mã sản phẩm pending hay đã xóa mềm nào xuất hiện trong danh sách | M27: Pass | N27: Jest + Supertest | O27: 25/09/2026
A28: PROD-002 | B28: Quản lý sản phẩm và tồn kho | C28: UC05 | D28: Lọc sản phẩm theo danh mục | E28: 4 danh mục đều có sản phẩm | F28: Danh mục đầu tiên có product_count lớn hơn 0 | G28: 1. Gửi GET /api/categories 2. Gửi GET /api/products và lọc theo tên danh mục 3. Đếm trực tiếp trong cơ sở dữ liệu | H28: Chỉ còn sản phẩm thuộc danh mục đã chọn; số lượng khớp số sản phẩm của danh mục (bước 3) | I28: Positive | J28: Cao | K28: Tự động | L28: Số sản phẩm sau khi lọc bằng số đếm trong cơ sở dữ liệu. Thao tác lọc do Shop.js thực hiện trên trình duyệt nên phần hiển thị chưa kiểm chứng | M28: Pass | N28: Jest + Supertest | O28: 25/09/2026 | P28: Mức kiểm chứng hạn chế: phần giao diện hoặc thời gian thực chưa kiểm chứng (Bảng 3.37, dòng 4)
A29: PROD-003 | B29: Quản lý sản phẩm và tồn kho | C29: UC05 | D29: Tìm kiếm theo từ khóa có kết quả | E29: Có sản phẩm tên chứa từ khóa | F29: keyword = Kiem Thu | G29: 1. Nhập từ khóa vào ô tìm kiếm 2. Nhấn tìm kiếm | H29: Hiển thị đúng các sản phẩm có tên chứa từ khóa, không phân biệt chữ hoa và chữ thường (bước 3) | I29: Positive | J29: Trung bình | K29: Tự động | L29: Chưa có kết quả; tìm kiếm là bộ lọc trên trình duyệt trong Shop.js, máy chủ không nhận tham số tìm kiếm | M29: Chưa thực hiện | P29: Lý do: chức năng nằm hoàn toàn ở giao diện, thuộc giai đoạn 6 chưa triển khai (Bảng 3.38, dòng 1)
A30: PROD-004 | B30: Quản lý sản phẩm và tồn kho | C30: UC05 | D30: Tìm kiếm với từ khóa không khớp sản phẩm nào | E30: Đang ở trang danh sách sản phẩm | F30: keyword = zzzzzzzz | G30: 1. Nhập từ khóa 2. Nhấn tìm kiếm | H30: Hiển thị thông báo không tìm thấy, không báo lỗi hệ thống (ngoại lệ 3a) | I30: Negative | J30: Trung bình | K30: Tự động | L30: Chưa có kết quả; cùng lý do với PROD-003 | M30: Chưa thực hiện | P30: Lý do: chức năng nằm hoàn toàn ở giao diện, thuộc giai đoạn 6 chưa triển khai (Bảng 3.38, dòng 1)
A31: PROD-005 | B31: Quản lý sản phẩm và tồn kho | C31: UC05 | D31: Xem chi tiết sản phẩm hợp lệ | E31: Tồn tại sản phẩm có id xác định | F31: Mã của sản phẩm đầu tiên trong danh sách công khai | G31: 1. Gửi GET /api/products/:id | H31: Mã 200; đủ tên, giá, giá gốc, mô tả, ảnh, tồn kho, danh sách biến thể và đánh giá (bước 5) | I31: Positive | J31: Cao | K31: Tự động | L31: Mã 200; có các trường id, name, price, stock. Các trường còn lại chưa được kịch bản kiểm tra | M31: Pass | N31: Jest + Supertest | O31: 25/09/2026 | P31: Mức kiểm chứng hạn chế: chỉ kiểm tra một phần kết quả mong đợi (Bảng 3.37, dòng 2)
A32: PROD-006 | B32: Quản lý sản phẩm và tồn kho | C32: UC05 | D32: Xem chi tiết sản phẩm với mã không tồn tại | E32: Máy chủ đang chạy | F32: productId = 999999 | G32: 1. Gửi GET /api/products/999999 | H32: Mã 404, không trả lỗi 500 (ngoại lệ 4a) | I32: Negative | J32: Trung bình | K32: Tự động | L32: Mã 404 | M32: Pass | N32: Jest + Supertest | O32: 25/09/2026
A33: PROD-007 | B33: Quản lý sản phẩm và tồn kho | C33: UC05 | D33: Xem danh sách biến thể | E33: 3 sản phẩm đầu có biến thể Size S, M, L | F33: Mã của một sản phẩm có biến thể | G33: 1. Gửi GET /api/variants/product/:id | H33: Mã 200; mỗi biến thể có tên, giá và tồn kho riêng | I33: Positive | J33: Cao | K33: Tự động | L33: Mã 200; danh sách có biến thể, bản ghi đầu có đủ variant_name, price, stock | M33: Pass | N33: Jest + Supertest | O33: 25/09/2026
A34: PROD-008 | B34: Quản lý sản phẩm và tồn kho | C34: UC12 | D34: Quản lý thêm sản phẩm mới hợp lệ | E34: Đăng nhập manager@tigershop.test | F34: name = SP cua Manager [thời điểm]; price = 250000; stock = 50; ảnh PNG hợp lệ | G34: 1. Gửi POST /api/products dạng multipart 2. Truy vấn status và manager_id của sản phẩm mới | H34: Mã 200; sản phẩm có status = pending và manager_id là người tạo; chưa hiển thị trên gian hàng cho tới khi được duyệt (bước 5, hậu điều kiện UC12) | I34: Positive | J34: Cao | K34: Tự động | L34: Mã 200; sản phẩm có status = active ngay khi tạo, tức là lên gian hàng mà không qua bước duyệt | M34: Fail | N34: Jest + Supertest | O34: 25/09/2026 | P34: Khiếm khuyết DEF-02, mức Cao (Bảng 3.36); kịch bản PROD-008b ghi nhận thêm DEF-03
A35: PROD-009 | B35: Quản lý sản phẩm và tồn kho | C35: UC12 | D35: Thêm sản phẩm khi bỏ trống tên và giá | E35: Đăng nhập Quản lý | F35: name rỗng; price rỗng | G35: 1. Gửi POST /api/products | H35: Mã 400, thông báo Thiếu thông tin sản phẩm (ngoại lệ 2a) | I35: Negative | J35: Cao | K35: Tự động | L35: Mã 400, Thiếu thông tin sản phẩm | M35: Pass | N35: Jest + Supertest | O35: 25/09/2026
A36: PROD-010 | B36: Quản lý sản phẩm và tồn kho | C36: UC12 | D36: Tải lên tệp sai định dạng | E36: Đăng nhập Quản lý | F36: tailieu.pdf | G36: 1. Gửi POST /api/products kèm tệp pdf ở trường image | H36: Từ chối tải lên, chỉ chấp nhận jpg, jpeg, png, webp (ngoại lệ 3a) | I36: Security | J36: Cao | K36: Tự động | L36: Yêu cầu bị từ chối (kịch bản chỉ kiểm tra mã từ 400 trở lên); bộ lọc fileFilter trong productRoutes.js chặn tệp trước khi ghi đĩa | M36: Pass | N36: Jest + Supertest | O36: 25/09/2026 | P36: Mức kiểm chứng hạn chế: chỉ kiểm tra mã trạng thái (Bảng 3.37, dòng 1)
A37: PROD-011 | B37: Quản lý sản phẩm và tồn kho | C37: UC12 | D37: Tải lên ảnh vượt giới hạn dung lượng | E37: Đăng nhập Quản lý | F37: anh_lon.jpg dung lượng 6 MB | G37: 1. Gửi POST /api/products kèm tệp | H37: Từ chối tải lên vì vượt giới hạn 5 MB (ngoại lệ 3a) | I37: Boundary | J37: Cao | K37: Tự động | L37: Yêu cầu bị từ chối (kịch bản chỉ kiểm tra mã từ 400 trở lên) | M37: Pass | N37: Jest + Supertest | O37: 25/09/2026 | P37: Mức kiểm chứng hạn chế: chỉ kiểm tra mã trạng thái (Bảng 3.37, dòng 1)
A38: PROD-012 | B38: Quản lý sản phẩm và tồn kho | C38: UC12 | D38: Cập nhật thông tin sản phẩm | E38: Đăng nhập Quản lý | F38: price = 299000; stock = 80 | G38: 1. Gửi PUT /api/products/:id 2. Truy vấn price và stock | H38: Mã 200; giá và tồn kho được cập nhật đúng (bước 7) | I38: Positive | J38: Cao | K38: Tự động | L38: Mã 200; price = 299000, stock = 80 | M38: Pass | N38: Jest + Supertest | O38: 25/09/2026
A39: PROD-013 | B39: Quản lý sản phẩm và tồn kho | C39: UC12 | D39: Xóa mềm và khôi phục sản phẩm | E39: Sản phẩm đang active | F39: Mã của một sản phẩm active | G39: 1. Gửi DELETE /api/products/:id 2. Gửi GET /api/products 3. Gửi PATCH /api/products/:id/restore | H39: Sau khi xóa: deleted_at có giá trị, sản phẩm biến mất khỏi gian hàng. Sau khi khôi phục: deleted_at trở về NULL (ngoại lệ 7b) | I39: Positive | J39: Cao | K39: Tự động | L39: Cả hai thao tác trả mã 200; deleted_at có giá trị rồi trở về NULL; trong khoảng giữa, sản phẩm không có trong danh sách công khai | M39: Pass | N39: Jest + Supertest | O39: 25/09/2026
A40: PROD-014 | B40: Quản lý sản phẩm và tồn kho | C40: UC12 | D40: Thêm biến thể cho sản phẩm | E40: Đăng nhập Quản lý | F40: variant_name = Size XL mau do; price = 270000; stock = 20 | G40: 1. Gửi POST /api/variants 2. Truy vấn product_variants | H40: Mã 200, thông báo Thêm variant thành công; bản ghi biến thể được tạo (bước 6) | I40: Positive | J40: Cao | K40: Tự động | L40: Mã 200, Thêm variant thành công; bản ghi có stock = 20 | M40: Pass | N40: Jest + Supertest | O40: 25/09/2026
A41: PROD-015 | B41: Quản lý sản phẩm và tồn kho | C41: UC12 | D41: Thêm biến thể khi thiếu dữ liệu bắt buộc | E41: Đăng nhập bằng tài khoản MANAGER | F41: variant_name rỗng; price rỗng | G41: 1. Gửi POST /api/variants | H41: Mã 400, thông báo Thiếu dữ liệu variant (ngoại lệ 6a) | I41: Negative | J41: Trung bình | K41: Tự động | L41: Mã 400, Thiếu dữ liệu variant | M41: Pass | N41: Jest + Supertest | O41: 25/09/2026
A42: PROD-016 | B42: Quản lý sản phẩm và tồn kho | C42: UC12 | D42: Cập nhật tồn kho hàng loạt | E42: Sản phẩm có 3 biến thể | F42: Mảng updates gồm 3 cặp mã biến thể và tồn kho mới 5, 10, 15 | G42: 1. Gửi PUT /api/variants/bulk-stock 2. Truy vấn tồn kho các biến thể | H42: Cả 3 biến thể được cập nhật đúng; tổng tồn kho của sản phẩm cha được tính lại chính xác (ngoại lệ 7c) | I42: Positive | J42: Trung bình | K42: Tự động | L42: Mã 200; tồn kho 3 biến thể lần lượt đúng 5, 10, 15. Tổng tồn kho của sản phẩm cha chưa được kịch bản đối chiếu | M42: Pass | N42: Jest + Supertest | O42: 25/09/2026 | P42: Mức kiểm chứng hạn chế: chỉ kiểm tra một phần kết quả mong đợi (Bảng 3.37, dòng 2)
A43: PROD-017 | B43: Quản lý sản phẩm và tồn kho | C43: UC13 | D43: Quản trị viên duyệt sản phẩm chờ | E43: Có sản phẩm pending; đăng nhập admin@tigershop.test | F43: status = active | G43: 1. Gửi PATCH /api/products/:id/decision 2. Truy vấn products và user_activity_logs | H43: status chuyển thành active; sản phẩm xuất hiện trên gian hàng; nhật ký ghi lại quyết định (bước 4, 5) | I43: Positive | J43: Cao | K43: Tự động | L43: Mã 200; status = active; user_activity_logs có bản ghi mới chứa nội dung Duyệt sản phẩm | M43: Pass | N43: Jest + Supertest | O43: 25/09/2026
A44: PROD-018 | B44: Quản lý sản phẩm và tồn kho | C44: UC13 | D44: Quản trị viên từ chối sản phẩm kèm lý do | E44: Có sản phẩm pending | F44: status = hidden; reason = Anh san pham khong dat chuan | G44: 1. Gửi PATCH /api/products/:id/decision 2. Truy vấn status và rejection_reason | H44: status chuyển thành hidden và rejection_reason lưu đúng lý do (ngoại lệ 3a) | I44: Positive | J44: Cao | K44: Tự động | L44: Mã 200; status = hidden; rejection_reason đúng nội dung. Kịch bản PROD-018b xác nhận giá trị nằm ngoài active và hidden bị từ chối với mã 400, Trạng thái không hợp lệ (ngoại lệ 3b) | M44: Pass | N44: Jest + Supertest | O44: 25/09/2026
A45: PROD-019 | B45: Quản lý sản phẩm và tồn kho | C45: UC13 | D45: Nhân viên cố gọi điểm cuối duyệt sản phẩm | E45: Đăng nhập bằng tài khoản STAFF | F45: token của staff@tigershop.test | G45: 1. Gửi PATCH /api/products/:id/decision | H45: Mã 403 (ngoại lệ 1a) | I45: Security | J45: Cao | K45: Tự động | L45: Mã 403 | M45: Pass | N45: Jest + Supertest | O45: 25/09/2026
A46: PROD-020 | B46: Quản lý sản phẩm và tồn kho | C46: UC13 | D46: Đưa sản phẩm đã bị từ chối trở lại hàng đợi duyệt | E46: Có sản phẩm status = hidden | F46: Mã của sản phẩm bị từ chối | G46: 1. Mở danh sách sản phẩm đã quyết định 2. Chọn sản phẩm 3. Nhấn Gửi duyệt lại | H46: status trở về pending, rejection_reason bị xóa, sản phẩm xuất hiện lại trong danh sách chờ (ngoại lệ 6a) | I46: Positive | J46: Trung bình | K46: Tự động | L46: Chưa có kết quả; điểm cuối PATCH /api/products/:id/restore-pending thuộc 14 điểm cuối chưa được bộ kiểm thử gọi tới (Bảng 2.13) | M46: Chưa thực hiện | P46: Lý do: có thể kiểm thử ở mức API nhưng chưa có kịch bản (Bảng 3.38, dòng 5)
A47: PROD-021 | B47: Quản lý sản phẩm và tồn kho | C47: UC14 | D47: Xem cảnh báo tồn kho thấp | E47: Dữ liệu mẫu có 3 sản phẩm tồn kho 3, 2 và 1 | F47: token của manager@tigershop.test | G47: 1. Gửi GET /api/products/inventory-alert | H47: Danh sách sản phẩm chưa bị xóa có tồn kho dưới 5, sắp xếp tăng dần (bước 2), kèm số sản phẩm trong thùng rác | I47: Positive | J47: Cao | K47: Tự động | L47: Mã 200; mọi mục đều có stock dưới 5 và theo thứ tự tăng dần. Số sản phẩm trong thùng rác chưa được kiểm tra | M47: Pass | N47: Jest + Supertest | O47: 25/09/2026 | P47: Mức kiểm chứng hạn chế: chỉ kiểm tra một phần kết quả mong đợi (Bảng 3.37, dòng 2)
A48: PROD-022 | B48: Quản lý sản phẩm và tồn kho | C48: UC14 | D48: Nhập thêm hàng và kiểm tra nhật ký kho | E48: Đăng nhập Quản lý | F48: quantity = 50; note = Nhap bo sung | G48: 1. Gửi POST /api/users/inventory/restock 2. Truy vấn stock 3. Truy vấn inventory_logs | H48: Tồn kho tăng đúng 50; inventory_logs ghi old_stock, new_stock, quantity_added và manager_id (hậu điều kiện UC14) | I48: Positive | J48: Cao | K48: Tự động | L48: Tồn kho tăng đúng 50 so với giá trị ban đầu; bản ghi inventory_logs có old_stock, new_stock và quantity_added = 50 đúng. Cột manager_id chưa được kiểm tra | M48: Pass | N48: Jest + Supertest | O48: 25/09/2026 | P48: Mức kiểm chứng hạn chế: chỉ kiểm tra một phần kết quả mong đợi (Bảng 3.37, dòng 2)
A49: ORD-001 | B49: Giỏ hàng và đơn hàng | C49: UC06 | D49: Thêm sản phẩm không có biến thể vào giỏ | E49: customer1 đã đăng nhập, sản phẩm còn hàng | F49: quantity = 2 | G49: 1. Mở trang chi tiết sản phẩm 2. Nhập số lượng 2 3. Nhấn Thêm vào giỏ | H49: Sản phẩm có trong giỏ với đúng số lượng; biểu tượng giỏ hàng cập nhật (bước 3) | I49: Positive | J49: Cao | K49: Tự động | L49: Chưa có kết quả | M49: Chưa thực hiện | P49: Lý do: chức năng nằm hoàn toàn ở giao diện, thuộc giai đoạn 6 chưa triển khai (Bảng 3.38, dòng 1)
A50: ORD-002 | B50: Giỏ hàng và đơn hàng | C50: UC06 | D50: Thêm sản phẩm có biến thể nhưng chưa chọn biến thể | E50: Sản phẩm có Size S, M, L | F50: Không chọn biến thể | G50: 1. Mở trang chi tiết 2. Nhấn Thêm vào giỏ | H50: Hiển thị cảnh báo; không thêm vào giỏ (ngoại lệ 1a) | I50: Negative | J50: Cao | K50: Tự động | L50: Chưa có kết quả | M50: Chưa thực hiện | P50: Lý do: chức năng nằm hoàn toàn ở giao diện, thuộc giai đoạn 6 chưa triển khai (Bảng 3.38, dòng 1)
A51: ORD-003 | B51: Giỏ hàng và đơn hàng | C51: UC06 | D51: Thêm số lượng vượt tồn kho | E51: San pham ton kho thap A còn 3 | F51: quantity = 10 | G51: 1. Nhập số lượng 10 2. Nhấn Thêm vào giỏ | H51: Cảnh báo và giới hạn số lượng theo tồn kho là 3 (ngoại lệ 2a) | I51: Boundary | J51: Cao | K51: Tự động | L51: Chưa có kết quả | M51: Chưa thực hiện | P51: Lý do: chức năng nằm hoàn toàn ở giao diện, thuộc giai đoạn 6 chưa triển khai (Bảng 3.38, dòng 1)
A52: ORD-004 | B52: Giỏ hàng và đơn hàng | C52: UC06 | D52: Nhập số lượng bằng 0 hoặc số âm | E52: Đang ở trang chi tiết sản phẩm | F52: quantity = 0; quantity = -1 | G52: 1. Nhập 0 rồi nhập -1 2. Nhấn Thêm vào giỏ | H52: Không cho phép thêm (ngoại lệ 2b) | I52: Boundary | J52: Trung bình | K52: Tự động | L52: Chưa có kết quả | M52: Chưa thực hiện | P52: Lý do: chức năng nằm hoàn toàn ở giao diện, thuộc giai đoạn 6 chưa triển khai (Bảng 3.38, dòng 1)
A53: ORD-005 | B53: Giỏ hàng và đơn hàng | C53: UC06 | D53: Cập nhật số lượng và xóa mục trong giỏ | E53: Giỏ có 2 mục | F53: Mục thứ nhất đổi thành 3; xóa mục thứ hai | G53: 1. Mở trang /cart 2. Tăng số lượng mục thứ nhất 3. Xóa mục thứ hai | H53: Tổng tiền tạm tính được tính lại đúng sau mỗi thao tác; mục bị xóa biến mất (bước 4, 5) | I53: Positive | J53: Cao | K53: Tự động | L53: Chưa có kết quả | M53: Chưa thực hiện | P53: Lý do: chức năng nằm hoàn toàn ở giao diện, thuộc giai đoạn 6 chưa triển khai (Bảng 3.38, dòng 1)
A54: ORD-006 | B54: Giỏ hàng và đơn hàng | C54: UC07 | D54: Đặt hàng thành công với COD | E54: customer1 đã đăng nhập; sản phẩm tồn kho 50 | F54: 2 sản phẩm; shipping_address = 123 Nguyen Trai, Ha Noi; payment_method = cod | G54: 1. Gửi POST /api/orders 2. Truy vấn tồn kho và bản ghi orders | H54: Mã 200 kèm orderId; đơn ở trạng thái pending với ngày giao dự kiến sau ba ngày; tồn kho giảm 2 (hậu điều kiện UC07) | I54: Positive | J54: Cao | K54: Tự động | L54: Mã 200, success = true, có orderId; expected_delivery đúng định dạng YYYY-MM-DD; status = pending, payment_method = cod; tồn kho giảm đúng 2. Giá trị cụ thể của ngày giao dự kiến chưa được đối chiếu | M54: Pass | N54: Jest + Supertest | O54: 25/09/2026 | P54: Mức kiểm chứng hạn chế: chỉ kiểm tra một phần kết quả mong đợi (Bảng 3.37, dòng 2)
A55: ORD-007 | B55: Giỏ hàng và đơn hàng | C55: UC07 | D55: Đặt hàng thành công với chuyển khoản QR | E55: Giỏ hàng có sản phẩm, đã đăng nhập | F55: payment_method = qr | G55: 1. Gửi POST /api/orders 2. Truy vấn orders | H55: Đơn có payment_method = qr; hội thoại hỗ trợ có thêm tin nhắn hệ thống (bước 4, 11) | I55: Positive | J55: Cao | K55: Tự động | L55: Mã 200; payment_method = qr. Tin nhắn hệ thống trong hội thoại chưa được kiểm tra | M55: Pass | N55: Jest + Supertest | O55: 25/09/2026 | P55: Mức kiểm chứng hạn chế: chỉ kiểm tra một phần kết quả mong đợi (Bảng 3.37, dòng 2)
A56: ORD-008 | B56: Giỏ hàng và đơn hàng | C56: UC07 | D56: Đặt hàng khi giỏ rỗng | E56: Đã đăng nhập, giỏ hàng không có sản phẩm | F56: items = mảng rỗng | G56: 1. Gửi POST /api/orders | H56: Mã 400, thông báo Giỏ hàng trống (ngoại lệ 7a) | I56: Negative | J56: Cao | K56: Tự động | L56: Mã 400, Giỏ hàng trống | M56: Pass | N56: Jest + Supertest | O56: 25/09/2026
A57: ORD-009 | B57: Giỏ hàng và đơn hàng | C57: UC07 | D57: Đặt hàng khi bỏ trống địa chỉ | E57: Giỏ hàng có sản phẩm | F57: shipping_address chỉ gồm khoảng trắng | G57: 1. Gửi POST /api/orders | H57: Mã 400, thông báo thiếu địa chỉ nhận hàng (ngoại lệ 7c) | I57: Negative | J57: Cao | K57: Tự động | L57: Mã 400, Thiếu địa chỉ nhận hàng | M57: Pass | N57: Jest + Supertest | O57: 25/09/2026
A58: ORD-010 | B58: Giỏ hàng và đơn hàng | C58: UC07 | D58: Đặt hàng với tổng tiền không hợp lệ | E58: Đã đăng nhập | F58: total = -50000; total = abc | G58: 1. Gửi với tổng tiền âm 2. Gửi với tổng tiền không phải số | H58: Cả hai trả mã 400 (ngoại lệ 7b) | I58: Negative | J58: Cao | K58: Tự động | L58: Cả hai trả mã 400, Tổng tiền không hợp lệ | M58: Pass | N58: Jest + Supertest | O58: 25/09/2026
A59: ORD-011 | B59: Giỏ hàng và đơn hàng | C59: UC07 | D59: Đặt hàng khi không gửi token | E59: Máy chủ đang chạy | F59: Không có header Authorization | G59: 1. Gửi POST /api/orders 2. Đếm số đơn trước và sau | H59: Mã 401; không tạo đơn (ngoại lệ 6a) | I59: Security | J59: Cao | K59: Tự động | L59: Mã 401; số đơn trong bảng orders không đổi | M59: Pass | N59: Jest + Supertest | O59: 25/09/2026
A60: ORD-012 | B60: Giỏ hàng và đơn hàng | C60: UC07 | D60: Đặt hàng vượt tồn kho | E60: San pham chi con mot cai có tồn kho 1 | F60: quantity = 5 | G60: 1. Gửi POST /api/orders 2. Kiểm tra orders, order_items và products | H60: Hoàn tác toàn bộ giao dịch, báo Hết hàng; không tạo orders và order_items; tồn kho giữ nguyên 1 (ngoại lệ 9a) | I60: Boundary | J60: Cao | K60: Tự động | L60: Mã 500, thông báo chứa Hết hàng; tồn kho vẫn là 1; không phát sinh bản ghi orders và order_items | M60: Pass | N60: Jest + Supertest | O60: 25/09/2026 | P60: Đề xuất trả mã 409 cho lỗi nghiệp vụ (mục 3.5.2)
A61: ORD-013 | B61: Giỏ hàng và đơn hàng | C61: UC07 | D61: Tính nguyên tử của giao dịch đặt hàng | E61: Đơn hàng gồm 2 sản phẩm, sản phẩm thứ hai không đủ tồn kho | F61: Mục 1: 1 sản phẩm còn 50; mục 2: 99 sản phẩm chỉ còn 1; total = 1000 | G61: 1. Gửi đơn gồm hai mục 2. Kiểm tra tồn kho của mục 1 và số đơn | H61: Toàn bộ giao dịch bị hoàn tác; tồn kho mục 1 không bị trừ dù đã được xử lý trước (ngoại lệ 9a) | I61: Negative | J61: Cao | K61: Tự động | L61: Mã 500; tồn kho mục 1 giữ nguyên; số đơn không đổi | M61: Pass | N61: Jest + Supertest | O61: 25/09/2026 | P61: Đề xuất trả mã 409 cho lỗi nghiệp vụ (mục 3.5.2)
A62: ORD-014 | B62: Giỏ hàng và đơn hàng | C62: UC07 | D62: Hai yêu cầu đồng thời cho sản phẩm tồn kho thấp | E62: Đặt lại tồn kho bằng 1 | F62: customer1 và customer2 cùng đặt 1 sản phẩm | G62: 1. Gửi đồng thời hai yêu cầu bằng Promise.all 2. Kiểm tra kết quả và tồn kho | H62: Chỉ một yêu cầu thành công; tồn kho về 0 và không âm, nhờ câu lệnh cập nhật có điều kiện stock lớn hơn hoặc bằng số lượng (bước 9) | I62: Boundary | J62: Cao | K62: Thủ công | L62: Đúng một yêu cầu trả mã 200; tồn kho bằng 0 | M62: Pass | N62: Jest + Supertest | O62: 25/09/2026 | P62: Thiết kế thủ công, đã thực hiện bằng kịch bản Jest (Bảng 3.4)
A63: ORD-015 | B63: Giỏ hàng và đơn hàng | C63: UC07 | D63: Tin nhắn hệ thống sau khi đặt hàng thành công | E63: Vừa đặt hàng thành công | F63: orderId vừa tạo | G63: 1. Đặt hàng 2. Mở hộp thoại hỗ trợ | H63: Hội thoại có tin nhắn hệ thống chứa mã đơn, tổng tiền, phương thức thanh toán; sự kiện new_message được phát (bước 11) | I63: Positive | J63: Trung bình | K63: Thủ công | L63: Chưa có kết quả; cần quan sát sự kiện thời gian thực trên trình duyệt | M63: Chưa thực hiện | P63: Lý do: cần hai phiên trình duyệt và sự kiện Socket.IO (rủi ro R08) (Bảng 3.38, dòng 3)
A64: ORD-016 | B64: Giỏ hàng và đơn hàng | C64: UC08 | D64: Xem danh sách đơn hàng của chính mình | E64: customer1 có 5 đơn mẫu và các đơn tạo trong lượt chạy | F64: token của customer1 | G64: 1. Gửi GET /api/orders/my 2. So với các đơn của customer1 trong cơ sở dữ liệu | H64: Mã 200; đủ các đơn của chính khách hàng, theo thời gian giảm dần (bước 2) | I64: Positive | J64: Cao | K64: Tự động | L64: Mã 200; tập orderId trả về trùng khớp tập đơn của customer1. Thứ tự sắp xếp chưa được kiểm tra | M64: Pass | N64: Jest + Supertest | O64: 25/09/2026 | P64: Mức kiểm chứng hạn chế: chỉ kiểm tra một phần kết quả mong đợi (Bảng 3.37, dòng 2)
A65: ORD-017 | B65: Giỏ hàng và đơn hàng | C65: UC08 | D65: Xem chi tiết đơn hàng | E65: Đơn thuộc về người dùng | F65: orderId của customer1 | G65: 1. Nhấn vào một đơn trong danh sách | H65: Trang /orders/:id hiển thị người nhận, mặt hàng, tổng tiền, phương thức thanh toán, trạng thái và ngày giao dự kiến (bước 4) | I65: Positive | J65: Cao | K65: Tự động | L65: Chưa có kết quả; kết quả mong đợi là nội dung hiển thị trên trang chi tiết đơn | M65: Chưa thực hiện | P65: Lý do: chức năng nằm hoàn toàn ở giao diện, thuộc giai đoạn 6 chưa triển khai (Bảng 3.38, dòng 1)
A66: ORD-018 | B66: Giỏ hàng và đơn hàng | C66: UC08 | D66: Truy cập đơn hàng của người dùng khác | E66: customer2 có đơn | F66: token của customer1; orderId của customer2 | G66: 1. Gửi GET /api/orders/:id | H66: Không trả dữ liệu đơn, trả mã 404 (ngoại lệ 3a) | I66: Security | J66: Cao | K66: Tự động | L66: Kịch bản chấp nhận mã 403 hoặc 404 và đạt; kịch bản tự bỏ qua bước kiểm tra nếu customer2 chưa có đơn, điều này phụ thuộc bên thắng ở ORD-014. Rà soát getOrderDetail xác nhận truy vấn lọc theo cả id và user_id, nên đơn của người khác nhận mã 404 | M66: Pass | N66: Jest + Supertest | O66: 25/09/2026 | P66: Mức kiểm chứng hạn chế: kịch bản có nhánh tự bỏ qua bước kiểm tra (Bảng 3.37, dòng 3)
A67: ORD-019 | B67: Giỏ hàng và đơn hàng | C67: UC08 | D67: Khách hàng hủy đơn đang pending | E67: Đơn hàng có status = pending thuộc về người dùng | F67: Đơn mới đặt gồm 2 sản phẩm | G67: 1. Đặt đơn 2. Gửi POST /api/orders/:id/cancel 3. Kiểm tra status và tồn kho | H67: Đơn chuyển sang cancelled; tồn kho được hoàn trả đúng số lượng (ngoại lệ 4a) | I67: Positive | J67: Cao | K67: Tự động | L67: Mã 200; status = cancelled; tồn kho tăng lại đúng 2 | M67: Pass | N67: Jest + Supertest | O67: 25/09/2026
A68: ORD-020 | B68: Giỏ hàng và đơn hàng | C68: UC08 | D68: Hủy đơn đã hoàn tất | E68: Đơn completed trong dữ liệu mẫu | F68: reason = Khach doi tra (cho nhân viên) | G68: 1. Khách hàng gửi POST /api/orders/:id/cancel 2. Nhân viên gửi POST /api/orders/staff/:id/cancel | H68: Cả hai bị từ chối; đơn giữ trạng thái completed (UC08 ngoại lệ 4b, UC11 ngoại lệ 4b) | I68: Negative | J68: Cao | K68: Tự động | L68: Khách hàng: mã 400, Chỉ có thể hủy đơn hàng ở trạng thái Pending. Nhân viên (kịch bản ORD-020b): mã 400, Không thể hủy đơn hàng đã completed. Đơn vẫn là completed | M68: Pass | N68: Jest + Supertest | O68: 25/09/2026
A69: ORD-021 | B69: Giỏ hàng và đơn hàng | C69: UC11 | D69: Nhân viên hủy đơn mà không nhập lý do | E69: staff@tigershop.test; có đơn pending | F69: reason rỗng | G69: 1. Gửi POST /api/orders/staff/:id/cancel | H69: Từ chối hủy đơn vì bỏ trống lý do (ngoại lệ 4b) | I69: Negative | J69: Cao | K69: Tự động | L69: Mã 400, Staff phải nhập lý do hủy đơn | M69: Pass | N69: Jest + Supertest | O69: 25/09/2026
A70: ORD-022 | B70: Giỏ hàng và đơn hàng | C70: UC11 | D70: Cập nhật trạng thái đơn theo tiến trình | E70: staff@tigershop.test; có đơn pending | F70: Lần lượt confirmed, shipping, completed; sau đó một giá trị nằm ngoài tập trạng thái | G70: 1. Gửi PUT /api/orders/admin/:id/status qua từng bước 2. Kiểm tra user_activity_logs 3. Gửi giá trị không hợp lệ | H70: Mỗi bước hợp lệ đều thành công, ghi người xử lý và nhật ký thao tác (bước 4, 5); giá trị nằm ngoài năm trạng thái hợp lệ hoặc đi ngược tiến trình bị từ chối (ngoại lệ 4a) | I70: Positive | J70: Cao | K70: Tự động | L70: Kịch bản STAT trong category_stats.test.js gửi giá trị processing bằng token nhân viên: máy chủ trả mã thành công và cột status nhận giá trị processing. Bước (1) và (2) chưa có kịch bản riêng | M70: Fail | N70: Jest + Supertest | O70: 25/09/2026 | P70: Khiếm khuyết DEF-11, mức Trung bình (Bảng 3.36); bằng chứng từ kịch bản nhóm STAT trong category_stats.test.js
A71: VOUC-001 | B71: Voucher và ví voucher | C71: UC10 | D71: Quản lý tạo voucher giảm theo phần trăm | E71: Đăng nhập manager@tigershop.test | F71: code = SALE[số ngẫu nhiên]; type = percent; value = 20; min_order_value = 200000; max_discount = 50000; quantity = 100; hiệu lực từ 01/01/2026 đến 31/12/2030 | G71: 1. Gửi POST /api/vouchers 2. Truy vấn bảng vouchers | H71: Voucher được tạo với status = active và used = 0 (bước 1) | I71: Positive | J71: Cao | K71: Tự động | L71: Yêu cầu thành công; đúng một bản ghi với status = active, used = 0 | M71: Pass | N71: Jest + Supertest | O71: 25/09/2026
A72: VOUC-002 | B72: Voucher và ví voucher | C72: UC10 | D72: Tạo voucher với mã đã tồn tại | E72: SALE20 có sẵn trong dữ liệu mẫu | F72: code = SALE20 | G72: 1. Gửi POST /api/vouchers 2. Đếm bản ghi có mã SALE20 | H72: Từ chối tạo; không có bản ghi thứ hai (ngoại lệ 1a) | I72: Negative | J72: Trung bình | K72: Tự động | L72: Yêu cầu bị từ chối (kịch bản kiểm tra mã từ 400 trở lên); vẫn chỉ có một bản ghi SALE20 | M72: Pass | N72: Jest + Supertest | O72: 25/09/2026 | P72: Mức kiểm chứng hạn chế: chỉ kiểm tra mã trạng thái (Bảng 3.37, dòng 1)
A73: VOUC-003 | B73: Voucher và ví voucher | C73: UC10 | D73: Khách hàng xem danh sách voucher công khai | E73: Tồn tại voucher active còn hiệu lực | F73: token của customer1 | G73: 1. Gửi GET /api/vouchers/public | H73: Chỉ gồm voucher đang hoạt động, còn hạn và còn lượt (bước 2) | I73: Positive | J73: Cao | K73: Tự động | L73: Mã 200; danh sách không chứa HETHAN (hết hạn) và HETLUOT (hết lượt) | M73: Pass | N73: Jest + Supertest | O73: 25/09/2026
A74: VOUC-004 | B74: Voucher và ví voucher | C74: UC10 | D74: Khách hàng nhận voucher vào ví | E74: customer2 chưa có GIAM50K | F74: voucherId của GIAM50K | G74: 1. Gửi POST /api/user-vouchers/receive/:voucherId 2. Truy vấn user_vouchers | H74: Bản ghi user_vouchers được tạo với used = 0 (bước 4) | I74: Positive | J74: Cao | K74: Tự động | L74: Yêu cầu thành công; đúng một bản ghi với used = 0 | M74: Pass | N74: Jest + Supertest | O74: 25/09/2026
A75: VOUC-005 | B75: Voucher và ví voucher | C75: UC10 | D75: Nhận lại voucher đã có trong ví | E75: customer1 đã có SALE20 | F75: voucherId của SALE20 | G75: 1. Gửi yêu cầu nhận lần nữa 2. Đếm bản ghi user_vouchers | H75: Không cho nhận lần hai; không tạo bản ghi trùng (ngoại lệ 3b) | I75: Negative | J75: Cao | K75: Tự động | L75: Vẫn một bản ghi. Nội dung phản hồi chưa được kịch bản kiểm tra | M75: Pass | N75: Jest + Supertest | O75: 25/09/2026 | P75: Mức kiểm chứng hạn chế: chỉ kiểm tra một phần kết quả mong đợi (Bảng 3.37, dòng 2)
A76: VOUC-006 | B76: Voucher và ví voucher | C76: UC10 | D76: Nhận voucher đã hết lượt | E76: Voucher có used bằng quantity | F76: voucherId của HETLUOT (used = quantity = 5) | G76: 1. Gửi POST /api/user-vouchers/receive/:voucherId | H76: Không cho nhận (ngoại lệ 3a) | I76: Negative | J76: Cao | K76: Tự động | L76: Mã 400, Voucher không hợp lệ hoặc đã hết | M76: Pass | N76: Jest + Supertest | O76: 25/09/2026
A77: VOUC-007 | B77: Voucher và ví voucher | C77: UC10 | D77: Nhận voucher đã hết hạn | E77: Voucher có end_date nhỏ hơn ngày hiện tại | F77: voucherId của HETHAN (end_date là ngày hôm trước) | G77: 1. Gửi POST /api/user-vouchers/receive/:voucherId | H77: Không cho nhận (ngoại lệ 3a) | I77: Boundary | J77: Cao | K77: Tự động | L77: Mã 400. Nội dung thông báo chưa được kịch bản kiểm tra | M77: Pass | N77: Jest + Supertest | O77: 25/09/2026 | P77: Mức kiểm chứng hạn chế: chỉ kiểm tra một phần kết quả mong đợi (Bảng 3.37, dòng 2)
A78: VOUC-008 | B78: Voucher và ví voucher | C78: UC10 | D78: Áp dụng voucher cho đơn đạt giá trị tối thiểu, mức giảm vượt trần | E78: Voucher SALE20 giảm 20 phần trăm, tối đa 50.000đ, đơn tối thiểu 200.000đ | F78: code = SALE20; total = 300000 | G78: 1. Gửi POST /api/vouchers/apply | H78: Mã 200; discount = 50000 do bị chặn bởi max_discount; finalTotal = 250000 (UC10 bước 5) | I78: Boundary | J78: Cao | K78: Tự động | L78: Mã 200; discount = 50000; finalTotal = 250000. Kịch bản VOUC-008b tại biên 200.000 đ cho discount = 40000 | M78: Pass | N78: Jest + Supertest | O78: 25/09/2026
A79: VOUC-009 | B79: Voucher và ví voucher | C79: UC10 | D79: Áp dụng voucher cho đơn dưới giá trị tối thiểu | E79: Voucher yêu cầu đơn tối thiểu 200.000đ | F79: code = SALE20; total = 150000 | G79: 1. Gửi POST /api/vouchers/apply | H79: Không áp dụng giảm giá, báo đơn chưa đạt giá trị tối thiểu (ngoại lệ 5a) | I79: Boundary | J79: Cao | K79: Tự động | L79: Mã 400, thông báo bắt đầu bằng Đơn tối thiểu. Theo mã nguồn, giá trị trong thông báo lấy thẳng từ cột DECIMAL nên hiển thị dạng 200000.00 thay vì 200.000 | M79: Pass | N79: Jest + Supertest | O79: 25/09/2026 | P79: Kịch bản VOUC-009c ghi nhận DEF-04
A80: VOUC-010 | B80: Voucher và ví voucher | C80: UC10 | D80: Áp dụng mã voucher không tồn tại | E80: Máy chủ đang chạy | F80: code = MAKHONGTONTAI; total = 500000 | G80: 1. Gửi POST /api/vouchers/apply | H80: Mã 400, thông báo Voucher không hợp lệ | I80: Negative | J80: Cao | K80: Tự động | L80: Mã 400, Voucher không hợp lệ | M80: Pass | N80: Jest + Supertest | O80: 25/09/2026 | P80: Kịch bản VOUC-010b ghi nhận DEF-09
A81: VOUC-011 | B81: Voucher và ví voucher | C81: UC07 | D81: Dùng voucher khi đặt hàng và đánh dấu đã dùng | E81: SALE20 có trong ví customer1, chưa dùng | F81: voucher_ids gồm mã của SALE20 | G81: 1. Gửi POST /api/orders kèm voucher 2. Truy vấn user_vouchers và vouchers | H81: Voucher trong ví được đánh dấu đã dùng, bộ đếm used tăng thêm 1, voucher chuyển không hoạt động khi hết lượt (UC07 bước 10) | I81: Positive | J81: Cao | K81: Tự động | L81: Mã 200; user_vouchers.used = 1; vouchers.used tăng đúng 1. Nhánh chuyển sang không hoạt động chưa được kiểm tra | M81: Pass | N81: Jest + Supertest | O81: 25/09/2026 | P81: Mức kiểm chứng hạn chế: chỉ kiểm tra một phần kết quả mong đợi (Bảng 3.37, dòng 2)
A82: VOUC-012 | B82: Voucher và ví voucher | C82: UC07 | D82: Dùng lại voucher đã sử dụng | E82: SALE20 vừa được dùng ở VOUC-011 | F82: voucher_ids gồm mã của SALE20 | G82: 1. Gửi POST /api/orders 2. Kiểm tra tồn kho và số đơn | H82: Hoàn tác giao dịch, báo Voucher không khả dụng; không tạo đơn, không trừ tồn kho (UC07 ngoại lệ 10a) | I82: Security | J82: Cao | K82: Tự động | L82: Mã 500, Voucher không khả dụng; tồn kho và số đơn không đổi | M82: Pass | N82: Jest + Supertest | O82: 25/09/2026 | P82: Đề xuất trả mã 409 cho lỗi nghiệp vụ (mục 3.5.2)
A83: REV-001 | B83: Đánh giá sản phẩm | C83: UC09 | D83: Đánh giá sản phẩm đã mua | E83: customer1 có đơn completed chứa sản phẩm trong dữ liệu mẫu | F83: rating = 5; comment = San pham rat tot | G83: 1. Gửi POST /api/products/:id/reviews 2. Truy vấn product_reviews | H83: Mã 200, thông báo Đã lưu đánh giá sản phẩm; đánh giá được lưu (bước 6) | I83: Positive | J83: Cao | K83: Tự động | L83: Mã 200, Đã lưu đánh giá sản phẩm; bản ghi có rating = 5 và đúng nội dung | M83: Pass | N83: Jest + Supertest | O83: 25/09/2026
A84: REV-002 | B84: Đánh giá sản phẩm | C84: UC09 | D84: Số sao nằm ngoài khoảng cho phép | E84: Khách hàng đủ điều kiện đánh giá | F84: rating = 0; rating = 6 | G84: 1. Gửi với điểm 0 2. Gửi với điểm 6 | H84: Cả hai trả mã 400 (ngoại lệ 2a) | I84: Boundary | J84: Cao | K84: Tự động | L84: Cả hai trả mã 400, Rating phải từ 1 đến 5. Kịch bản REV-002b xác nhận hai giá trị biên 1 và 5 được chấp nhận | M84: Pass | N84: Jest + Supertest | O84: 25/09/2026
A85: REV-003 | B85: Đánh giá sản phẩm | C85: UC09 | D85: Đánh giá sản phẩm chưa từng mua | E85: customer2 chưa có đơn nào chứa sản phẩm | F85: rating = 5 | G85: 1. Gửi POST /api/products/:id/reviews | H85: Mã 403, thông báo Đánh giá chỉ khả dụng khi đơn đã hoàn tất (ngoại lệ 5a) | I85: Security | J85: Cao | K85: Tự động | L85: Mã 403, Đánh giá chỉ khả dụng khi đơn đã hoàn tất | M85: Pass | N85: Jest + Supertest | O85: 25/09/2026
A86: REV-004 | B86: Đánh giá sản phẩm | C86: UC09 | D86: Cập nhật đánh giá đã có | E86: customer1 đã đánh giá sản phẩm | F86: rating = 3; comment = Dung mot tuan thay binh thuong | G86: 1. Gửi đánh giá lần hai 2. Đếm và đọc bản ghi product_reviews | H86: Cập nhật đánh giá cũ thay vì tạo mới, nhờ ràng buộc duy nhất (product_id, user_id) (ngoại lệ 6a) | I86: Positive | J86: Cao | K86: Tự động | L86: Mã 200; số bản ghi không đổi; rating = 3 và comment mới. Cột updated_at chưa được kiểm tra | M86: Pass | N86: Jest + Supertest | O86: 25/09/2026 | P86: Mức kiểm chứng hạn chế: chỉ kiểm tra một phần kết quả mong đợi (Bảng 3.37, dòng 2)
A87: REV-005 | B87: Đánh giá sản phẩm | C87: UC09 | D87: Đánh giá kèm ảnh minh họa | E87: Khách hàng đủ điều kiện đánh giá | F87: rating = 4; review.png | G87: 1. Gửi đánh giá kèm tệp ảnh 2. Truy vấn image_url | H87: Ảnh được lưu vào thư mục uploads, đường dẫn ghi vào image_url (bước 3) | I87: Positive | J87: Trung bình | K87: Tự động | L87: Mã 200; image_url bắt đầu bằng uploads/ | M87: Pass | N87: Jest + Supertest | O87: 25/09/2026
A88: REV-006 | B88: Đánh giá sản phẩm | C88: UC09 | D88: Nhân viên cố gửi đánh giá | E88: Đăng nhập bằng tài khoản STAFF | F88: token của staff@tigershop.test | G88: 1. Gửi POST /api/products/:id/reviews | H88: Mã 403; chỉ khách hàng được đánh giá (tác nhân của UC09) | I88: Security | J88: Cao | K88: Tự động | L88: Mã 403, Chỉ khách hàng mới được đánh giá sản phẩm | M88: Pass | N88: Jest + Supertest | O88: 25/09/2026
A89: REV-007 | B89: Đánh giá sản phẩm | C89: UC09 | D89: Xem danh sách đánh giá của sản phẩm | E89: Sản phẩm đã có đánh giá | F89: Mã sản phẩm đã đánh giá ở REV-001 | G89: 1. Gửi GET /api/products/:id/reviews | H89: Mã 200; đủ tên người đánh giá, số sao, nội dung và ảnh nếu có | I89: Positive | J89: Trung bình | K89: Tự động | L89: Mã 200; danh sách có ít nhất một đánh giá. Các trường của từng đánh giá chưa được kiểm tra | M89: Pass | N89: Jest + Supertest | O89: 25/09/2026 | P89: Mức kiểm chứng hạn chế: chỉ kiểm tra một phần kết quả mong đợi (Bảng 3.37, dòng 2)
A90: REV-008 | B90: Đánh giá sản phẩm | C90: UC09 | D90: Đánh giá khi đơn thanh toán QR chưa hoàn tất | E90: customer2 vừa đặt đơn QR, đơn có status = pending | F90: rating = 5; comment = Danh gia khi don QR con pending | G90: 1. Đặt đơn QR 2. Xác nhận đơn đang pending 3. Gửi đánh giá cho sản phẩm trong đơn | H90: Mã 200, đánh giá được lưu, vì đơn thanh toán bằng chuyển khoản QR thỏa tiền điều kiện của UC09 | I90: Negative | J90: Cao | K90: Thủ công | L90: Mã 200, đánh giá được lưu khi đơn QR vẫn ở trạng thái pending | M90: Pass | N90: Jest + Supertest | O90: 25/09/2026 | P90: Đơn QR thỏa tiền điều kiện UC09 theo mục 1.1.2; Thiết kế thủ công, đã thực hiện bằng kịch bản Jest (Bảng 3.4)
A91: CHAT-001 | B91: Chat hỗ trợ thời gian thực | C91: UC21 | D91: Tự động tạo hội thoại khi khách hàng mở hộp thoại hỗ trợ | E91: customer1 chưa có hội thoại | F91: token của customer1 | G91: 1. Gửi GET /api/chat/my-thread hai lần 2. Đếm bản ghi threads của customer1 | H91: Lần đầu tạo một hội thoại ở trạng thái open; lần sau dùng lại đúng hội thoại cũ, mỗi khách hàng có đúng một hội thoại (bước 2) | I91: Positive | J91: Cao | K91: Tự động | L91: Mã 200; hai lần trả về cùng một id; bảng threads có đúng một bản ghi của customer1 | M91: Pass | N91: Jest + Supertest | O91: 25/09/2026
A92: CHAT-002 | B92: Chat hỗ trợ thời gian thực | C92: UC21 | D92: Khách hàng gửi tin nhắn cho nhân viên | E92: Hội thoại đã tồn tại | F92: content = Cho minh hoi ve don hang | G92: 1. Gửi POST /api/chat/messages 2. Truy vấn chat_messages | H92: Tin nhắn được lưu và phát sự kiện new_message tới phòng hội thoại (bước 5) | I92: Positive | J92: Cao | K92: Tự động | L92: Yêu cầu thành công; sender_role = USER, nội dung đúng. Sự kiện Socket.IO chưa kiểm chứng. Kịch bản CHAT-002b xác nhận tin nhắn chỉ gồm khoảng trắng bị từ chối với mã 400 | M92: Pass | N92: Jest + Supertest | O92: 25/09/2026 | P92: Mức kiểm chứng hạn chế: phần giao diện hoặc thời gian thực chưa kiểm chứng (Bảng 3.37, dòng 4)
A93: CHAT-003 | B93: Chat hỗ trợ thời gian thực | C93: UC21 | D93: Khách hàng yêu cầu gặp nhân viên | E93: Hội thoại đã tồn tại | F93: threadId hợp lệ | G93: 1. Nhấn Gặp nhân viên 2. Quan sát trạng thái hội thoại và màn hình nhân viên | H93: Hội thoại chuyển sang staff_needed và sự kiện request_staff được phát tới nhân viên (bước 3) | I93: Positive | J93: Cao | K93: Thủ công | L93: Chưa đủ kết quả. Kịch bản CHAT2-001 mới xác nhận phần máy chủ: status = staff_needed, is_human_needed = 1. Phần phát sự kiện tới nhân viên chưa kiểm chứng | M93: Chưa thực hiện | P93: Lý do: cần hai phiên trình duyệt và sự kiện Socket.IO (rủi ro R08) (Bảng 3.38, dòng 3)
A94: CHAT-004 | B94: Chat hỗ trợ thời gian thực | C94: UC21 | D94: Nhân viên trả lời và khách hàng nhận tin theo thời gian thực | E94: Hai trình duyệt đang mở | F94: message = Chao ban, minh ho tro ngay | G94: 1. Nhân viên gửi tin 2. Quan sát màn hình khách hàng mà không tải lại trang | H94: Tin nhắn xuất hiện tức thì trên màn hình khách hàng (bước 5) | I94: Positive | J94: Cao | K94: Thủ công | L94: Chưa có kết quả | M94: Chưa thực hiện | P94: Lý do: cần hai phiên trình duyệt và sự kiện Socket.IO (rủi ro R08) (Bảng 3.38, dòng 3)
A95: CHAT-005 | B95: Chat hỗ trợ thời gian thực | C95: UC21 | D95: Giới hạn tần suất gửi tin qua Socket.IO | E95: Hội thoại đang mở | F95: 8 tin nhắn liên tiếp trong 60 giây | G95: 1. Gửi liên tục 8 tin 2. Ghi nhận phản hồi | H95: Năm tin đầu được xử lý; từ tin thứ 6 bị chặn tạm thời (ngoại lệ 5a) | I95: Security | J95: Trung bình | K95: Thủ công | L95: Chưa có kết quả | M95: Chưa thực hiện | P95: Lý do: cần hai phiên trình duyệt và sự kiện Socket.IO (rủi ro R08) (Bảng 3.38, dòng 3)
A96: CHAT-006 | B96: Chat hỗ trợ thời gian thực | C96: UC21 | D96: Tự động kết nối lại khi mất kết nối WebSocket | E96: Hội thoại đang mở | F96: Ngắt mạng 10 giây rồi khôi phục | G96: 1. Ngắt mạng 2. Chờ 10 giây 3. Khôi phục mạng và gửi tin mới | H96: Giao diện tự kết nối lại; tin mới gửi thành công; không mất lịch sử (ngoại lệ 5b) | I96: Negative | J96: Trung bình | K96: Thủ công | L96: Chưa có kết quả | M96: Chưa thực hiện | P96: Lý do: cần hai phiên trình duyệt và sự kiện Socket.IO (rủi ro R08) (Bảng 3.38, dòng 3)
A97: CHAT-007 | B97: Chat hỗ trợ thời gian thực | C97: UC21 | D97: Xem danh sách hội thoại hỗ trợ | E97: Đã có hội thoại của customer1 | F97: token của admin (điểm cuối cho phép ADMIN, MANAGER, STAFF) | G97: 1. Gửi GET /api/chat/admin/threads | H97: Danh sách hội thoại kèm email khách hàng và thời điểm tin nhắn cuối, sắp xếp giảm dần (ngoại lệ 7a) | I97: Positive | J97: Cao | K97: Tự động | L97: Mã 200; mỗi phần tử có threadId, userId, email. Thứ tự sắp xếp chưa được kiểm tra | M97: Pass | N97: Jest + Supertest | O97: 25/09/2026 | P97: Mức kiểm chứng hạn chế: chỉ kiểm tra một phần kết quả mong đợi (Bảng 3.37, dòng 2)
A98: CHAT-008 | B98: Chat hỗ trợ thời gian thực | C98: UC21 | D98: Xem nhanh đơn hàng của khách trong khung hội thoại | E98: customer1 có đơn | F98: userId của customer1; token của admin | G98: 1. Gửi GET /api/chat/admin/users/:userId/orders | H98: Trả về đúng danh sách đơn của khách hàng đó (bước 7) | I98: Positive | J98: Trung bình | K98: Tự động | L98: Mã 200. Nội dung danh sách chưa được đối chiếu | M98: Pass | N98: Jest + Supertest | O98: 25/09/2026 | P98: Mức kiểm chứng hạn chế: chỉ kiểm tra mã trạng thái (Bảng 3.37, dòng 1)
A99: CHAT-009 | B99: Chat hỗ trợ thời gian thực | C99: UC21 | D99: Khách hàng cố đọc hội thoại không thuộc về mình | E99: customer2 có hội thoại chứa tin nhắn riêng | F99: token của customer1; threadId của customer2; tin nhắn mẫu Thong tin rieng tu cua khach hang 2 | G99: 1. Gửi GET /api/chat/messages/:threadId bằng token của customer1 | H99: Hệ thống từ chối; chỉ chủ hội thoại, nhân viên và Quản trị viên được đọc (ngoại lệ 5c) | I99: Security | J99: Cao | K99: Tự động | L99: Mã 200; phản hồi chứa nguyên văn tin nhắn riêng tư của customer2 | M99: Fail | N99: Jest + Supertest | O99: 25/09/2026 | P99: Khiếm khuyết DEF-08, trùng VUL-01, mức Nghiêm trọng (Bảng 3.36)
A100: CHAT-010 | B100: Chat hỗ trợ thời gian thực | C100: UC22 | D100: Nhận thông báo khi trạng thái đơn hàng thay đổi | E100: Khách hàng có đơn đang xử lý | F100: Nhân viên đổi đơn sang shipping | G100: 1. Nhân viên cập nhật trạng thái đơn 2. Khách hàng quan sát biểu tượng chuông | H100: notifications có bản ghi cho đúng người dùng; số chưa đọc trên biểu tượng chuông tăng 1 (bước 1, 2) | I100: Positive | J100: Cao | K100: Thủ công | L100: Chưa có kết quả; cần quan sát giao diện khách hàng trong lúc nhân viên thao tác | M100: Chưa thực hiện | P100: Lý do: cần hai phiên trình duyệt và sự kiện Socket.IO (rủi ro R08) (Bảng 3.38, dòng 3)
...

Sheet AUTH
A1: Mã TC | B1: Nhóm chức năng | C1: UC liên quan | D1: Tiêu đề kiểm thử | E1: Điều kiện tiên quyết | F1: Dữ liệu đầu vào | G1: Các bước thực hiện | H1: Kết quả mong đợi | I1: Loại KT | J1: Mức ưu tiên | K1: Phương pháp | L1: Kết quả thực tế | M1: Trạng thái | N1: Người thực hiện | O1: Ngày thực hiện | P1: Ghi chú
A2: AUTH-001 | B2: Xác thực và phân quyền | C2: UC01 | D2: Đăng ký với dữ liệu hợp lệ | E2: Email chưa tồn tại | F2: name = Nguoi dung moi; email = new.user.[thời điểm]@tigershop.test; password = Test@123; phone = 0912345678; birthday = 2000-05-20 | G2: 1. Gửi POST /api/auth/register 2. Truy vấn bảng users theo email 3. Truy vấn user_vouchers của tài khoản mới | H2: Mã 200, thông báo Register successful; users có role_id = 5, status = active; ví có một voucher chào mừng giảm 50% (hậu điều kiện UC01) | I2: Positive | J2: Cao | K2: Tự động | L2: Mã 200, Register successful; role_id = 5, status = active; ví có đúng một voucher value = 50. Voucher được ghi sau khi phản hồi đã trả về nên kịch bản phải chờ tối đa 3 giây mới thấy bản ghi (liên quan DEF-01) | M2: Pass | N2: Jest + Supertest | O2: 25/09/2026 | P2: Quan sát được DEF-01: voucher chào mừng ghi sau phản hồi, không cùng giao dịch
A3: AUTH-002 | B3: Xác thực và phân quyền | C3: UC01 | D3: Đăng ký khi bỏ trống họ tên | E3: Máy chủ đang chạy; không cần đăng nhập | F3: name rỗng; các trường khác hợp lệ | G3: 1. Gửi POST /api/auth/register | H3: Mã 400, thông báo Thiếu thông tin đăng ký (ngoại lệ 5a) | I3: Negative | J3: Cao | K3: Tự động | L3: Mã 400, Thiếu thông tin đăng ký | M3: Pass | N3: Jest + Supertest | O3: 25/09/2026
A4: AUTH-003 | B4: Xác thực và phân quyền | C4: UC01 | D4: Đăng ký khi bỏ trống email | E4: Máy chủ đang chạy; không cần đăng nhập | F4: email rỗng; các trường khác hợp lệ | G4: 1. Gửi POST /api/auth/register | H4: Mã 400, thông báo Thiếu thông tin đăng ký (ngoại lệ 5a) | I4: Negative | J4: Cao | K4: Tự động | L4: Mã 400, Thiếu thông tin đăng ký | M4: Pass | N4: Jest + Supertest | O4: 25/09/2026
A5: AUTH-004 | B5: Xác thực và phân quyền | C5: UC01 | D5: Đăng ký khi bỏ trống mật khẩu | E5: Máy chủ đang chạy; không cần đăng nhập | F5: password rỗng; các trường khác hợp lệ | G5: 1. Gửi POST /api/auth/register | H5: Mã 400, thông báo Thiếu thông tin đăng ký (ngoại lệ 5a) | I5: Negative | J5: Cao | K5: Tự động | L5: Mã 400, Thiếu thông tin đăng ký | M5: Pass | N5: Jest + Supertest | O5: 25/09/2026
A6: AUTH-005 | B6: Xác thực và phân quyền | C6: UC01 | D6: Đăng ký khi bỏ trống số điện thoại | E6: Máy chủ đang chạy; không cần đăng nhập | F6: phone rỗng; các trường khác hợp lệ | G6: 1. Gửi POST /api/auth/register | H6: Mã 400, thông báo Thiếu thông tin đăng ký (ngoại lệ 5a) | I6: Negative | J6: Trung bình | K6: Tự động | L6: Mã 400, Thiếu thông tin đăng ký | M6: Pass | N6: Jest + Supertest | O6: 25/09/2026
A7: AUTH-006 | B7: Xác thực và phân quyền | C7: UC01 | D7: Đăng ký với email đã tồn tại | E7: customer1@tigershop.test có sẵn trong dữ liệu mẫu | F7: email = customer1@tigershop.test; các trường khác hợp lệ | G7: 1. Gửi POST /api/auth/register 2. Đếm bản ghi users có email này | H7: Từ chối đăng ký, mã 409 kèm thông báo thư điện tử đã được sử dụng; không phát sinh bản ghi trùng (ngoại lệ 6a) | I7: Negative | J7: Cao | K7: Tự động | L7: Mã 500, thông báo Email đã tồn tại; số bản ghi vẫn là 1 nhờ ràng buộc UNIQUE | M7: Fail | N7: Jest + Supertest | O7: 25/09/2026 | P7: Khiếm khuyết DEF-12, mức Thấp (Bảng 3.36)
A8: AUTH-007 | B8: Xác thực và phân quyền | C8: UC01 | D8: Mật khẩu xác nhận không khớp | E8: Đang ở trang /register | F8: password = Test@123; confirmPassword = Test@456 | G8: 1. Nhập hai mật khẩu khác nhau 2. Nhấn Đăng ký | H8: Giao diện báo lỗi xác nhận mật khẩu và không gửi yêu cầu tới máy chủ (Hình 1.7) | I8: Negative | J8: Cao | K8: Tự động | L8: Chưa có kết quả; kiểm tra này nằm hoàn toàn trong Register.js | M8: Chưa thực hiện | P8: Lý do: chức năng nằm hoàn toàn ở giao diện, thuộc giai đoạn 6 chưa triển khai (Bảng 3.38, dòng 1)
A9: AUTH-008 | B9: Xác thực và phân quyền | C9: UC01 | D9: Đăng ký với email sai định dạng | E9: Đang ở trang /register | F9: email = abc@@test | G9: 1. Nhập email sai định dạng 2. Nhấn Đăng ký | H9: Giao diện chặn gửi biểu mẫu và cảnh báo định dạng email (Hình 1.7) | I9: Negative | J9: Trung bình | K9: Tự động | L9: Chưa có kết quả; kiểm tra này nằm hoàn toàn trong Register.js | M9: Chưa thực hiện | P9: Lý do: chức năng nằm hoàn toàn ở giao diện, thuộc giai đoạn 6 chưa triển khai (Bảng 3.38, dòng 1)
A10: AUTH-009 | B10: Xác thực và phân quyền | C10: UC01 | D10: Mật khẩu được băm trước khi lưu | E10: Đăng ký thành công một tài khoản mới | F10: email = hash.check.[thời điểm]@tigershop.test; password = Test@123 | G10: 1. Đăng ký tài khoản 2. Đọc cột password theo email 3. So khớp bằng bcrypt.compare | H10: Cột password là chuỗi băm bcrypt, khác mật khẩu gốc (bước 6; mục 1.3.3) | I10: Security | J10: Cao | K10: Tự động | L10: Giá trị lưu khác mật khẩu gốc, khớp mẫu chuỗi băm bcrypt; bcrypt.compare với mật khẩu gốc trả về true | M10: Pass | N10: Jest + Supertest | O10: 25/09/2026
A11: AUTH-010 | B11: Xác thực và phân quyền | C11: UC01 | D11: Voucher chào mừng được phát tự động | E11: Vừa đăng ký tài khoản mới | F11: tài khoản tạo ở AUTH-001 | G11: 1. Đăng nhập tài khoản mới 2. Mở trang Voucher của tôi | H11: Ví có đúng một voucher giảm 50%, áp dụng cho đơn từ 50.000 đ, giảm tối đa 100.000 đ, hiệu lực 30 ngày (bước 7) | I11: Positive | J11: Trung bình | K11: Thủ công | L11: Chưa kiểm tra trên giao diện. Kịch bản AUTH-001 mới xác nhận giá trị giảm 50%; đơn tối thiểu, mức giảm tối đa và hạn dùng chưa được đối chiếu | M11: Chưa thực hiện | P11: Lý do: kịch bản hiện có chưa đủ tin cậy làm bằng chứng (Bảng 3.38, dòng 2)
A12: AUTH-011 | B12: Xác thực và phân quyền | C12: UC01 | D12: Giới hạn tần suất trên nhóm API xác thực | E12: Bộ giới hạn thật, không giả lập | F12: 13 yêu cầu POST /api/auth/login liên tiếp từ cùng một địa chỉ | G12: 1. Gửi liên tiếp 13 yêu cầu 2. Ghi mã trạng thái của từng yêu cầu | H12: Mười yêu cầu đầu được xử lý bình thường; từ yêu cầu thứ 11 trả mã 429 (ngoại lệ 4a) | I12: Security | J12: Cao | K12: Tự động | L12: Yêu cầu 1 đến 10 được xử lý (mã 401 vì email không tồn tại); yêu cầu 11 đến 13 trả mã 429. Kịch bản AUTH-011b xác nhận thông báo tiếng Việt có cụm từ quá nhanh | M12: Pass | N12: Jest + Supertest | O12: 25/09/2026
A13: AUTH-012 | B13: Xác thực và phân quyền | C13: UC02 | D13: Đăng nhập tài khoản Quản trị viên | E13: Tài khoản đang hoạt động | F13: admin@tigershop.test; Test@123 | G13: 1. Gửi POST /api/auth/login | H13: Mã 200, trả về token và role = ADMIN; giao diện chuyển tới /admin/dashboard (bước 8) | I13: Positive | J13: Cao | K13: Tự động | L13: Mã 200, token là chuỗi JWT, role = ADMIN. Phần chuyển trang trên giao diện chưa kiểm chứng | M13: Pass | N13: Jest + Supertest | O13: 25/09/2026 | P13: Mức kiểm chứng hạn chế: phần giao diện hoặc thời gian thực chưa kiểm chứng (Bảng 3.37, dòng 4)
A14: AUTH-013 | B14: Xác thực và phân quyền | C14: UC02 | D14: Đăng nhập tài khoản Quản lý | E14: Tài khoản đang hoạt động | F14: manager@tigershop.test; Test@123 | G14: 1. Gửi POST /api/auth/login | H14: Mã 200, role = MANAGER; giao diện chuyển tới /manager/workspace | I14: Positive | J14: Cao | K14: Tự động | L14: Mã 200, token là chuỗi JWT, role = MANAGER. Phần chuyển trang chưa kiểm chứng | M14: Pass | N14: Jest + Supertest | O14: 25/09/2026 | P14: Mức kiểm chứng hạn chế: phần giao diện hoặc thời gian thực chưa kiểm chứng (Bảng 3.37, dòng 4)
A15: AUTH-014 | B15: Xác thực và phân quyền | C15: UC02 | D15: Đăng nhập tài khoản Nhân viên | E15: status = active | F15: staff@tigershop.test; Test@123 | G15: 1. Gửi POST /api/auth/login | H15: Mã 200, role = STAFF; giao diện chuyển tới /staff/workspace | I15: Positive | J15: Cao | K15: Tự động | L15: Mã 200, token là chuỗi JWT, role = STAFF. Phần chuyển trang chưa kiểm chứng | M15: Pass | N15: Jest + Supertest | O15: 25/09/2026 | P15: Mức kiểm chứng hạn chế: phần giao diện hoặc thời gian thực chưa kiểm chứng (Bảng 3.37, dòng 4)
A16: AUTH-015 | B16: Xác thực và phân quyền | C16: UC02 | D16: Đăng nhập tài khoản Khách hàng | E16: Tài khoản đang hoạt động | F16: customer1@tigershop.test; Test@123 | G16: 1. Gửi POST /api/auth/login | H16: Mã 200, role = CUSTOMER; giao diện chuyển tới /home | I16: Positive | J16: Cao | K16: Tự động | L16: Mã 200, token là chuỗi JWT, role = CUSTOMER. Phần chuyển trang chưa kiểm chứng | M16: Pass | N16: Jest + Supertest | O16: 25/09/2026 | P16: Mức kiểm chứng hạn chế: phần giao diện hoặc thời gian thực chưa kiểm chứng (Bảng 3.37, dòng 4)
A17: AUTH-016 | B17: Xác thực và phân quyền | C17: UC02 | D17: Đăng nhập với mật khẩu sai | E17: Tài khoản tồn tại trong hệ thống | F17: customer1@tigershop.test; SaiMatKhau123 | G17: 1. Gửi POST /api/auth/login | H17: Mã 401, thông báo Wrong password; không cấp token (ngoại lệ 6a) | I17: Negative | J17: Cao | K17: Tự động | L17: Mã 401, Wrong password; phản hồi không có trường token | M17: Pass | N17: Jest + Supertest | O17: 25/09/2026 | P17: Hai thông báo khác nhau cho phép dò email (VUL-10, Chương VI)
A18: AUTH-017 | B18: Xác thực và phân quyền | C18: UC02 | D18: Đăng nhập với email không tồn tại | E18: Email khongtontai@tigershop.test chưa từng đăng ký | F18: khongtontai@tigershop.test; Test@123 | G18: 1. Gửi POST /api/auth/login | H18: Mã 401, thông báo User not found (ngoại lệ 4a) | I18: Negative | J18: Cao | K18: Tự động | L18: Mã 401, User not found | M18: Pass | N18: Jest + Supertest | O18: 25/09/2026 | P18: Hai thông báo khác nhau cho phép dò email (VUL-10, Chương VI)
A19: AUTH-018 | B19: Xác thực và phân quyền | C19: UC02 | D19: Bỏ trống email và mật khẩu | E19: Máy chủ đang chạy; không cần đăng nhập | F19: email rỗng; password rỗng | G19: 1. Gửi POST /api/auth/login | H19: Mã 400, thông báo Thiếu email hoặc mật khẩu (ngoại lệ 2a) | I19: Negative | J19: Trung bình | K19: Tự động | L19: Mã 400, Thiếu email hoặc mật khẩu | M19: Pass | N19: Jest + Supertest | O19: 25/09/2026
A20: AUTH-019 | B20: Xác thực và phân quyền | C20: UC02 | D20: Token cấp trước khi tài khoản bị khóa | E20: customer2 đang hoạt động | F20: token của customer2 | G20: 1. Đăng nhập customer2 và gọi GET /api/users/me 2. Đặt is_active = 0 3. Gọi lại GET /api/users/me bằng token cũ | H20: Lần gọi sau khi khóa trả mã 403, thông báo Tài khoản của bạn đã bị khóa. (UC23 ngoại lệ 3a) | I20: Security | J20: Cao | K20: Tự động | L20: Trước khi khóa mã 200; sau khi khóa mã 403 với đúng thông báo. Kịch bản AUTH-019b xác nhận thêm tài khoản customer.locked bị chặn ngay ở bước đăng nhập (mã 403, không cấp token, ngoại lệ 5c) | M20: Pass | N20: Jest + Supertest | O20: 25/09/2026
A21: AUTH-020 | B21: Xác thực và phân quyền | C21: UC03 | D21: Gọi API được bảo vệ khi không gửi token | E21: Máy chủ đang chạy | F21: Yêu cầu GET /api/users/me không có header Authorization | G21: 1. Gửi yêu cầu | H21: Mã 401, thông báo Token không tồn tại | I21: Security | J21: Cao | K21: Tự động | L21: Mã 401, Token không tồn tại | M21: Pass | N21: Jest + Supertest | O21: 25/09/2026
A22: AUTH-021 | B22: Xác thực và phân quyền | C22: UC03 | D22: Gọi API với token sai định dạng hoặc đã hết hạn | E22: Máy chủ đang chạy | F22: Bearer abc.def.ghi; token hợp lệ về chữ ký nhưng hết hạn từ 1 giờ trước | G22: 1. Gửi yêu cầu kèm token sai định dạng 2. Gửi yêu cầu kèm token hết hạn | H22: Cả hai trường hợp trả mã 401, thông báo Token không hợp lệ (ngoại lệ 1a) | I22: Security | J22: Cao | K22: Tự động | L22: Cả hai trả mã 401, Token không hợp lệ (trường hợp hết hạn chạy ở kịch bản AUTH-021b) | M22: Pass | N22: Jest + Supertest | O22: 25/09/2026
A23: AUTH-022 | B23: Xác thực và phân quyền | C23: UC03 | D23: Đăng xuất và xác nhận phiên đã kết thúc | E23: Đang đăng nhập trên trình duyệt | F23: Không | G23: 1. Nhấn Đăng xuất 2. Kiểm tra localStorage 3. Truy cập lại trang cần đăng nhập | H23: Dữ liệu xác thực trong localStorage bị xóa, trình duyệt chuyển về /login và không vào lại được trang bảo vệ (hậu điều kiện UC03) | I23: Positive | J23: Cao | K23: Tự động | L23: Chưa có kết quả; UC03 không có điểm cuối API, toàn bộ xử lý nằm ở giao diện | M23: Chưa thực hiện | P23: Lý do: chức năng nằm hoàn toàn ở giao diện, thuộc giai đoạn 6 chưa triển khai (Bảng 3.38, dòng 1)
A24: AUTH-023 | B24: Xác thực và phân quyền | C24: UC04 | D24: Xem và cập nhật hồ sơ cá nhân | E24: customer1 đã đăng nhập | F24: name = Khach hang mot da doi ten; phone = 0987654321 | G24: 1. Gửi GET /api/users/me 2. Gửi PUT /api/users/me 3. Truy vấn bảng users | H24: Mã 200 ở cả hai yêu cầu; họ tên và số điện thoại mới được lưu (bước 5) | I24: Positive | J24: Cao | K24: Tự động | L24: Cả hai yêu cầu trả mã 200; cột name và phone mang đúng giá trị mới. Phần hiển thị sau khi tải lại trang chưa kiểm chứng | M24: Pass | N24: Jest + Supertest | O24: 25/09/2026 | P24: Mức kiểm chứng hạn chế: phần giao diện hoặc thời gian thực chưa kiểm chứng (Bảng 3.37, dòng 4)
A25: AUTH-024 | B25: Xác thực và phân quyền | C25: UC04 | D25: Đổi mật khẩu với mật khẩu hiện tại không đúng | E25: customer2 đã đăng nhập | F25: currentPassword = SaiMatKhauCu; newPassword = MatKhauMoi@123 | G25: 1. Gửi PUT /api/users/me/change-password 2. So sánh cột password trước và sau | H25: Mã 401, thông báo Mật khẩu hiện tại không đúng; cột password không thay đổi (ngoại lệ 3a) | I25: Security | J25: Cao | K25: Tự động | L25: Yêu cầu bị từ chối (kịch bản kiểm tra mã từ 400 trở lên); cột password giữ nguyên. Kịch bản AUTH-024b xác nhận mật khẩu mới dưới 6 ký tự bị từ chối với mã 400 | M25: Pass | N25: Jest + Supertest | O25: 25/09/2026 | P25: Mức kiểm chứng hạn chế: chỉ kiểm tra mã trạng thái (Bảng 3.37, dòng 1)
A26: AUTH-025 | B26: Xác thực và phân quyền | C26: UC04 | D26: Cập nhật ảnh đại diện | E26: Người dùng đã đăng nhập | F26: avatar.png dung lượng 500 KB | G26: 1. Mở trang Hồ sơ 2. Chọn ảnh mới 3. Nhấn Tải lên | H26: Ảnh được lưu vào thư mục uploads, cột avatar được cập nhật, ảnh mới hiển thị trên thanh điều hướng | I26: Positive | J26: Trung bình | K26: Tự động | L26: Chưa có kết quả đủ tin cậy; kịch bản USR-007 có gọi POST /api/users/me/avatar nhưng tự bỏ qua bước kiểm tra khi máy chủ trả lỗi | M26: Chưa thực hiện | P26: Lý do: kịch bản hiện có chưa đủ tin cậy làm bằng chứng (Bảng 3.38, dòng 2)

Sheet PROD
A1: Mã TC | B1: Nhóm chức năng | C1: UC liên quan | D1: Tiêu đề kiểm thử | E1: Điều kiện tiên quyết | F1: Dữ liệu đầu vào | G1: Các bước thực hiện | H1: Kết quả mong đợi | I1: Loại KT | J1: Mức ưu tiên | K1: Phương pháp | L1: Kết quả thực tế | M1: Trạng thái | N1: Người thực hiện | O1: Ngày thực hiện | P1: Ghi chú
A2: PROD-001 | B2: Quản lý sản phẩm và tồn kho | C2: UC05 | D2: Xem danh sách sản phẩm khi chưa đăng nhập | E2: Dữ liệu mẫu có 18 sản phẩm active và 3 sản phẩm pending | F2: Không gửi token | G2: 1. Gửi GET /api/products 2. Đối chiếu với các sản phẩm có status khác active hoặc đã xóa mềm | H2: Mã 200; chỉ có sản phẩm status = active và chưa bị xóa mềm (bước 2) | I2: Positive | J2: Cao | K2: Tự động | L2: Mã 200; không mã sản phẩm pending hay đã xóa mềm nào xuất hiện trong danh sách | M2: Pass | N2: Jest + Supertest | O2: 25/09/2026
A3: PROD-002 | B3: Quản lý sản phẩm và tồn kho | C3: UC05 | D3: Lọc sản phẩm theo danh mục | E3: 4 danh mục đều có sản phẩm | F3: Danh mục đầu tiên có product_count lớn hơn 0 | G3: 1. Gửi GET /api/categories 2. Gửi GET /api/products và lọc theo tên danh mục 3. Đếm trực tiếp trong cơ sở dữ liệu | H3: Chỉ còn sản phẩm thuộc danh mục đã chọn; số lượng khớp số sản phẩm của danh mục (bước 3) | I3: Positive | J3: Cao | K3: Tự động | L3: Số sản phẩm sau khi lọc bằng số đếm trong cơ sở dữ liệu. Thao tác lọc do Shop.js thực hiện trên trình duyệt nên phần hiển thị chưa kiểm chứng | M3: Pass | N3: Jest + Supertest | O3: 25/09/2026 | P3: Mức kiểm chứng hạn chế: phần giao diện hoặc thời gian thực chưa kiểm chứng (Bảng 3.37, dòng 4)
A4: PROD-003 | B4: Quản lý sản phẩm và tồn kho | C4: UC05 | D4: Tìm kiếm theo từ khóa có kết quả | E4: Có sản phẩm tên chứa từ khóa | F4: keyword = Kiem Thu | G4: 1. Nhập từ khóa vào ô tìm kiếm 2. Nhấn tìm kiếm | H4: Hiển thị đúng các sản phẩm có tên chứa từ khóa, không phân biệt chữ hoa và chữ thường (bước 3) | I4: Positive | J4: Trung bình | K4: Tự động | L4: Chưa có kết quả; tìm kiếm là bộ lọc trên trình duyệt trong Shop.js, máy chủ không nhận tham số tìm kiếm | M4: Chưa thực hiện | P4: Lý do: chức năng nằm hoàn toàn ở giao diện, thuộc giai đoạn 6 chưa triển khai (Bảng 3.38, dòng 1)
A5: PROD-004 | B5: Quản lý sản phẩm và tồn kho | C5: UC05 | D5: Tìm kiếm với từ khóa không khớp sản phẩm nào | E5: Đang ở trang danh sách sản phẩm | F5: keyword = zzzzzzzz | G5: 1. Nhập từ khóa 2. Nhấn tìm kiếm | H5: Hiển thị thông báo không tìm thấy, không báo lỗi hệ thống (ngoại lệ 3a) | I5: Negative | J5: Trung bình | K5: Tự động | L5: Chưa có kết quả; cùng lý do với PROD-003 | M5: Chưa thực hiện | P5: Lý do: chức năng nằm hoàn toàn ở giao diện, thuộc giai đoạn 6 chưa triển khai (Bảng 3.38, dòng 1)
A6: PROD-005 | B6: Quản lý sản phẩm và tồn kho | C6: UC05 | D6: Xem chi tiết sản phẩm hợp lệ | E6: Tồn tại sản phẩm có id xác định | F6: Mã của sản phẩm đầu tiên trong danh sách công khai | G6: 1. Gửi GET /api/products/:id | H6: Mã 200; đủ tên, giá, giá gốc, mô tả, ảnh, tồn kho, danh sách biến thể và đánh giá (bước 5) | I6: Positive | J6: Cao | K6: Tự động | L6: Mã 200; có các trường id, name, price, stock. Các trường còn lại chưa được kịch bản kiểm tra | M6: Pass | N6: Jest + Supertest | O6: 25/09/2026 | P6: Mức kiểm chứng hạn chế: chỉ kiểm tra một phần kết quả mong đợi (Bảng 3.37, dòng 2)
A7: PROD-006 | B7: Quản lý sản phẩm và tồn kho | C7: UC05 | D7: Xem chi tiết sản phẩm với mã không tồn tại | E7: Máy chủ đang chạy | F7: productId = 999999 | G7: 1. Gửi GET /api/products/999999 | H7: Mã 404, không trả lỗi 500 (ngoại lệ 4a) | I7: Negative | J7: Trung bình | K7: Tự động | L7: Mã 404 | M7: Pass | N7: Jest + Supertest | O7: 25/09/2026
A8: PROD-007 | B8: Quản lý sản phẩm và tồn kho | C8: UC05 | D8: Xem danh sách biến thể | E8: 3 sản phẩm đầu có biến thể Size S, M, L | F8: Mã của một sản phẩm có biến thể | G8: 1. Gửi GET /api/variants/product/:id | H8: Mã 200; mỗi biến thể có tên, giá và tồn kho riêng | I8: Positive | J8: Cao | K8: Tự động | L8: Mã 200; danh sách có biến thể, bản ghi đầu có đủ variant_name, price, stock | M8: Pass | N8: Jest + Supertest | O8: 25/09/2026
A9: PROD-008 | B9: Quản lý sản phẩm và tồn kho | C9: UC12 | D9: Quản lý thêm sản phẩm mới hợp lệ | E9: Đăng nhập manager@tigershop.test | F9: name = SP cua Manager [thời điểm]; price = 250000; stock = 50; ảnh PNG hợp lệ | G9: 1. Gửi POST /api/products dạng multipart 2. Truy vấn status và manager_id của sản phẩm mới | H9: Mã 200; sản phẩm có status = pending và manager_id là người tạo; chưa hiển thị trên gian hàng cho tới khi được duyệt (bước 5, hậu điều kiện UC12) | I9: Positive | J9: Cao | K9: Tự động | L9: Mã 200; sản phẩm có status = active ngay khi tạo, tức là lên gian hàng mà không qua bước duyệt | M9: Fail | N9: Jest + Supertest | O9: 25/09/2026 | P9: Khiếm khuyết DEF-02, mức Cao (Bảng 3.36); kịch bản PROD-008b ghi nhận thêm DEF-03
A10: PROD-009 | B10: Quản lý sản phẩm và tồn kho | C10: UC12 | D10: Thêm sản phẩm khi bỏ trống tên và giá | E10: Đăng nhập Quản lý | F10: name rỗng; price rỗng | G10: 1. Gửi POST /api/products | H10: Mã 400, thông báo Thiếu thông tin sản phẩm (ngoại lệ 2a) | I10: Negative | J10: Cao | K10: Tự động | L10: Mã 400, Thiếu thông tin sản phẩm | M10: Pass | N10: Jest + Supertest | O10: 25/09/2026
A11: PROD-010 | B11: Quản lý sản phẩm và tồn kho | C11: UC12 | D11: Tải lên tệp sai định dạng | E11: Đăng nhập Quản lý | F11: tailieu.pdf | G11: 1. Gửi POST /api/products kèm tệp pdf ở trường image | H11: Từ chối tải lên, chỉ chấp nhận jpg, jpeg, png, webp (ngoại lệ 3a) | I11: Security | J11: Cao | K11: Tự động | L11: Yêu cầu bị từ chối (kịch bản chỉ kiểm tra mã từ 400 trở lên); bộ lọc fileFilter trong productRoutes.js chặn tệp trước khi ghi đĩa | M11: Pass | N11: Jest + Supertest | O11: 25/09/2026 | P11: Mức kiểm chứng hạn chế: chỉ kiểm tra mã trạng thái (Bảng 3.37, dòng 1)
A12: PROD-011 | B12: Quản lý sản phẩm và tồn kho | C12: UC12 | D12: Tải lên ảnh vượt giới hạn dung lượng | E12: Đăng nhập Quản lý | F12: anh_lon.jpg dung lượng 6 MB | G12: 1. Gửi POST /api/products kèm tệp | H12: Từ chối tải lên vì vượt giới hạn 5 MB (ngoại lệ 3a) | I12: Boundary | J12: Cao | K12: Tự động | L12: Yêu cầu bị từ chối (kịch bản chỉ kiểm tra mã từ 400 trở lên) | M12: Pass | N12: Jest + Supertest | O12: 25/09/2026 | P12: Mức kiểm chứng hạn chế: chỉ kiểm tra mã trạng thái (Bảng 3.37, dòng 1)
A13: PROD-012 | B13: Quản lý sản phẩm và tồn kho | C13: UC12 | D13: Cập nhật thông tin sản phẩm | E13: Đăng nhập Quản lý | F13: price = 299000; stock = 80 | G13: 1. Gửi PUT /api/products/:id 2. Truy vấn price và stock | H13: Mã 200; giá và tồn kho được cập nhật đúng (bước 7) | I13: Positive | J13: Cao | K13: Tự động | L13: Mã 200; price = 299000, stock = 80 | M13: Pass | N13: Jest + Supertest | O13: 25/09/2026
A14: PROD-013 | B14: Quản lý sản phẩm và tồn kho | C14: UC12 | D14: Xóa mềm và khôi phục sản phẩm | E14: Sản phẩm đang active | F14: Mã của một sản phẩm active | G14: 1. Gửi DELETE /api/products/:id 2. Gửi GET /api/products 3. Gửi PATCH /api/products/:id/restore | H14: Sau khi xóa: deleted_at có giá trị, sản phẩm biến mất khỏi gian hàng. Sau khi khôi phục: deleted_at trở về NULL (ngoại lệ 7b) | I14: Positive | J14: Cao | K14: Tự động | L14: Cả hai thao tác trả mã 200; deleted_at có giá trị rồi trở về NULL; trong khoảng giữa, sản phẩm không có trong danh sách công khai | M14: Pass | N14: Jest + Supertest | O14: 25/09/2026
A15: PROD-014 | B15: Quản lý sản phẩm và tồn kho | C15: UC12 | D15: Thêm biến thể cho sản phẩm | E15: Đăng nhập Quản lý | F15: variant_name = Size XL mau do; price = 270000; stock = 20 | G15: 1. Gửi POST /api/variants 2. Truy vấn product_variants | H15: Mã 200, thông báo Thêm variant thành công; bản ghi biến thể được tạo (bước 6) | I15: Positive | J15: Cao | K15: Tự động | L15: Mã 200, Thêm variant thành công; bản ghi có stock = 20 | M15: Pass | N15: Jest + Supertest | O15: 25/09/2026
A16: PROD-015 | B16: Quản lý sản phẩm và tồn kho | C16: UC12 | D16: Thêm biến thể khi thiếu dữ liệu bắt buộc | E16: Đăng nhập bằng tài khoản MANAGER | F16: variant_name rỗng; price rỗng | G16: 1. Gửi POST /api/variants | H16: Mã 400, thông báo Thiếu dữ liệu variant (ngoại lệ 6a) | I16: Negative | J16: Trung bình | K16: Tự động | L16: Mã 400, Thiếu dữ liệu variant | M16: Pass | N16: Jest + Supertest | O16: 25/09/2026
A17: PROD-016 | B17: Quản lý sản phẩm và tồn kho | C17: UC12 | D17: Cập nhật tồn kho hàng loạt | E17: Sản phẩm có 3 biến thể | F17: Mảng updates gồm 3 cặp mã biến thể và tồn kho mới 5, 10, 15 | G17: 1. Gửi PUT /api/variants/bulk-stock 2. Truy vấn tồn kho các biến thể | H17: Cả 3 biến thể được cập nhật đúng; tổng tồn kho của sản phẩm cha được tính lại chính xác (ngoại lệ 7c) | I17: Positive | J17: Trung bình | K17: Tự động | L17: Mã 200; tồn kho 3 biến thể lần lượt đúng 5, 10, 15. Tổng tồn kho của sản phẩm cha chưa được kịch bản đối chiếu | M17: Pass | N17: Jest + Supertest | O17: 25/09/2026 | P17: Mức kiểm chứng hạn chế: chỉ kiểm tra một phần kết quả mong đợi (Bảng 3.37, dòng 2)
A18: PROD-017 | B18: Quản lý sản phẩm và tồn kho | C18: UC13 | D18: Quản trị viên duyệt sản phẩm chờ | E18: Có sản phẩm pending; đăng nhập admin@tigershop.test | F18: status = active | G18: 1. Gửi PATCH /api/products/:id/decision 2. Truy vấn products và user_activity_logs | H18: status chuyển thành active; sản phẩm xuất hiện trên gian hàng; nhật ký ghi lại quyết định (bước 4, 5) | I18: Positive | J18: Cao | K18: Tự động | L18: Mã 200; status = active; user_activity_logs có bản ghi mới chứa nội dung Duyệt sản phẩm | M18: Pass | N18: Jest + Supertest | O18: 25/09/2026
A19: PROD-018 | B19: Quản lý sản phẩm và tồn kho | C19: UC13 | D19: Quản trị viên từ chối sản phẩm kèm lý do | E19: Có sản phẩm pending | F19: status = hidden; reason = Anh san pham khong dat chuan | G19: 1. Gửi PATCH /api/products/:id/decision 2. Truy vấn status và rejection_reason | H19: status chuyển thành hidden và rejection_reason lưu đúng lý do (ngoại lệ 3a) | I19: Positive | J19: Cao | K19: Tự động | L19: Mã 200; status = hidden; rejection_reason đúng nội dung. Kịch bản PROD-018b xác nhận giá trị nằm ngoài active và hidden bị từ chối với mã 400, Trạng thái không hợp lệ (ngoại lệ 3b) | M19: Pass | N19: Jest + Supertest | O19: 25/09/2026
A20: PROD-019 | B20: Quản lý sản phẩm và tồn kho | C20: UC13 | D20: Nhân viên cố gọi điểm cuối duyệt sản phẩm | E20: Đăng nhập bằng tài khoản STAFF | F20: token của staff@tigershop.test | G20: 1. Gửi PATCH /api/products/:id/decision | H20: Mã 403 (ngoại lệ 1a) | I20: Security | J20: Cao | K20: Tự động | L20: Mã 403 | M20: Pass | N20: Jest + Supertest | O20: 25/09/2026
A21: PROD-020 | B21: Quản lý sản phẩm và tồn kho | C21: UC13 | D21: Đưa sản phẩm đã bị từ chối trở lại hàng đợi duyệt | E21: Có sản phẩm status = hidden | F21: Mã của sản phẩm bị từ chối | G21: 1. Mở danh sách sản phẩm đã quyết định 2. Chọn sản phẩm 3. Nhấn Gửi duyệt lại | H21: status trở về pending, rejection_reason bị xóa, sản phẩm xuất hiện lại trong danh sách chờ (ngoại lệ 6a) | I21: Positive | J21: Trung bình | K21: Tự động | L21: Chưa có kết quả; điểm cuối PATCH /api/products/:id/restore-pending thuộc 14 điểm cuối chưa được bộ kiểm thử gọi tới (Bảng 2.13) | M21: Chưa thực hiện | P21: Lý do: có thể kiểm thử ở mức API nhưng chưa có kịch bản (Bảng 3.38, dòng 5)
A22: PROD-021 | B22: Quản lý sản phẩm và tồn kho | C22: UC14 | D22: Xem cảnh báo tồn kho thấp | E22: Dữ liệu mẫu có 3 sản phẩm tồn kho 3, 2 và 1 | F22: token của manager@tigershop.test | G22: 1. Gửi GET /api/products/inventory-alert | H22: Danh sách sản phẩm chưa bị xóa có tồn kho dưới 5, sắp xếp tăng dần (bước 2), kèm số sản phẩm trong thùng rác | I22: Positive | J22: Cao | K22: Tự động | L22: Mã 200; mọi mục đều có stock dưới 5 và theo thứ tự tăng dần. Số sản phẩm trong thùng rác chưa được kiểm tra | M22: Pass | N22: Jest + Supertest | O22: 25/09/2026 | P22: Mức kiểm chứng hạn chế: chỉ kiểm tra một phần kết quả mong đợi (Bảng 3.37, dòng 2)
A23: PROD-022 | B23: Quản lý sản phẩm và tồn kho | C23: UC14 | D23: Nhập thêm hàng và kiểm tra nhật ký kho | E23: Đăng nhập Quản lý | F23: quantity = 50; note = Nhap bo sung | G23: 1. Gửi POST /api/users/inventory/restock 2. Truy vấn stock 3. Truy vấn inventory_logs | H23: Tồn kho tăng đúng 50; inventory_logs ghi old_stock, new_stock, quantity_added và manager_id (hậu điều kiện UC14) | I23: Positive | J23: Cao | K23: Tự động | L23: Tồn kho tăng đúng 50 so với giá trị ban đầu; bản ghi inventory_logs có old_stock, new_stock và quantity_added = 50 đúng. Cột manager_id chưa được kiểm tra | M23: Pass | N23: Jest + Supertest | O23: 25/09/2026 | P23: Mức kiểm chứng hạn chế: chỉ kiểm tra một phần kết quả mong đợi (Bảng 3.37, dòng 2)

Sheet ORD
A1: Mã TC | B1: Nhóm chức năng | C1: UC liên quan | D1: Tiêu đề kiểm thử | E1: Điều kiện tiên quyết | F1: Dữ liệu đầu vào | G1: Các bước thực hiện | H1: Kết quả mong đợi | I1: Loại KT | J1: Mức ưu tiên | K1: Phương pháp | L1: Kết quả thực tế | M1: Trạng thái | N1: Người thực hiện | O1: Ngày thực hiện | P1: Ghi chú
A2: ORD-001 | B2: Giỏ hàng và đơn hàng | C2: UC06 | D2: Thêm sản phẩm không có biến thể vào giỏ | E2: customer1 đã đăng nhập, sản phẩm còn hàng | F2: quantity = 2 | G2: 1. Mở trang chi tiết sản phẩm 2. Nhập số lượng 2 3. Nhấn Thêm vào giỏ | H2: Sản phẩm có trong giỏ với đúng số lượng; biểu tượng giỏ hàng cập nhật (bước 3) | I2: Positive | J2: Cao | K2: Tự động | L2: Chưa có kết quả | M2: Chưa thực hiện | P2: Lý do: chức năng nằm hoàn toàn ở giao diện, thuộc giai đoạn 6 chưa triển khai (Bảng 3.38, dòng 1)
A3: ORD-002 | B3: Giỏ hàng và đơn hàng | C3: UC06 | D3: Thêm sản phẩm có biến thể nhưng chưa chọn biến thể | E3: Sản phẩm có Size S, M, L | F3: Không chọn biến thể | G3: 1. Mở trang chi tiết 2. Nhấn Thêm vào giỏ | H3: Hiển thị cảnh báo; không thêm vào giỏ (ngoại lệ 1a) | I3: Negative | J3: Cao | K3: Tự động | L3: Chưa có kết quả | M3: Chưa thực hiện | P3: Lý do: chức năng nằm hoàn toàn ở giao diện, thuộc giai đoạn 6 chưa triển khai (Bảng 3.38, dòng 1)
A4: ORD-003 | B4: Giỏ hàng và đơn hàng | C4: UC06 | D4: Thêm số lượng vượt tồn kho | E4: San pham ton kho thap A còn 3 | F4: quantity = 10 | G4: 1. Nhập số lượng 10 2. Nhấn Thêm vào giỏ | H4: Cảnh báo và giới hạn số lượng theo tồn kho là 3 (ngoại lệ 2a) | I4: Boundary | J4: Cao | K4: Tự động | L4: Chưa có kết quả | M4: Chưa thực hiện | P4: Lý do: chức năng nằm hoàn toàn ở giao diện, thuộc giai đoạn 6 chưa triển khai (Bảng 3.38, dòng 1)
A5: ORD-004 | B5: Giỏ hàng và đơn hàng | C5: UC06 | D5: Nhập số lượng bằng 0 hoặc số âm | E5: Đang ở trang chi tiết sản phẩm | F5: quantity = 0; quantity = -1 | G5: 1. Nhập 0 rồi nhập -1 2. Nhấn Thêm vào giỏ | H5: Không cho phép thêm (ngoại lệ 2b) | I5: Boundary | J5: Trung bình | K5: Tự động | L5: Chưa có kết quả | M5: Chưa thực hiện | P5: Lý do: chức năng nằm hoàn toàn ở giao diện, thuộc giai đoạn 6 chưa triển khai (Bảng 3.38, dòng 1)
A6: ORD-005 | B6: Giỏ hàng và đơn hàng | C6: UC06 | D6: Cập nhật số lượng và xóa mục trong giỏ | E6: Giỏ có 2 mục | F6: Mục thứ nhất đổi thành 3; xóa mục thứ hai | G6: 1. Mở trang /cart 2. Tăng số lượng mục thứ nhất 3. Xóa mục thứ hai | H6: Tổng tiền tạm tính được tính lại đúng sau mỗi thao tác; mục bị xóa biến mất (bước 4, 5) | I6: Positive | J6: Cao | K6: Tự động | L6: Chưa có kết quả | M6: Chưa thực hiện | P6: Lý do: chức năng nằm hoàn toàn ở giao diện, thuộc giai đoạn 6 chưa triển khai (Bảng 3.38, dòng 1)
A7: ORD-006 | B7: Giỏ hàng và đơn hàng | C7: UC07 | D7: Đặt hàng thành công với COD | E7: customer1 đã đăng nhập; sản phẩm tồn kho 50 | F7: 2 sản phẩm; shipping_address = 123 Nguyen Trai, Ha Noi; payment_method = cod | G7: 1. Gửi POST /api/orders 2. Truy vấn tồn kho và bản ghi orders | H7: Mã 200 kèm orderId; đơn ở trạng thái pending với ngày giao dự kiến sau ba ngày; tồn kho giảm 2 (hậu điều kiện UC07) | I7: Positive | J7: Cao | K7: Tự động | L7: Mã 200, success = true, có orderId; expected_delivery đúng định dạng YYYY-MM-DD; status = pending, payment_method = cod; tồn kho giảm đúng 2. Giá trị cụ thể của ngày giao dự kiến chưa được đối chiếu | M7: Pass | N7: Jest + Supertest | O7: 25/09/2026 | P7: Mức kiểm chứng hạn chế: chỉ kiểm tra một phần kết quả mong đợi (Bảng 3.37, dòng 2)
A8: ORD-007 | B8: Giỏ hàng và đơn hàng | C8: UC07 | D8: Đặt hàng thành công với chuyển khoản QR | E8: Giỏ hàng có sản phẩm, đã đăng nhập | F8: payment_method = qr | G8: 1. Gửi POST /api/orders 2. Truy vấn orders | H8: Đơn có payment_method = qr; hội thoại hỗ trợ có thêm tin nhắn hệ thống (bước 4, 11) | I8: Positive | J8: Cao | K8: Tự động | L8: Mã 200; payment_method = qr. Tin nhắn hệ thống trong hội thoại chưa được kiểm tra | M8: Pass | N8: Jest + Supertest | O8: 25/09/2026 | P8: Mức kiểm chứng hạn chế: chỉ kiểm tra một phần kết quả mong đợi (Bảng 3.37, dòng 2)
A9: ORD-008 | B9: Giỏ hàng và đơn hàng | C9: UC07 | D9: Đặt hàng khi giỏ rỗng | E9: Đã đăng nhập, giỏ hàng không có sản phẩm | F9: items = mảng rỗng | G9: 1. Gửi POST /api/orders | H9: Mã 400, thông báo Giỏ hàng trống (ngoại lệ 7a) | I9: Negative | J9: Cao | K9: Tự động | L9: Mã 400, Giỏ hàng trống | M9: Pass | N9: Jest + Supertest | O9: 25/09/2026
A10: ORD-009 | B10: Giỏ hàng và đơn hàng | C10: UC07 | D10: Đặt hàng khi bỏ trống địa chỉ | E10: Giỏ hàng có sản phẩm | F10: shipping_address chỉ gồm khoảng trắng | G10: 1. Gửi POST /api/orders | H10: Mã 400, thông báo thiếu địa chỉ nhận hàng (ngoại lệ 7c) | I10: Negative | J10: Cao | K10: Tự động | L10: Mã 400, Thiếu địa chỉ nhận hàng | M10: Pass | N10: Jest + Supertest | O10: 25/09/2026
A11: ORD-010 | B11: Giỏ hàng và đơn hàng | C11: UC07 | D11: Đặt hàng với tổng tiền không hợp lệ | E11: Đã đăng nhập | F11: total = -50000; total = abc | G11: 1. Gửi với tổng tiền âm 2. Gửi với tổng tiền không phải số | H11: Cả hai trả mã 400 (ngoại lệ 7b) | I11: Negative | J11: Cao | K11: Tự động | L11: Cả hai trả mã 400, Tổng tiền không hợp lệ | M11: Pass | N11: Jest + Supertest | O11: 25/09/2026
A12: ORD-011 | B12: Giỏ hàng và đơn hàng | C12: UC07 | D12: Đặt hàng khi không gửi token | E12: Máy chủ đang chạy | F12: Không có header Authorization | G12: 1. Gửi POST /api/orders 2. Đếm số đơn trước và sau | H12: Mã 401; không tạo đơn (ngoại lệ 6a) | I12: Security | J12: Cao | K12: Tự động | L12: Mã 401; số đơn trong bảng orders không đổi | M12: Pass | N12: Jest + Supertest | O12: 25/09/2026
A13: ORD-012 | B13: Giỏ hàng và đơn hàng | C13: UC07 | D13: Đặt hàng vượt tồn kho | E13: San pham chi con mot cai có tồn kho 1 | F13: quantity = 5 | G13: 1. Gửi POST /api/orders 2. Kiểm tra orders, order_items và products | H13: Hoàn tác toàn bộ giao dịch, báo Hết hàng; không tạo orders và order_items; tồn kho giữ nguyên 1 (ngoại lệ 9a) | I13: Boundary | J13: Cao | K13: Tự động | L13: Mã 500, thông báo chứa Hết hàng; tồn kho vẫn là 1; không phát sinh bản ghi orders và order_items | M13: Pass | N13: Jest + Supertest | O13: 25/09/2026 | P13: Đề xuất trả mã 409 cho lỗi nghiệp vụ (mục 3.5.2)
A14: ORD-013 | B14: Giỏ hàng và đơn hàng | C14: UC07 | D14: Tính nguyên tử của giao dịch đặt hàng | E14: Đơn hàng gồm 2 sản phẩm, sản phẩm thứ hai không đủ tồn kho | F14: Mục 1: 1 sản phẩm còn 50; mục 2: 99 sản phẩm chỉ còn 1; total = 1000 | G14: 1. Gửi đơn gồm hai mục 2. Kiểm tra tồn kho của mục 1 và số đơn | H14: Toàn bộ giao dịch bị hoàn tác; tồn kho mục 1 không bị trừ dù đã được xử lý trước (ngoại lệ 9a) | I14: Negative | J14: Cao | K14: Tự động | L14: Mã 500; tồn kho mục 1 giữ nguyên; số đơn không đổi | M14: Pass | N14: Jest + Supertest | O14: 25/09/2026 | P14: Đề xuất trả mã 409 cho lỗi nghiệp vụ (mục 3.5.2)
A15: ORD-014 | B15: Giỏ hàng và đơn hàng | C15: UC07 | D15: Hai yêu cầu đồng thời cho sản phẩm tồn kho thấp | E15: Đặt lại tồn kho bằng 1 | F15: customer1 và customer2 cùng đặt 1 sản phẩm | G15: 1. Gửi đồng thời hai yêu cầu bằng Promise.all 2. Kiểm tra kết quả và tồn kho | H15: Chỉ một yêu cầu thành công; tồn kho về 0 và không âm, nhờ câu lệnh cập nhật có điều kiện stock lớn hơn hoặc bằng số lượng (bước 9) | I15: Boundary | J15: Cao | K15: Thủ công | L15: Đúng một yêu cầu trả mã 200; tồn kho bằng 0 | M15: Pass | N15: Jest + Supertest | O15: 25/09/2026 | P15: Thiết kế thủ công, đã thực hiện bằng kịch bản Jest (Bảng 3.4)
A16: ORD-015 | B16: Giỏ hàng và đơn hàng | C16: UC07 | D16: Tin nhắn hệ thống sau khi đặt hàng thành công | E16: Vừa đặt hàng thành công | F16: orderId vừa tạo | G16: 1. Đặt hàng 2. Mở hộp thoại hỗ trợ | H16: Hội thoại có tin nhắn hệ thống chứa mã đơn, tổng tiền, phương thức thanh toán; sự kiện new_message được phát (bước 11) | I16: Positive | J16: Trung bình | K16: Thủ công | L16: Chưa có kết quả; cần quan sát sự kiện thời gian thực trên trình duyệt | M16: Chưa thực hiện | P16: Lý do: cần hai phiên trình duyệt và sự kiện Socket.IO (rủi ro R08) (Bảng 3.38, dòng 3)
A17: ORD-016 | B17: Giỏ hàng và đơn hàng | C17: UC08 | D17: Xem danh sách đơn hàng của chính mình | E17: customer1 có 5 đơn mẫu và các đơn tạo trong lượt chạy | F17: token của customer1 | G17: 1. Gửi GET /api/orders/my 2. So với các đơn của customer1 trong cơ sở dữ liệu | H17: Mã 200; đủ các đơn của chính khách hàng, theo thời gian giảm dần (bước 2) | I17: Positive | J17: Cao | K17: Tự động | L17: Mã 200; tập orderId trả về trùng khớp tập đơn của customer1. Thứ tự sắp xếp chưa được kiểm tra | M17: Pass | N17: Jest + Supertest | O17: 25/09/2026 | P17: Mức kiểm chứng hạn chế: chỉ kiểm tra một phần kết quả mong đợi (Bảng 3.37, dòng 2)
A18: ORD-017 | B18: Giỏ hàng và đơn hàng | C18: UC08 | D18: Xem chi tiết đơn hàng | E18: Đơn thuộc về người dùng | F18: orderId của customer1 | G18: 1. Nhấn vào một đơn trong danh sách | H18: Trang /orders/:id hiển thị người nhận, mặt hàng, tổng tiền, phương thức thanh toán, trạng thái và ngày giao dự kiến (bước 4) | I18: Positive | J18: Cao | K18: Tự động | L18: Chưa có kết quả; kết quả mong đợi là nội dung hiển thị trên trang chi tiết đơn | M18: Chưa thực hiện | P18: Lý do: chức năng nằm hoàn toàn ở giao diện, thuộc giai đoạn 6 chưa triển khai (Bảng 3.38, dòng 1)
A19: ORD-018 | B19: Giỏ hàng và đơn hàng | C19: UC08 | D19: Truy cập đơn hàng của người dùng khác | E19: customer2 có đơn | F19: token của customer1; orderId của customer2 | G19: 1. Gửi GET /api/orders/:id | H19: Không trả dữ liệu đơn, trả mã 404 (ngoại lệ 3a) | I19: Security | J19: Cao | K19: Tự động | L19: Kịch bản chấp nhận mã 403 hoặc 404 và đạt; kịch bản tự bỏ qua bước kiểm tra nếu customer2 chưa có đơn, điều này phụ thuộc bên thắng ở ORD-014. Rà soát getOrderDetail xác nhận truy vấn lọc theo cả id và user_id, nên đơn của người khác nhận mã 404 | M19: Pass | N19: Jest + Supertest | O19: 25/09/2026 | P19: Mức kiểm chứng hạn chế: kịch bản có nhánh tự bỏ qua bước kiểm tra (Bảng 3.37, dòng 3)
A20: ORD-019 | B20: Giỏ hàng và đơn hàng | C20: UC08 | D20: Khách hàng hủy đơn đang pending | E20: Đơn hàng có status = pending thuộc về người dùng | F20: Đơn mới đặt gồm 2 sản phẩm | G20: 1. Đặt đơn 2. Gửi POST /api/orders/:id/cancel 3. Kiểm tra status và tồn kho | H20: Đơn chuyển sang cancelled; tồn kho được hoàn trả đúng số lượng (ngoại lệ 4a) | I20: Positive | J20: Cao | K20: Tự động | L20: Mã 200; status = cancelled; tồn kho tăng lại đúng 2 | M20: Pass | N20: Jest + Supertest | O20: 25/09/2026
A21: ORD-020 | B21: Giỏ hàng và đơn hàng | C21: UC08 | D21: Hủy đơn đã hoàn tất | E21: Đơn completed trong dữ liệu mẫu | F21: reason = Khach doi tra (cho nhân viên) | G21: 1. Khách hàng gửi POST /api/orders/:id/cancel 2. Nhân viên gửi POST /api/orders/staff/:id/cancel | H21: Cả hai bị từ chối; đơn giữ trạng thái completed (UC08 ngoại lệ 4b, UC11 ngoại lệ 4b) | I21: Negative | J21: Cao | K21: Tự động | L21: Khách hàng: mã 400, Chỉ có thể hủy đơn hàng ở trạng thái Pending. Nhân viên (kịch bản ORD-020b): mã 400, Không thể hủy đơn hàng đã completed. Đơn vẫn là completed | M21: Pass | N21: Jest + Supertest | O21: 25/09/2026
A22: ORD-021 | B22: Giỏ hàng và đơn hàng | C22: UC11 | D22: Nhân viên hủy đơn mà không nhập lý do | E22: staff@tigershop.test; có đơn pending | F22: reason rỗng | G22: 1. Gửi POST /api/orders/staff/:id/cancel | H22: Từ chối hủy đơn vì bỏ trống lý do (ngoại lệ 4b) | I22: Negative | J22: Cao | K22: Tự động | L22: Mã 400, Staff phải nhập lý do hủy đơn | M22: Pass | N22: Jest + Supertest | O22: 25/09/2026
A23: ORD-022 | B23: Giỏ hàng và đơn hàng | C23: UC11 | D23: Cập nhật trạng thái đơn theo tiến trình | E23: staff@tigershop.test; có đơn pending | F23: Lần lượt confirmed, shipping, completed; sau đó một giá trị nằm ngoài tập trạng thái | G23: 1. Gửi PUT /api/orders/admin/:id/status qua từng bước 2. Kiểm tra user_activity_logs 3. Gửi giá trị không hợp lệ | H23: Mỗi bước hợp lệ đều thành công, ghi người xử lý và nhật ký thao tác (bước 4, 5); giá trị nằm ngoài năm trạng thái hợp lệ hoặc đi ngược tiến trình bị từ chối (ngoại lệ 4a) | I23: Positive | J23: Cao | K23: Tự động | L23: Kịch bản STAT trong category_stats.test.js gửi giá trị processing bằng token nhân viên: máy chủ trả mã thành công và cột status nhận giá trị processing. Bước (1) và (2) chưa có kịch bản riêng | M23: Fail | N23: Jest + Supertest | O23: 25/09/2026 | P23: Khiếm khuyết DEF-11, mức Trung bình (Bảng 3.36); bằng chứng từ kịch bản nhóm STAT trong category_stats.test.js

Sheet VOUC
A1: Mã TC | B1: Nhóm chức năng | C1: UC liên quan | D1: Tiêu đề kiểm thử | E1: Điều kiện tiên quyết | F1: Dữ liệu đầu vào | G1: Các bước thực hiện | H1: Kết quả mong đợi | I1: Loại KT | J1: Mức ưu tiên | K1: Phương pháp | L1: Kết quả thực tế | M1: Trạng thái | N1: Người thực hiện | O1: Ngày thực hiện | P1: Ghi chú
A2: VOUC-001 | B2: Voucher và ví voucher | C2: UC10 | D2: Quản lý tạo voucher giảm theo phần trăm | E2: Đăng nhập manager@tigershop.test | F2: code = SALE[số ngẫu nhiên]; type = percent; value = 20; min_order_value = 200000; max_discount = 50000; quantity = 100; hiệu lực từ 01/01/2026 đến 31/12/2030 | G2: 1. Gửi POST /api/vouchers 2. Truy vấn bảng vouchers | H2: Voucher được tạo với status = active và used = 0 (bước 1) | I2: Positive | J2: Cao | K2: Tự động | L2: Yêu cầu thành công; đúng một bản ghi với status = active, used = 0 | M2: Pass | N2: Jest + Supertest | O2: 25/09/2026
A3: VOUC-002 | B3: Voucher và ví voucher | C3: UC10 | D3: Tạo voucher với mã đã tồn tại | E3: SALE20 có sẵn trong dữ liệu mẫu | F3: code = SALE20 | G3: 1. Gửi POST /api/vouchers 2. Đếm bản ghi có mã SALE20 | H3: Từ chối tạo; không có bản ghi thứ hai (ngoại lệ 1a) | I3: Negative | J3: Trung bình | K3: Tự động | L3: Yêu cầu bị từ chối (kịch bản kiểm tra mã từ 400 trở lên); vẫn chỉ có một bản ghi SALE20 | M3: Pass | N3: Jest + Supertest | O3: 25/09/2026 | P3: Mức kiểm chứng hạn chế: chỉ kiểm tra mã trạng thái (Bảng 3.37, dòng 1)
A4: VOUC-003 | B4: Voucher và ví voucher | C4: UC10 | D4: Khách hàng xem danh sách voucher công khai | E4: Tồn tại voucher active còn hiệu lực | F4: token của customer1 | G4: 1. Gửi GET /api/vouchers/public | H4: Chỉ gồm voucher đang hoạt động, còn hạn và còn lượt (bước 2) | I4: Positive | J4: Cao | K4: Tự động | L4: Mã 200; danh sách không chứa HETHAN (hết hạn) và HETLUOT (hết lượt) | M4: Pass | N4: Jest + Supertest | O4: 25/09/2026
A5: VOUC-004 | B5: Voucher và ví voucher | C5: UC10 | D5: Khách hàng nhận voucher vào ví | E5: customer2 chưa có GIAM50K | F5: voucherId của GIAM50K | G5: 1. Gửi POST /api/user-vouchers/receive/:voucherId 2. Truy vấn user_vouchers | H5: Bản ghi user_vouchers được tạo với used = 0 (bước 4) | I5: Positive | J5: Cao | K5: Tự động | L5: Yêu cầu thành công; đúng một bản ghi với used = 0 | M5: Pass | N5: Jest + Supertest | O5: 25/09/2026
A6: VOUC-005 | B6: Voucher và ví voucher | C6: UC10 | D6: Nhận lại voucher đã có trong ví | E6: customer1 đã có SALE20 | F6: voucherId của SALE20 | G6: 1. Gửi yêu cầu nhận lần nữa 2. Đếm bản ghi user_vouchers | H6: Không cho nhận lần hai; không tạo bản ghi trùng (ngoại lệ 3b) | I6: Negative | J6: Cao | K6: Tự động | L6: Vẫn một bản ghi. Nội dung phản hồi chưa được kịch bản kiểm tra | M6: Pass | N6: Jest + Supertest | O6: 25/09/2026 | P6: Mức kiểm chứng hạn chế: chỉ kiểm tra một phần kết quả mong đợi (Bảng 3.37, dòng 2)
A7: VOUC-006 | B7: Voucher và ví voucher | C7: UC10 | D7: Nhận voucher đã hết lượt | E7: Voucher có used bằng quantity | F7: voucherId của HETLUOT (used = quantity = 5) | G7: 1. Gửi POST /api/user-vouchers/receive/:voucherId | H7: Không cho nhận (ngoại lệ 3a) | I7: Negative | J7: Cao | K7: Tự động | L7: Mã 400, Voucher không hợp lệ hoặc đã hết | M7: Pass | N7: Jest + Supertest | O7: 25/09/2026
A8: VOUC-007 | B8: Voucher và ví voucher | C8: UC10 | D8: Nhận voucher đã hết hạn | E8: Voucher có end_date nhỏ hơn ngày hiện tại | F8: voucherId của HETHAN (end_date là ngày hôm trước) | G8: 1. Gửi POST /api/user-vouchers/receive/:voucherId | H8: Không cho nhận (ngoại lệ 3a) | I8: Boundary | J8: Cao | K8: Tự động | L8: Mã 400. Nội dung thông báo chưa được kịch bản kiểm tra | M8: Pass | N8: Jest + Supertest | O8: 25/09/2026 | P8: Mức kiểm chứng hạn chế: chỉ kiểm tra một phần kết quả mong đợi (Bảng 3.37, dòng 2)
A9: VOUC-008 | B9: Voucher và ví voucher | C9: UC10 | D9: Áp dụng voucher cho đơn đạt giá trị tối thiểu, mức giảm vượt trần | E9: Voucher SALE20 giảm 20 phần trăm, tối đa 50.000đ, đơn tối thiểu 200.000đ | F9: code = SALE20; total = 300000 | G9: 1. Gửi POST /api/vouchers/apply | H9: Mã 200; discount = 50000 do bị chặn bởi max_discount; finalTotal = 250000 (UC10 bước 5) | I9: Boundary | J9: Cao | K9: Tự động | L9: Mã 200; discount = 50000; finalTotal = 250000. Kịch bản VOUC-008b tại biên 200.000 đ cho discount = 40000 | M9: Pass | N9: Jest + Supertest | O9: 25/09/2026
A10: VOUC-009 | B10: Voucher và ví voucher | C10: UC10 | D10: Áp dụng voucher cho đơn dưới giá trị tối thiểu | E10: Voucher yêu cầu đơn tối thiểu 200.000đ | F10: code = SALE20; total = 150000 | G10: 1. Gửi POST /api/vouchers/apply | H10: Không áp dụng giảm giá, báo đơn chưa đạt giá trị tối thiểu (ngoại lệ 5a) | I10: Boundary | J10: Cao | K10: Tự động | L10: Mã 400, thông báo bắt đầu bằng Đơn tối thiểu. Theo mã nguồn, giá trị trong thông báo lấy thẳng từ cột DECIMAL nên hiển thị dạng 200000.00 thay vì 200.000 | M10: Pass | N10: Jest + Supertest | O10: 25/09/2026 | P10: Kịch bản VOUC-009c ghi nhận DEF-04
A11: VOUC-010 | B11: Voucher và ví voucher | C11: UC10 | D11: Áp dụng mã voucher không tồn tại | E11: Máy chủ đang chạy | F11: code = MAKHONGTONTAI; total = 500000 | G11: 1. Gửi POST /api/vouchers/apply | H11: Mã 400, thông báo Voucher không hợp lệ | I11: Negative | J11: Cao | K11: Tự động | L11: Mã 400, Voucher không hợp lệ | M11: Pass | N11: Jest + Supertest | O11: 25/09/2026 | P11: Kịch bản VOUC-010b ghi nhận DEF-09
A12: VOUC-011 | B12: Voucher và ví voucher | C12: UC07 | D12: Dùng voucher khi đặt hàng và đánh dấu đã dùng | E12: SALE20 có trong ví customer1, chưa dùng | F12: voucher_ids gồm mã của SALE20 | G12: 1. Gửi POST /api/orders kèm voucher 2. Truy vấn user_vouchers và vouchers | H12: Voucher trong ví được đánh dấu đã dùng, bộ đếm used tăng thêm 1, voucher chuyển không hoạt động khi hết lượt (UC07 bước 10) | I12: Positive | J12: Cao | K12: Tự động | L12: Mã 200; user_vouchers.used = 1; vouchers.used tăng đúng 1. Nhánh chuyển sang không hoạt động chưa được kiểm tra | M12: Pass | N12: Jest + Supertest | O12: 25/09/2026 | P12: Mức kiểm chứng hạn chế: chỉ kiểm tra một phần kết quả mong đợi (Bảng 3.37, dòng 2)
A13: VOUC-012 | B13: Voucher và ví voucher | C13: UC07 | D13: Dùng lại voucher đã sử dụng | E13: SALE20 vừa được dùng ở VOUC-011 | F13: voucher_ids gồm mã của SALE20 | G13: 1. Gửi POST /api/orders 2. Kiểm tra tồn kho và số đơn | H13: Hoàn tác giao dịch, báo Voucher không khả dụng; không tạo đơn, không trừ tồn kho (UC07 ngoại lệ 10a) | I13: Security | J13: Cao | K13: Tự động | L13: Mã 500, Voucher không khả dụng; tồn kho và số đơn không đổi | M13: Pass | N13: Jest + Supertest | O13: 25/09/2026 | P13: Đề xuất trả mã 409 cho lỗi nghiệp vụ (mục 3.5.2)

Sheet REV
A1: Mã TC | B1: Nhóm chức năng | C1: UC liên quan | D1: Tiêu đề kiểm thử | E1: Điều kiện tiên quyết | F1: Dữ liệu đầu vào | G1: Các bước thực hiện | H1: Kết quả mong đợi | I1: Loại KT | J1: Mức ưu tiên | K1: Phương pháp | L1: Kết quả thực tế | M1: Trạng thái | N1: Người thực hiện | O1: Ngày thực hiện | P1: Ghi chú
A2: REV-001 | B2: Đánh giá sản phẩm | C2: UC09 | D2: Đánh giá sản phẩm đã mua | E2: customer1 có đơn completed chứa sản phẩm trong dữ liệu mẫu | F2: rating = 5; comment = San pham rat tot | G2: 1. Gửi POST /api/products/:id/reviews 2. Truy vấn product_reviews | H2: Mã 200, thông báo Đã lưu đánh giá sản phẩm; đánh giá được lưu (bước 6) | I2: Positive | J2: Cao | K2: Tự động | L2: Mã 200, Đã lưu đánh giá sản phẩm; bản ghi có rating = 5 và đúng nội dung | M2: Pass | N2: Jest + Supertest | O2: 25/09/2026
A3: REV-002 | B3: Đánh giá sản phẩm | C3: UC09 | D3: Số sao nằm ngoài khoảng cho phép | E3: Khách hàng đủ điều kiện đánh giá | F3: rating = 0; rating = 6 | G3: 1. Gửi với điểm 0 2. Gửi với điểm 6 | H3: Cả hai trả mã 400 (ngoại lệ 2a) | I3: Boundary | J3: Cao | K3: Tự động | L3: Cả hai trả mã 400, Rating phải từ 1 đến 5. Kịch bản REV-002b xác nhận hai giá trị biên 1 và 5 được chấp nhận | M3: Pass | N3: Jest + Supertest | O3: 25/09/2026
A4: REV-003 | B4: Đánh giá sản phẩm | C4: UC09 | D4: Đánh giá sản phẩm chưa từng mua | E4: customer2 chưa có đơn nào chứa sản phẩm | F4: rating = 5 | G4: 1. Gửi POST /api/products/:id/reviews | H4: Mã 403, thông báo Đánh giá chỉ khả dụng khi đơn đã hoàn tất (ngoại lệ 5a) | I4: Security | J4: Cao | K4: Tự động | L4: Mã 403, Đánh giá chỉ khả dụng khi đơn đã hoàn tất | M4: Pass | N4: Jest + Supertest | O4: 25/09/2026
A5: REV-004 | B5: Đánh giá sản phẩm | C5: UC09 | D5: Cập nhật đánh giá đã có | E5: customer1 đã đánh giá sản phẩm | F5: rating = 3; comment = Dung mot tuan thay binh thuong | G5: 1. Gửi đánh giá lần hai 2. Đếm và đọc bản ghi product_reviews | H5: Cập nhật đánh giá cũ thay vì tạo mới, nhờ ràng buộc duy nhất (product_id, user_id) (ngoại lệ 6a) | I5: Positive | J5: Cao | K5: Tự động | L5: Mã 200; số bản ghi không đổi; rating = 3 và comment mới. Cột updated_at chưa được kiểm tra | M5: Pass | N5: Jest + Supertest | O5: 25/09/2026 | P5: Mức kiểm chứng hạn chế: chỉ kiểm tra một phần kết quả mong đợi (Bảng 3.37, dòng 2)
A6: REV-005 | B6: Đánh giá sản phẩm | C6: UC09 | D6: Đánh giá kèm ảnh minh họa | E6: Khách hàng đủ điều kiện đánh giá | F6: rating = 4; review.png | G6: 1. Gửi đánh giá kèm tệp ảnh 2. Truy vấn image_url | H6: Ảnh được lưu vào thư mục uploads, đường dẫn ghi vào image_url (bước 3) | I6: Positive | J6: Trung bình | K6: Tự động | L6: Mã 200; image_url bắt đầu bằng uploads/ | M6: Pass | N6: Jest + Supertest | O6: 25/09/2026
A7: REV-006 | B7: Đánh giá sản phẩm | C7: UC09 | D7: Nhân viên cố gửi đánh giá | E7: Đăng nhập bằng tài khoản STAFF | F7: token của staff@tigershop.test | G7: 1. Gửi POST /api/products/:id/reviews | H7: Mã 403; chỉ khách hàng được đánh giá (tác nhân của UC09) | I7: Security | J7: Cao | K7: Tự động | L7: Mã 403, Chỉ khách hàng mới được đánh giá sản phẩm | M7: Pass | N7: Jest + Supertest | O7: 25/09/2026
A8: REV-007 | B8: Đánh giá sản phẩm | C8: UC09 | D8: Xem danh sách đánh giá của sản phẩm | E8: Sản phẩm đã có đánh giá | F8: Mã sản phẩm đã đánh giá ở REV-001 | G8: 1. Gửi GET /api/products/:id/reviews | H8: Mã 200; đủ tên người đánh giá, số sao, nội dung và ảnh nếu có | I8: Positive | J8: Trung bình | K8: Tự động | L8: Mã 200; danh sách có ít nhất một đánh giá. Các trường của từng đánh giá chưa được kiểm tra | M8: Pass | N8: Jest + Supertest | O8: 25/09/2026 | P8: Mức kiểm chứng hạn chế: chỉ kiểm tra một phần kết quả mong đợi (Bảng 3.37, dòng 2)
A9: REV-008 | B9: Đánh giá sản phẩm | C9: UC09 | D9: Đánh giá khi đơn thanh toán QR chưa hoàn tất | E9: customer2 vừa đặt đơn QR, đơn có status = pending | F9: rating = 5; comment = Danh gia khi don QR con pending | G9: 1. Đặt đơn QR 2. Xác nhận đơn đang pending 3. Gửi đánh giá cho sản phẩm trong đơn | H9: Mã 200, đánh giá được lưu, vì đơn thanh toán bằng chuyển khoản QR thỏa tiền điều kiện của UC09 | I9: Negative | J9: Cao | K9: Thủ công | L9: Mã 200, đánh giá được lưu khi đơn QR vẫn ở trạng thái pending | M9: Pass | N9: Jest + Supertest | O9: 25/09/2026 | P9: Đơn QR thỏa tiền điều kiện UC09 theo mục 1.1.2; Thiết kế thủ công, đã thực hiện bằng kịch bản Jest (Bảng 3.4)

Sheet CHAT
A1: Mã TC | B1: Nhóm chức năng | C1: UC liên quan | D1: Tiêu đề kiểm thử | E1: Điều kiện tiên quyết | F1: Dữ liệu đầu vào | G1: Các bước thực hiện | H1: Kết quả mong đợi | I1: Loại KT | J1: Mức ưu tiên | K1: Phương pháp | L1: Kết quả thực tế | M1: Trạng thái | N1: Người thực hiện | O1: Ngày thực hiện | P1: Ghi chú
A2: CHAT-001 | B2: Chat hỗ trợ thời gian thực | C2: UC21 | D2: Tự động tạo hội thoại khi khách hàng mở hộp thoại hỗ trợ | E2: customer1 chưa có hội thoại | F2: token của customer1 | G2: 1. Gửi GET /api/chat/my-thread hai lần 2. Đếm bản ghi threads của customer1 | H2: Lần đầu tạo một hội thoại ở trạng thái open; lần sau dùng lại đúng hội thoại cũ, mỗi khách hàng có đúng một hội thoại (bước 2) | I2: Positive | J2: Cao | K2: Tự động | L2: Mã 200; hai lần trả về cùng một id; bảng threads có đúng một bản ghi của customer1 | M2: Pass | N2: Jest + Supertest | O2: 25/09/2026
A3: CHAT-002 | B3: Chat hỗ trợ thời gian thực | C3: UC21 | D3: Khách hàng gửi tin nhắn cho nhân viên | E3: Hội thoại đã tồn tại | F3: content = Cho minh hoi ve don hang | G3: 1. Gửi POST /api/chat/messages 2. Truy vấn chat_messages | H3: Tin nhắn được lưu và phát sự kiện new_message tới phòng hội thoại (bước 5) | I3: Positive | J3: Cao | K3: Tự động | L3: Yêu cầu thành công; sender_role = USER, nội dung đúng. Sự kiện Socket.IO chưa kiểm chứng. Kịch bản CHAT-002b xác nhận tin nhắn chỉ gồm khoảng trắng bị từ chối với mã 400 | M3: Pass | N3: Jest + Supertest | O3: 25/09/2026 | P3: Mức kiểm chứng hạn chế: phần giao diện hoặc thời gian thực chưa kiểm chứng (Bảng 3.37, dòng 4)
A4: CHAT-003 | B4: Chat hỗ trợ thời gian thực | C4: UC21 | D4: Khách hàng yêu cầu gặp nhân viên | E4: Hội thoại đã tồn tại | F4: threadId hợp lệ | G4: 1. Nhấn Gặp nhân viên 2. Quan sát trạng thái hội thoại và màn hình nhân viên | H4: Hội thoại chuyển sang staff_needed và sự kiện request_staff được phát tới nhân viên (bước 3) | I4: Positive | J4: Cao | K4: Thủ công | L4: Chưa đủ kết quả. Kịch bản CHAT2-001 mới xác nhận phần máy chủ: status = staff_needed, is_human_needed = 1. Phần phát sự kiện tới nhân viên chưa kiểm chứng | M4: Chưa thực hiện | P4: Lý do: cần hai phiên trình duyệt và sự kiện Socket.IO (rủi ro R08) (Bảng 3.38, dòng 3)
A5: CHAT-004 | B5: Chat hỗ trợ thời gian thực | C5: UC21 | D5: Nhân viên trả lời và khách hàng nhận tin theo thời gian thực | E5: Hai trình duyệt đang mở | F5: message = Chao ban, minh ho tro ngay | G5: 1. Nhân viên gửi tin 2. Quan sát màn hình khách hàng mà không tải lại trang | H5: Tin nhắn xuất hiện tức thì trên màn hình khách hàng (bước 5) | I5: Positive | J5: Cao | K5: Thủ công | L5: Chưa có kết quả | M5: Chưa thực hiện | P5: Lý do: cần hai phiên trình duyệt và sự kiện Socket.IO (rủi ro R08) (Bảng 3.38, dòng 3)
A6: CHAT-005 | B6: Chat hỗ trợ thời gian thực | C6: UC21 | D6: Giới hạn tần suất gửi tin qua Socket.IO | E6: Hội thoại đang mở | F6: 8 tin nhắn liên tiếp trong 60 giây | G6: 1. Gửi liên tục 8 tin 2. Ghi nhận phản hồi | H6: Năm tin đầu được xử lý; từ tin thứ 6 bị chặn tạm thời (ngoại lệ 5a) | I6: Security | J6: Trung bình | K6: Thủ công | L6: Chưa có kết quả | M6: Chưa thực hiện | P6: Lý do: cần hai phiên trình duyệt và sự kiện Socket.IO (rủi ro R08) (Bảng 3.38, dòng 3)
A7: CHAT-006 | B7: Chat hỗ trợ thời gian thực | C7: UC21 | D7: Tự động kết nối lại khi mất kết nối WebSocket | E7: Hội thoại đang mở | F7: Ngắt mạng 10 giây rồi khôi phục | G7: 1. Ngắt mạng 2. Chờ 10 giây 3. Khôi phục mạng và gửi tin mới | H7: Giao diện tự kết nối lại; tin mới gửi thành công; không mất lịch sử (ngoại lệ 5b) | I7: Negative | J7: Trung bình | K7: Thủ công | L7: Chưa có kết quả | M7: Chưa thực hiện | P7: Lý do: cần hai phiên trình duyệt và sự kiện Socket.IO (rủi ro R08) (Bảng 3.38, dòng 3)
A8: CHAT-007 | B8: Chat hỗ trợ thời gian thực | C8: UC21 | D8: Xem danh sách hội thoại hỗ trợ | E8: Đã có hội thoại của customer1 | F8: token của admin (điểm cuối cho phép ADMIN, MANAGER, STAFF) | G8: 1. Gửi GET /api/chat/admin/threads | H8: Danh sách hội thoại kèm email khách hàng và thời điểm tin nhắn cuối, sắp xếp giảm dần (ngoại lệ 7a) | I8: Positive | J8: Cao | K8: Tự động | L8: Mã 200; mỗi phần tử có threadId, userId, email. Thứ tự sắp xếp chưa được kiểm tra | M8: Pass | N8: Jest + Supertest | O8: 25/09/2026 | P8: Mức kiểm chứng hạn chế: chỉ kiểm tra một phần kết quả mong đợi (Bảng 3.37, dòng 2)
A9: CHAT-008 | B9: Chat hỗ trợ thời gian thực | C9: UC21 | D9: Xem nhanh đơn hàng của khách trong khung hội thoại | E9: customer1 có đơn | F9: userId của customer1; token của admin | G9: 1. Gửi GET /api/chat/admin/users/:userId/orders | H9: Trả về đúng danh sách đơn của khách hàng đó (bước 7) | I9: Positive | J9: Trung bình | K9: Tự động | L9: Mã 200. Nội dung danh sách chưa được đối chiếu | M9: Pass | N9: Jest + Supertest | O9: 25/09/2026 | P9: Mức kiểm chứng hạn chế: chỉ kiểm tra mã trạng thái (Bảng 3.37, dòng 1)
A10: CHAT-009 | B10: Chat hỗ trợ thời gian thực | C10: UC21 | D10: Khách hàng cố đọc hội thoại không thuộc về mình | E10: customer2 có hội thoại chứa tin nhắn riêng | F10: token của customer1; threadId của customer2; tin nhắn mẫu Thong tin rieng tu cua khach hang 2 | G10: 1. Gửi GET /api/chat/messages/:threadId bằng token của customer1 | H10: Hệ thống từ chối; chỉ chủ hội thoại, nhân viên và Quản trị viên được đọc (ngoại lệ 5c) | I10: Security | J10: Cao | K10: Tự động | L10: Mã 200; phản hồi chứa nguyên văn tin nhắn riêng tư của customer2 | M10: Fail | N10: Jest + Supertest | O10: 25/09/2026 | P10: Khiếm khuyết DEF-08, trùng VUL-01, mức Nghiêm trọng (Bảng 3.36)
A11: CHAT-010 | B11: Chat hỗ trợ thời gian thực | C11: UC22 | D11: Nhận thông báo khi trạng thái đơn hàng thay đổi | E11: Khách hàng có đơn đang xử lý | F11: Nhân viên đổi đơn sang shipping | G11: 1. Nhân viên cập nhật trạng thái đơn 2. Khách hàng quan sát biểu tượng chuông | H11: notifications có bản ghi cho đúng người dùng; số chưa đọc trên biểu tượng chuông tăng 1 (bước 1, 2) | I11: Positive | J11: Cao | K11: Thủ công | L11: Chưa có kết quả; cần quan sát giao diện khách hàng trong lúc nhân viên thao tác | M11: Chưa thực hiện | P11: Lý do: cần hai phiên trình duyệt và sự kiện Socket.IO (rủi ro R08) (Bảng 3.38, dòng 3)
A12: CHAT-011 | B12: Chat hỗ trợ thời gian thực | C12: UC22 | D12: Đánh dấu đã đọc và bộ lọc loại thông báo | E12: customer1 có thông báo chưa đọc | F12: Chèn 1 thông báo loại order và 1 thông báo loại low_stock chưa đọc | G12: 1. Gửi GET /api/notifications/unread 2. Gửi GET /api/notifications 3. Gửi PUT /api/notifications/mark-read 4. Đếm lại | H12: Số chưa đọc không tính các loại admin_report, low_stock, revenue (ngoại lệ 2b); sau khi đánh dấu, số chưa đọc về 0 (bước 4) | I12: Positive | J12: Trung bình | K12: Tự động | L12: count = 1 (không tính low_stock); sau khi đánh dấu, count = 0. Kịch bản CHAT-011b xác nhận customer1 không thấy thông báo của customer2 (ngoại lệ 3a) | M12: Pass | N12: Jest + Supertest | O12: 25/09/2026

Sheet AI
A1: Mã TC | B1: Nhóm chức năng | C1: UC liên quan | D1: Tiêu đề kiểm thử | E1: Điều kiện tiên quyết | F1: Dữ liệu đầu vào | G1: Các bước thực hiện | H1: Kết quả mong đợi | I1: Loại KT | J1: Mức ưu tiên | K1: Phương pháp | L1: Kết quả thực tế | M1: Trạng thái | N1: Người thực hiện | O1: Ngày thực hiện | P1: Ghi chú
A2: AI-001 | B2: Trợ lý ảo Tiger AI | C2: UC20 | D2: Gửi câu hỏi tư vấn hợp lệ | E2: Đã cấu hình GEMINI_API_KEY; kho có sản phẩm còn hàng | F2: message = Minh muon tim ao khoac mua dong duoi 500 nghin | G2: 1. Gửi POST /api/chat/ai/talk | H2: Mã 200 kèm câu trả lời; chỉ dẫn hệ thống gửi cho mô hình gemini-2.5-flash chứa danh mục sản phẩm đang hoạt động, chưa bị xóa và còn hàng (bước 5, 6, 8) | I2: Positive | J2: Cao | K2: Thủ công | L2: Mã 200, reply không rỗng, mô hình được gọi đúng một lần. Kịch bản AI-001b xác nhận chỉ dẫn hệ thống chứa tên sản phẩm còn hàng có thật và mô hình được chọn là gemini-2.5-flash | M2: Pass | N2: Jest + Supertest | O2: 25/09/2026 | P2: Thiết kế thủ công, đã thực hiện bằng kịch bản Jest (Bảng 3.4)
A3: AI-002 | B3: Trợ lý ảo Tiger AI | C3: UC20 | D3: Gửi tin nhắn rỗng | E3: customer1 đã đăng nhập | F3: message rỗng; message chỉ gồm khoảng trắng | G3: 1. Gửi hai tin nhắn | H3: Mã 400 (ngoại lệ 2a) | I3: Negative | J3: Cao | K3: Tự động | L3: Cả hai trả mã 400, Tin nhắn không được để trống; mô hình không bị gọi | M3: Pass | N3: Jest + Supertest | O3: 25/09/2026
A4: AI-003 | B4: Trợ lý ảo Tiger AI | C4: UC20 | D4: Lưu lịch sử hội thoại | E4: Đã gửi ít nhất 1 câu hỏi | F4: message = Cau hoi luu lich su | G4: 1. Gửi câu hỏi 2. Truy vấn ai_chat_messages | H4: Câu hỏi (vai USER) và câu trả lời (vai AI) được lưu (bước 7) | I4: Positive | J4: Cao | K4: Tự động | L4: Tổng số tin tăng đúng 2; hai bản ghi mới có role USER và AI | M4: Pass | N4: Jest + Supertest | O4: 25/09/2026
A5: AI-004 | B5: Trợ lý ảo Tiger AI | C5: UC20 | D5: Mỗi người dùng chỉ có một phiên AI | E5: Người dùng đã có phiên AI | F5: Gửi 3 câu hỏi liên tiếp | G5: 1. Gửi 3 câu hỏi 2. Đếm ai_chat_sessions của customer1 | H5: Đúng một bản ghi phiên, được dùng lại (hậu điều kiện UC20) | I5: Positive | J5: Cao | K5: Tự động | L5: Đúng một bản ghi | M5: Pass | N5: Jest + Supertest | O5: 25/09/2026
A6: AI-005 | B6: Trợ lý ảo Tiger AI | C6: UC20 | D6: Duy trì ngữ cảnh nhiều lượt | E6: Đã có lịch sử hội thoại | F6: message = Cai do con size L khong | G6: 1. Gửi câu hỏi dùng đại từ thay thế | H6: 10 tin nhắn gần nhất được nạp và chuẩn hóa thành hội thoại nhiều lượt gửi kèm yêu cầu tới mô hình (bước 4) | I6: Positive | J6: Cao | K6: Thủ công | L6: Lịch sử gửi kèm mô hình không rỗng, bắt đầu bằng lượt của người dùng và không quá 10 tin | M6: Pass | N6: Jest + Supertest | O6: 25/09/2026 | P6: Thiết kế thủ công, đã thực hiện bằng kịch bản Jest (Bảng 3.4)
A7: AI-006 | B7: Trợ lý ảo Tiger AI | C7: UC20 | D7: Hỏi về sản phẩm không có trong kho | E7: Kho hàng không có sản phẩm loại này | F7: message = Shop co ban xe may khong | G7: 1. Gửi câu hỏi | H7: Trợ lý trả lời trung thực là không có, không bịa sản phẩm | I7: Negative | J7: Cao | K7: Thủ công | L7: Chưa có kết quả; nội dung câu trả lời phụ thuộc chất lượng của Gemini, chỉ đánh giá được khi gọi dịch vụ thật | M7: Chưa thực hiện | P7: Lý do: kết quả mong đợi thuộc chất lượng nội tại của Gemini (Bảng 2.3) (Bảng 3.38, dòng 4)
A8: AI-007 | B8: Trợ lý ảo Tiger AI | C8: UC20 | D8: Xử lý khi thiếu khóa API Gemini | E8: Xóa hoặc để trống biến môi trường GEMINI_API_KEY | F8: Xóa biến môi trường GEMINI_API_KEY; message = Xin chao | G8: 1. Gửi câu hỏi khi thiếu khóa | H8: Phản hồi success: false kèm thông báo Tiger AI đang bảo trì; hệ thống không sập (ngoại lệ 3a; mục 1.3.6) | I8: Negative | J8: Cao | K8: Thủ công | L8: Mã 200, success = false, thông báo chứa cụm bảo trì; mô hình không bị gọi | M8: Pass | N8: Jest + Supertest | O8: 25/09/2026 | P8: Trả mã 200 cho phản hồi thất bại, ghi nhận PERF-04 ở Chương V; Thiết kế thủ công, đã thực hiện bằng kịch bản Jest (Bảng 3.4)
A9: AI-008 | B9: Trợ lý ảo Tiger AI | C9: UC20 | D9: Thời gian phản hồi của trợ lý ảo | E9: Đã cấu hình GEMINI_API_KEY; gọi dịch vụ Gemini thật, không giả lập | F9: 10 câu hỏi khác nhau (thực tế đo 6 câu) | G9: 1. Gửi tuần tự từng câu tới Gemini thật 2. Ghi thời gian từ lúc gửi tới lúc nhận đủ câu trả lời | H9: Thời gian phản hồi trung bình dưới 5.000 ms (Bảng 1.31, chỉ tiêu 3) | I9: Positive | J9: Cao | K9: Thủ công | L9: Đo 6 lượt (mục 5.4.5): trung bình 5.017 ms; 1 trên 6 lượt nhận thông báo bảo trì thay vì câu trả lời. Cỡ mẫu nhỏ hơn thiết kế | M9: Fail | N9: Đo trực tiếp với Gemini thật | O9: 25/09/2026 | P9: Khiếm khuyết PERF-03, mức Trung bình (Bảng 3.36); cỡ mẫu 6 lượt, nhỏ hơn 10 lượt đã thiết kế; Thiết kế thủ công, thực hiện bằng phép đo riêng 6 lượt (mục 5.4.5)
A10: AI-009 | B10: Trợ lý ảo Tiger AI | C10: UC20 | D10: Gợi ý voucher theo từ khóa | E10: Hệ thống hoạt động bình thường | F10: message = Sản phẩm này hơi đắt so với mình | G10: 1. Gửi câu hỏi có từ khóa đắt | H10: Phản hồi kèm gợi ý mã TIGER_PROMO_10 (ngoại lệ 8a) | I10: Positive | J10: Trung bình | K10: Tự động | L10: Mã 200; voucher = TIGER_PROMO_10. Kịch bản AI-009b xác nhận câu hỏi thông thường không kèm voucher | M10: Pass | N10: Jest + Supertest | O10: 25/09/2026 | P10: Kịch bản AI-009c ghi nhận DEF-10
A11: AI-010 | B11: Trợ lý ảo Tiger AI | C11: UC20 | D11: Xóa lịch sử hội thoại với trợ lý | E11: Người dùng có lịch sử hội thoại | F11: token của customer1 | G11: 1. Gửi DELETE /api/chat/ai/history 2. Đếm ai_chat_messages và ai_chat_sessions | H11: Toàn bộ tin nhắn của phiên bị xóa; bản ghi phiên được giữ lại (ngoại lệ 8b) | I11: Positive | J11: Trung bình | K11: Tự động | L11: Mã 200; ai_chat_messages về 0; ai_chat_sessions vẫn là 1. Kịch bản AI-010b xác nhận lịch sử mới được ghi lại bình thường sau khi xóa | M11: Pass | N11: Jest + Supertest | O11: 25/09/2026

Sheet HR
A1: Mã TC | B1: Nhóm chức năng | C1: UC liên quan | D1: Tiêu đề kiểm thử | E1: Điều kiện tiên quyết | F1: Dữ liệu đầu vào | G1: Các bước thực hiện | H1: Kết quả mong đợi | I1: Loại KT | J1: Mức ưu tiên | K1: Phương pháp | L1: Kết quả thực tế | M1: Trạng thái | N1: Người thực hiện | O1: Ngày thực hiện | P1: Ghi chú
A2: HR-001 | B2: Ca làm, chấm công và lương | C2: UC15 | D2: Nhân viên vào ca thành công | E2: staff@tigershop.test là nhân viên chính thức, không có phiên đang mở | F2: token của staff | G2: 1. Gửi POST /api/users/attendance/clock-in 2. Truy vấn attendance_sessions | H2: Mã 201 kèm session_id; phiên mới có status = open, wage_rate đúng theo employment_status (bước 4, 5) | I2: Positive | J2: Cao | K2: Tự động | L2: Mã 201; session_id là số; status = open; check_out_at là NULL; wage_rate = 25000 | M2: Pass | N2: Jest + Supertest | O2: 25/09/2026
A3: HR-002 | B3: Ca làm, chấm công và lương | C3: UC15 | D3: Vào ca lần hai khi đang có ca chưa đóng | E3: Đã vào ca ở HR-001 | F3: token của staff | G3: 1. Gửi lại POST /api/users/attendance/clock-in | H3: Mã 400 kèm thông báo còn ca làm chưa kết thúc; không tạo phiên thứ hai (ngoại lệ 3a) | I3: Negative | J3: Cao | K3: Tự động | L3: Mã 400, Bạn đang có ca làm chưa check-out | M3: Pass | N3: Jest + Supertest | O3: 25/09/2026
A4: HR-003 | B4: Ca làm, chấm công và lương | C4: UC15 | D4: Tài khoản không phải Nhân viên cố chấm công | E4: Đăng nhập bằng tài khoản CUSTOMER hoặc MANAGER | F4: token của customer1 và của manager | G4: 1. Gửi POST /api/users/attendance/clock-in bằng từng token | H4: Mã 403, thông báo Chỉ Staff được chấm công (ngoại lệ 2a) | I4: Security | J4: Cao | K4: Tự động | L4: Cả hai tài khoản nhận mã 403 với đúng thông báo | M4: Pass | N4: Jest + Supertest | O4: 25/09/2026
A5: HR-004 | B5: Ca làm, chấm công và lương | C5: UC15 | D5: Nhân viên chưa được duyệt cố chấm công | E5: Tài khoản STAFF có status khác active | F5: staff.pending@tigershop.test (status = pending) | G5: 1. Đăng nhập 2. Gửi POST /api/users/attendance/clock-in | H5: Nhân viên chưa được duyệt không chấm công được, bị chặn với mã 403 (UC15 ngoại lệ 2b; UC02 ngoại lệ 5a) | I5: Security | J5: Cao | K5: Tự động | L5: Tài khoản bị chặn ngay ở bước đăng nhập với mã 403, thông báo Tài khoản đang chờ duyệt, nên không có token để gọi điểm cuối chấm công. Nhánh kiểm tra Staff chưa active tại điểm cuối chấm công chưa được kích hoạt | M5: Pass | N5: Jest + Supertest | O5: 25/09/2026 | P5: Mức kiểm chứng hạn chế: kịch bản có nhánh tự bỏ qua bước kiểm tra (Bảng 3.37, dòng 3)
A6: HR-005 | B6: Ca làm, chấm công và lương | C6: UC15 | D6: Kết thúc ca và tính số giây làm việc | E6: Có phiên đang mở từ HR-001 | F6: token của staff | G6: 1. Gửi POST /api/users/attendance/clock-out 2. Truy vấn phiên vừa đóng | H6: Phiên chuyển sang closed; check_out_at là thời điểm kết thúc ca; worked_seconds tính bằng TIMESTAMPDIFF (bước 7) | I6: Positive | J6: Cao | K6: Tự động | L6: Mã 200; status = closed; check_out_at có giá trị; worked_seconds không âm. Kịch bản không chờ 60 giây như thiết kế nên chưa đối chiếu giá trị cụ thể | M6: Pass | N6: Jest + Supertest | O6: 25/09/2026 | P6: Mức kiểm chứng hạn chế: chỉ kiểm tra một phần kết quả mong đợi (Bảng 3.37, dòng 2)
A7: HR-006 | B7: Ca làm, chấm công và lương | C7: UC15 | D7: Kết thúc ca khi không có ca nào đang mở | E7: Đã kết thúc ca ở HR-005 | F7: token của staff | G7: 1. Gửi POST /api/users/attendance/clock-out | H7: Mã 400 (ngoại lệ 6a) | I7: Negative | J7: Cao | K7: Tự động | L7: Mã 400, Không có ca làm đang mở để check-out | M7: Pass | N7: Jest + Supertest | O7: 25/09/2026
A8: HR-007 | B8: Ca làm, chấm công và lương | C8: UC15 | D8: Đơn giá giờ công theo trạng thái lao động | E8: Một nhân viên thử việc và một nhân viên chính thức | F8: probation_hourly_rate = 20000; official_hourly_rate = 25000 | G8: 1. Cho staff.probation@tigershop.test vào ca 2. So sánh wage_rate với phiên của HR-001 | H8: Phiên của nhân viên thử việc có wage_rate = 20000; phiên của nhân viên chính thức có wage_rate = 25000 (bước 4) | I8: Positive | J8: Cao | K8: Tự động | L8: Phiên thử việc có wage_rate = 20000; phiên chính thức ở HR-001 có wage_rate = 25000 | M8: Pass | N8: Jest + Supertest | O8: 25/09/2026
A9: HR-008 | B9: Ca làm, chấm công và lương | C9: UC16 | D9: Nhân viên đăng ký ca làm việc | E9: Đăng nhập staff@tigershop.test | F9: shift_date = ngày mai; start_time = 08:00; end_time = 17:00; note = Ca sang | G9: 1. Gửi POST /api/shifts/register 2. Truy vấn shift_registrations | H9: Bản ghi đăng ký ca được tạo ở trạng thái pending (bước 3) | I9: Positive | J9: Cao | K9: Tự động | L9: Yêu cầu thành công; status = pending. Kịch bản HR-008b xác nhận thiếu trường bắt buộc bị từ chối với mã 400; HR-008c xác nhận nhân viên xem được ca của mình | M9: Pass | N9: Jest + Supertest | O9: 25/09/2026
A10: HR-009 | B10: Ca làm, chấm công và lương | C10: UC16 | D10: Đăng ký ca với giờ kết thúc sớm hơn giờ bắt đầu | E10: Đăng nhập bằng STAFF | F10: start_time = 17:00; end_time = 08:00 | G10: 1. Nhập khung giờ không hợp lý 2. Nhấn Đăng ký | H10: Từ chối đăng ký vì giờ kết thúc không sau giờ bắt đầu (ngoại lệ 1a; Hình 1.14) | I10: Negative | J10: Cao | K10: Tự động | L10: Chưa có kết quả; chưa có kịch bản cho trường hợp này | M10: Chưa thực hiện | P10: Lý do: có thể kiểm thử ở mức API nhưng chưa có kịch bản (Bảng 3.38, dòng 5)
A11: HR-010 | B11: Ca làm, chấm công và lương | C11: UC16 | D11: Quản lý duyệt và từ chối ca làm việc | E11: Có ca pending từ HR-008; đăng nhập manager@tigershop.test | F11: status = approved cho ca thứ nhất; status = rejected cho ca thứ hai | G11: 1. Gửi PATCH /api/shifts/:id/status để duyệt 2. Gửi PATCH để từ chối ca thứ hai 3. Truy vấn status và manager_id | H11: Ca thứ nhất approved, ca thứ hai rejected; cả hai ghi nhận người xử lý (bước 5, 6) | I11: Positive | J11: Cao | K11: Tự động | L11: Ca thứ nhất chuyển approved, manager_id có giá trị. Nhánh từ chối chưa có kịch bản. Kịch bản HR-010b xác nhận nhân viên tự duyệt ca của mình bị chặn với mã 403 | M11: Pass | N11: Jest + Supertest | O11: 25/09/2026 | P11: Mức kiểm chứng hạn chế: chỉ kiểm tra một phần kết quả mong đợi (Bảng 3.37, dòng 2)
A12: HR-011 | B12: Ca làm, chấm công và lương | C12: UC17 | D12: Nhân viên gửi đơn xin đi muộn | E12: Đăng nhập staff@tigershop.test | F12: request_type = late; request_date = ngày mai; minutes_late = 30; reason = Tac duong | G12: 1. Gửi POST /api/users/staff/requests 2. Truy vấn staff_requests | H12: Đơn được lưu ở trạng thái pending với đúng số phút đi muộn (bước 2, 4) | I12: Positive | J12: Cao | K12: Tự động | L12: Yêu cầu thành công; request_type = late, minutes_late = 30, status = pending | M12: Pass | N12: Jest + Supertest | O12: 25/09/2026
A13: HR-012 | B13: Ca làm, chấm công và lương | C13: UC17 | D13: Gửi đơn khi bỏ trống lý do | E13: Đăng nhập bằng STAFF | F13: request_type = leave; reason rỗng | G13: 1. Gửi POST /api/users/staff/requests | H13: Mã 400, thông báo Thiếu thông tin đơn xin (ngoại lệ 2a) | I13: Negative | J13: Trung bình | K13: Tự động | L13: Mã 400; nội dung thông báo chưa được kịch bản kiểm tra. Kịch bản HR-012b xác nhận Quản lý duyệt được đơn từ, status chuyển approved (bước 5) | M13: Pass | N13: Jest + Supertest | O13: 25/09/2026 | P13: Mức kiểm chứng hạn chế: chỉ kiểm tra mã trạng thái (Bảng 3.37, dòng 1)
A14: HR-013 | B14: Ca làm, chấm công và lương | C14: UC19 | D14: Quản lý xem bảng lương toàn bộ nhân viên | E14: Có phiên chấm công đã đóng | F14: token của manager; month = tháng hiện tại | G14: 1. Gửi GET /api/users/staff/payroll?month=YYYY-MM 2. Đối chiếu với truy vấn SQL | H14: Lương của từng nhân viên bằng tổng worked_seconds chia 3600 nhân wage_rate lưu trong từng phiên (bước 2, 3) | I14: Positive | J14: Cao | K14: Thủ công | L14: Mã 200. Số liệu chưa được đối chiếu với truy vấn SQL. Kịch bản HR-013b xác nhận thiếu tham số month bị từ chối với mã 400 | M14: Pass | N14: Jest + Supertest | O14: 25/09/2026 | P14: Mức kiểm chứng hạn chế: chỉ kiểm tra mã trạng thái (Bảng 3.37, dòng 1); Thiết kế thủ công, đã thực hiện bằng kịch bản Jest (Bảng 3.4)
A15: HR-014 | B15: Ca làm, chấm công và lương | C15: UC19 | D15: Nhân viên xem bảng lương cá nhân | E15: Nhân viên có ít nhất 1 phiên chấm công đã đóng | F15: token của staff; month = tháng hiện tại | G15: 1. Gửi GET /api/users/staff/payroll/me?month=YYYY-MM | H15: Chỉ có dữ liệu của chính nhân viên đó, kèm chi tiết từng phiên (bước 5) | I15: Positive | J15: Cao | K15: Tự động | L15: Mã 200. Nội dung chưa được đối chiếu | M15: Pass | N15: Jest + Supertest | O15: 25/09/2026 | P15: Mức kiểm chứng hạn chế: chỉ kiểm tra mã trạng thái (Bảng 3.37, dòng 1)
A16: HR-015 | B16: Ca làm, chấm công và lương | C16: UC19 | D16: Nhân viên cố xem bảng lương toàn bộ | E16: Đăng nhập bằng STAFF | F16: token của staff | G16: 1. Gửi GET /api/users/staff/payroll?month=YYYY-MM | H16: Từ chối với mã 403; nhân viên chỉ xem được bảng lương của mình (ngoại lệ 5a) | I16: Security | J16: Cao | K16: Tự động | L16: Mã 403 | M16: Pass | N16: Jest + Supertest | O16: 25/09/2026

Sheet ADM
A1: Mã TC | B1: Nhóm chức năng | C1: UC liên quan | D1: Tiêu đề kiểm thử | E1: Điều kiện tiên quyết | F1: Dữ liệu đầu vào | G1: Các bước thực hiện | H1: Kết quả mong đợi | I1: Loại KT | J1: Mức ưu tiên | K1: Phương pháp | L1: Kết quả thực tế | M1: Trạng thái | N1: Người thực hiện | O1: Ngày thực hiện | P1: Ghi chú
A2: ADM-001 | B2: Quản trị hệ thống | C2: UC18 | D2: Duyệt tài khoản nhân viên đang chờ | E2: staff.pending@tigershop.test có status = pending | F2: token của admin; token của manager | G2: 1. Gửi PATCH /api/users/staff/:id/approve bằng token của Quản trị viên 2. Gửi cùng yêu cầu bằng token của Quản lý (kịch bản ADM-001b) | H2: Quản trị viên duyệt được: tài khoản chuyển active, nhân viên bắt đầu ở trạng thái thử việc (bước 4). Quản lý bị từ chối với mã 403, thông báo Chỉ Admin mới được duyệt tài khoản (ngoại lệ 4b) | I2: Positive | J2: Cao | K2: Tự động | L2: Token Quản trị viên: yêu cầu thành công, status = active. Token Quản lý: mã 403 với đúng thông báo. Giá trị employment_status sau khi duyệt chưa được kiểm tra | M2: Pass | N2: Jest + Supertest | O2: 25/09/2026 | P2: Kịch bản ADM-001b ghi nhận DEF-05 (phân quyền đặt ở hai nơi); Mức kiểm chứng hạn chế: chỉ kiểm tra một phần kết quả mong đợi (Bảng 3.37, dòng 2)
A3: ADM-002 | B3: Quản trị hệ thống | C3: UC18 | D3: Chuyển nhân viên từ thử việc sang chính thức | E3: staff.probation@tigershop.test đang thử việc | F3: token của manager | G3: 1. Gửi PATCH /api/users/staff/:id/official 2. Truy vấn employment_status và official_at | H3: employment_status chuyển official; official_at được ghi nhận; các phiên chấm công sau đó dùng official_hourly_rate (bước 5) | I3: Positive | J3: Cao | K3: Tự động | L3: Yêu cầu thành công; employment_status = official; official_at có giá trị. Việc vào ca lại với đơn giá mới chưa được kiểm tra | M3: Pass | N3: Jest + Supertest | O3: 25/09/2026 | P3: Mức kiểm chứng hạn chế: chỉ kiểm tra một phần kết quả mong đợi (Bảng 3.37, dòng 2)
A4: ADM-003 | B4: Quản trị hệ thống | C4: UC23 | D4: Quản trị viên thay đổi vai trò người dùng | E4: Đăng nhập admin@tigershop.test | F4: Tài khoản customer2; role_id = 3 | G4: 1. Gửi PUT /api/users/:id/role 2. Truy vấn role_id 3. Đăng nhập lại bằng tài khoản đó | H4: role_id được cập nhật (bước 3, 4); sau khi đăng nhập lại, người dùng vào không gian làm việc của vai trò mới | I4: Positive | J4: Cao | K4: Tự động | L4: Yêu cầu thành công; role_id = 3. Phần đăng nhập lại và chuyển trang chưa kiểm chứng | M4: Pass | N4: Jest + Supertest | O4: 25/09/2026 | P4: Mức kiểm chứng hạn chế: phần giao diện hoặc thời gian thực chưa kiểm chứng (Bảng 3.37, dòng 4)
A5: ADM-004 | B5: Quản trị hệ thống | C5: UC23 | D5: Quản trị viên khóa tài khoản người dùng | E5: Đăng nhập bằng ADMIN, tồn tại tài khoản đang hoạt động | F5: Tài khoản customer1; is_active = 0 | G5: 1. Gửi PUT /api/users/:id/status 2. Dùng token cũ của customer1 gọi GET /api/users/me | H5: Người bị khóa nhận mã 403 ngay ở lần gọi kế tiếp dù token còn hạn (ngoại lệ 3a) | I5: Security | J5: Cao | K5: Tự động | L5: Trước khi khóa mã 200; sau khi khóa mã 403 | M5: Pass | N5: Jest + Supertest | O5: 25/09/2026
A6: ADM-005 | B6: Quản trị hệ thống | C6: UC23 | D6: Quản trị viên đặt lại mật khẩu cho người dùng | E6: Đăng nhập admin@tigershop.test | F6: Tài khoản customer2; đặt lại hai lần liên tiếp (kịch bản ADM-005 và ADM-005b), mỗi lần gửi kèm một giá trị newPassword khác nhau | G6: 1. Gửi POST /api/users/:id/reset-password 2. Kiểm tra cột password và nội dung phản hồi 3. Lặp lại lần hai và so sánh | H6: Mỗi lần đặt lại, hệ thống sinh một mật khẩu tạm thời riêng, băm bằng bcrypt và không trả mật khẩu dạng rõ trong phản hồi (ngoại lệ 3b; mục 1.3.3) | I6: Security | J6: Cao | K6: Tự động | L6: Cột password là chuỗi băm bcrypt, nhưng cả hai lần đều là cùng một hằng số: bcrypt.compare với tiger@123 trả về true. Nội dung phản hồi chứa nguyên văn tiger@123; giá trị gửi lên bị bỏ qua | M6: Fail | N6: Jest + Supertest | O6: 25/09/2026 | P6: Khiếm khuyết DEF-06, trùng VUL-02, mức Nghiêm trọng (Bảng 3.36)
A7: ADM-006 | B7: Quản trị hệ thống | C7: UC23 | D7: Xóa mềm và khôi phục tài khoản | E7: Đăng nhập bằng ADMIN | F7: Tài khoản customer2 | G7: 1. Gửi DELETE /api/users/:id 2. Truy vấn deleted_at 3. Gửi PATCH /api/users/:id/restore | H7: Sau khi xóa: deleted_at được gán, tài khoản không còn trong danh sách; sau khi khôi phục: deleted_at trở về NULL (ngoại lệ 3c) | I7: Positive | J7: Trung bình | K7: Tự động | L7: Cả hai thao tác thành công; deleted_at có giá trị rồi trở về NULL. Danh sách người dùng chưa được đối chiếu | M7: Pass | N7: Jest + Supertest | O7: 25/09/2026 | P7: Mức kiểm chứng hạn chế: chỉ kiểm tra một phần kết quả mong đợi (Bảng 3.37, dòng 2)
A8: ADM-007 | B8: Quản trị hệ thống | C8: UC23 | D8: Khách hàng cố gọi điểm cuối quản trị người dùng | E8: Đăng nhập bằng CUSTOMER | F8: token của customer1 | G8: 1. Gửi GET /api/users 2. Gửi PUT /api/users/:id/role với role_id = 1 | H8: Cả hai yêu cầu bị từ chối với mã 403 (ngoại lệ 3f); phân quyền được kiểm tra ở máy chủ | I8: Security | J8: Cao | K8: Tự động | L8: Cả hai nhận mã 403; role_id của tài khoản đích vẫn là 3, không bị leo thang đặc quyền | M8: Pass | N8: Jest + Supertest | O8: 25/09/2026
A9: ADM-008 | B9: Quản trị hệ thống | C9: UC24 | D9: Xem thống kê sản phẩm bán chạy (UC24) | E9: Có đơn completed trong dữ liệu mẫu | F9: token của admin | G9: 1. Gửi GET /api/orders/admin/best-selling 2. Đối chiếu với truy vấn SQL chỉ lấy đơn completed | H9: Số liệu khớp với dữ liệu tổng hợp trực tiếp từ các bảng orders, order_items, products; chỉ tính đơn completed (bước 2) | I9: Positive | J9: Cao | K9: Thủ công | L9: Mã 200; danh sách mã sản phẩm và thứ tự trùng khớp kết quả truy vấn SQL. Kịch bản ADM-008b xác nhận nhân viên bị chặn với mã 403 ở điểm cuối thống kê doanh thu (ngoại lệ 1a) | M9: Pass | N9: Jest + Supertest | O9: 25/09/2026 | P9: Thiết kế thủ công, đã thực hiện bằng kịch bản Jest (Bảng 3.4)
A10: ADM-009 | B10: Quản trị hệ thống | C10: UC25 | D10: Quản trị viên xem nhật ký thao tác (UC25) | E10: Đã có thao tác quản trị trước đó | F10: token của admin | G10: 1. Gửi GET /api/users/logs | H10: Hiển thị hành động, người thực hiện, đối tượng tác động và thời điểm, theo thời gian giảm dần (bước 2, 3) | I10: Positive | J10: Trung bình | K10: Tự động | L10: Mã 200. Nội dung từng bản ghi nhật ký chưa được đối chiếu | M10: Pass | N10: Jest + Supertest | O10: 25/09/2026 | P10: Mức kiểm chứng hạn chế: chỉ kiểm tra mã trạng thái (Bảng 3.37, dòng 1)
A11: ADM-010 | B11: Quản trị hệ thống | C11: UC25 | D11: Người dùng không phải Quản trị viên xem nhật ký (UC25) | E11: Đăng nhập bằng CUSTOMER hoặc STAFF | F11: token của customer1 và của staff | G11: 1. Gửi GET /api/users/logs bằng từng token | H11: Mã 403; không lộ bản ghi nhật ký nào (ngoại lệ 1a) | I11: Security | J11: Cao | K11: Tự động | L11: Cả hai nhận mã 403; phản hồi không chứa mảng nhật ký | M11: Pass | N11: Jest + Supertest | O11: 25/09/2026

Sheet Truy vết UC và TC
A1: MA TRẬN TRUY VẾT GIỮA USE CASE VÀ TEST CASE (Bảng 3.32)
A3: Mã UC | B3: Số test case | C3: Danh sách mã test case | D3: Pass | E3: Fail | F3: Chưa thực hiện | G3: Đã thực hiện | H3: Ghi chú
A4: UC01 | B4: =COUNTIF('Toàn bộ Test Case'!C:C,A4) -> 11 | C4: AUTH-001, AUTH-002, AUTH-003, AUTH-004, AUTH-005, AUTH-006, AUTH-007, AUTH-008, AUTH-009, AUTH-010, AUTH-011 | D4: =COUNTIFS('Toàn bộ Test Case'!C:C,A4,'Toàn bộ Test Case'!M:M,"Pass") -> 7 | E4: =COUNTIFS('Toàn bộ Test Case'!C:C,A4,'Toàn bộ Test Case'!M:M,"Fail") -> 1 | F4: =COUNTIFS('Toàn bộ Test Case'!C:C,A4,'Toàn bộ Test Case'!M:M,"Chưa thực hiện") -> 3 | G4: =D4+E4 -> 8 | H4: AUTH-006 không đạt (DEF-12)
A5: UC02 | B5: =COUNTIF('Toàn bộ Test Case'!C:C,A5) -> 8 | C5: AUTH-012, AUTH-013, AUTH-014, AUTH-015, AUTH-016, AUTH-017, AUTH-018, AUTH-019 | D5: =COUNTIFS('Toàn bộ Test Case'!C:C,A5,'Toàn bộ Test Case'!M:M,"Pass") -> 8 | E5: =COUNTIFS('Toàn bộ Test Case'!C:C,A5,'Toàn bộ Test Case'!M:M,"Fail") -> 0 | F5: =COUNTIFS('Toàn bộ Test Case'!C:C,A5,'Toàn bộ Test Case'!M:M,"Chưa thực hiện") -> 0 | G5: =D5+E5 -> 8
A6: UC03 | B6: =COUNTIF('Toàn bộ Test Case'!C:C,A6) -> 3 | C6: AUTH-020, AUTH-021, AUTH-022 | D6: =COUNTIFS('Toàn bộ Test Case'!C:C,A6,'Toàn bộ Test Case'!M:M,"Pass") -> 2 | E6: =COUNTIFS('Toàn bộ Test Case'!C:C,A6,'Toàn bộ Test Case'!M:M,"Fail") -> 0 | F6: =COUNTIFS('Toàn bộ Test Case'!C:C,A6,'Toàn bộ Test Case'!M:M,"Chưa thực hiện") -> 1 | G6: =D6+E6 -> 2
A7: UC04 | B7: =COUNTIF('Toàn bộ Test Case'!C:C,A7) -> 3 | C7: AUTH-023, AUTH-024, AUTH-025 | D7: =COUNTIFS('Toàn bộ Test Case'!C:C,A7,'Toàn bộ Test Case'!M:M,"Pass") -> 2 | E7: =COUNTIFS('Toàn bộ Test Case'!C:C,A7,'Toàn bộ Test Case'!M:M,"Fail") -> 0 | F7: =COUNTIFS('Toàn bộ Test Case'!C:C,A7,'Toàn bộ Test Case'!M:M,"Chưa thực hiện") -> 1 | G7: =D7+E7 -> 2
A8: UC05 | B8: =COUNTIF('Toàn bộ Test Case'!C:C,A8) -> 7 | C8: PROD-001, PROD-002, PROD-003, PROD-004, PROD-005, PROD-006, PROD-007 | D8: =COUNTIFS('Toàn bộ Test Case'!C:C,A8,'Toàn bộ Test Case'!M:M,"Pass") -> 5 | E8: =COUNTIFS('Toàn bộ Test Case'!C:C,A8,'Toàn bộ Test Case'!M:M,"Fail") -> 0 | F8: =COUNTIFS('Toàn bộ Test Case'!C:C,A8,'Toàn bộ Test Case'!M:M,"Chưa thực hiện") -> 2 | G8: =D8+E8 -> 5
A9: UC06 | B9: =COUNTIF('Toàn bộ Test Case'!C:C,A9) -> 5 | C9: ORD-001, ORD-002, ORD-003, ORD-004, ORD-005 | D9: =COUNTIFS('Toàn bộ Test Case'!C:C,A9,'Toàn bộ Test Case'!M:M,"Pass") -> 0 | E9: =COUNTIFS('Toàn bộ Test Case'!C:C,A9,'Toàn bộ Test Case'!M:M,"Fail") -> 0 | F9: =COUNTIFS('Toàn bộ Test Case'!C:C,A9,'Toàn bộ Test Case'!M:M,"Chưa thực hiện") -> 5 | G9: =D9+E9 -> 0 | H9: Chưa thực hiện test case nào; UC06 không có API theo đặc tả
A10: UC07 | B10: =COUNTIF('Toàn bộ Test Case'!C:C,A10) -> 12 | C10: ORD-006, ORD-007, ORD-008, ORD-009, ORD-010, ORD-011, ORD-012, ORD-013, ORD-014, ORD-015, VOUC-011, VOUC-012 | D10: =COUNTIFS('Toàn bộ Test Case'!C:C,A10,'Toàn bộ Test Case'!M:M,"Pass") -> 11 | E10: =COUNTIFS('Toàn bộ Test Case'!C:C,A10,'Toàn bộ Test Case'!M:M,"Fail") -> 0 | F10: =COUNTIFS('Toàn bộ Test Case'!C:C,A10,'Toàn bộ Test Case'!M:M,"Chưa thực hiện") -> 1 | G10: =D10+E10 -> 11
A11: UC08 | B11: =COUNTIF('Toàn bộ Test Case'!C:C,A11) -> 5 | C11: ORD-016, ORD-017, ORD-018, ORD-019, ORD-020 | D11: =COUNTIFS('Toàn bộ Test Case'!C:C,A11,'Toàn bộ Test Case'!M:M,"Pass") -> 4 | E11: =COUNTIFS('Toàn bộ Test Case'!C:C,A11,'Toàn bộ Test Case'!M:M,"Fail") -> 0 | F11: =COUNTIFS('Toàn bộ Test Case'!C:C,A11,'Toàn bộ Test Case'!M:M,"Chưa thực hiện") -> 1 | G11: =D11+E11 -> 4
A12: UC09 | B12: =COUNTIF('Toàn bộ Test Case'!C:C,A12) -> 8 | C12: REV-001, REV-002, REV-003, REV-004, REV-005, REV-006, REV-007, REV-008 | D12: =COUNTIFS('Toàn bộ Test Case'!C:C,A12,'Toàn bộ Test Case'!M:M,"Pass") -> 8 | E12: =COUNTIFS('Toàn bộ Test Case'!C:C,A12,'Toàn bộ Test Case'!M:M,"Fail") -> 0 | F12: =COUNTIFS('Toàn bộ Test Case'!C:C,A12,'Toàn bộ Test Case'!M:M,"Chưa thực hiện") -> 0 | G12: =D12+E12 -> 8
A13: UC10 | B13: =COUNTIF('Toàn bộ Test Case'!C:C,A13) -> 10 | C13: VOUC-001, VOUC-002, VOUC-003, VOUC-004, VOUC-005, VOUC-006, VOUC-007, VOUC-008, VOUC-009, VOUC-010 | D13: =COUNTIFS('Toàn bộ Test Case'!C:C,A13,'Toàn bộ Test Case'!M:M,"Pass") -> 10 | E13: =COUNTIFS('Toàn bộ Test Case'!C:C,A13,'Toàn bộ Test Case'!M:M,"Fail") -> 0 | F13: =COUNTIFS('Toàn bộ Test Case'!C:C,A13,'Toàn bộ Test Case'!M:M,"Chưa thực hiện") -> 0 | G13: =D13+E13 -> 10
A14: UC11 | B14: =COUNTIF('Toàn bộ Test Case'!C:C,A14) -> 2 | C14: ORD-021, ORD-022 | D14: =COUNTIFS('Toàn bộ Test Case'!C:C,A14,'Toàn bộ Test Case'!M:M,"Pass") -> 1 | E14: =COUNTIFS('Toàn bộ Test Case'!C:C,A14,'Toàn bộ Test Case'!M:M,"Fail") -> 1 | F14: =COUNTIFS('Toàn bộ Test Case'!C:C,A14,'Toàn bộ Test Case'!M:M,"Chưa thực hiện") -> 0 | G14: =D14+E14 -> 2 | H14: ORD-022 không đạt (DEF-11)
A15: UC12 | B15: =COUNTIF('Toàn bộ Test Case'!C:C,A15) -> 9 | C15: PROD-008, PROD-009, PROD-010, PROD-011, PROD-012, PROD-013, PROD-014, PROD-015, PROD-016 | D15: =COUNTIFS('Toàn bộ Test Case'!C:C,A15,'Toàn bộ Test Case'!M:M,"Pass") -> 8 | E15: =COUNTIFS('Toàn bộ Test Case'!C:C,A15,'Toàn bộ Test Case'!M:M,"Fail") -> 1 | F15: =COUNTIFS('Toàn bộ Test Case'!C:C,A15,'Toàn bộ Test Case'!M:M,"Chưa thực hiện") -> 0 | G15: =D15+E15 -> 9 | H15: PROD-008 không đạt (DEF-02)
A16: UC13 | B16: =COUNTIF('Toàn bộ Test Case'!C:C,A16) -> 4 | C16: PROD-017, PROD-018, PROD-019, PROD-020 | D16: =COUNTIFS('Toàn bộ Test Case'!C:C,A16,'Toàn bộ Test Case'!M:M,"Pass") -> 3 | E16: =COUNTIFS('Toàn bộ Test Case'!C:C,A16,'Toàn bộ Test Case'!M:M,"Fail") -> 0 | F16: =COUNTIFS('Toàn bộ Test Case'!C:C,A16,'Toàn bộ Test Case'!M:M,"Chưa thực hiện") -> 1 | G16: =D16+E16 -> 3
A17: UC14 | B17: =COUNTIF('Toàn bộ Test Case'!C:C,A17) -> 2 | C17: PROD-021, PROD-022 | D17: =COUNTIFS('Toàn bộ Test Case'!C:C,A17,'Toàn bộ Test Case'!M:M,"Pass") -> 2 | E17: =COUNTIFS('Toàn bộ Test Case'!C:C,A17,'Toàn bộ Test Case'!M:M,"Fail") -> 0 | F17: =COUNTIFS('Toàn bộ Test Case'!C:C,A17,'Toàn bộ Test Case'!M:M,"Chưa thực hiện") -> 0 | G17: =D17+E17 -> 2
A18: UC15 | B18: =COUNTIF('Toàn bộ Test Case'!C:C,A18) -> 7 | C18: HR-001, HR-002, HR-003, HR-004, HR-005, HR-006, HR-007 | D18: =COUNTIFS('Toàn bộ Test Case'!C:C,A18,'Toàn bộ Test Case'!M:M,"Pass") -> 7 | E18: =COUNTIFS('Toàn bộ Test Case'!C:C,A18,'Toàn bộ Test Case'!M:M,"Fail") -> 0 | F18: =COUNTIFS('Toàn bộ Test Case'!C:C,A18,'Toàn bộ Test Case'!M:M,"Chưa thực hiện") -> 0 | G18: =D18+E18 -> 7
A19: UC16 | B19: =COUNTIF('Toàn bộ Test Case'!C:C,A19) -> 3 | C19: HR-008, HR-009, HR-010 | D19: =COUNTIFS('Toàn bộ Test Case'!C:C,A19,'Toàn bộ Test Case'!M:M,"Pass") -> 2 | E19: =COUNTIFS('Toàn bộ Test Case'!C:C,A19,'Toàn bộ Test Case'!M:M,"Fail") -> 0 | F19: =COUNTIFS('Toàn bộ Test Case'!C:C,A19,'Toàn bộ Test Case'!M:M,"Chưa thực hiện") -> 1 | G19: =D19+E19 -> 2
A20: UC17 | B20: =COUNTIF('Toàn bộ Test Case'!C:C,A20) -> 2 | C20: HR-011, HR-012 | D20: =COUNTIFS('Toàn bộ Test Case'!C:C,A20,'Toàn bộ Test Case'!M:M,"Pass") -> 2 | E20: =COUNTIFS('Toàn bộ Test Case'!C:C,A20,'Toàn bộ Test Case'!M:M,"Fail") -> 0 | F20: =COUNTIFS('Toàn bộ Test Case'!C:C,A20,'Toàn bộ Test Case'!M:M,"Chưa thực hiện") -> 0 | G20: =D20+E20 -> 2
A21: UC18 | B21: =COUNTIF('Toàn bộ Test Case'!C:C,A21) -> 2 | C21: ADM-001, ADM-002 | D21: =COUNTIFS('Toàn bộ Test Case'!C:C,A21,'Toàn bộ Test Case'!M:M,"Pass") -> 2 | E21: =COUNTIFS('Toàn bộ Test Case'!C:C,A21,'Toàn bộ Test Case'!M:M,"Fail") -> 0 | F21: =COUNTIFS('Toàn bộ Test Case'!C:C,A21,'Toàn bộ Test Case'!M:M,"Chưa thực hiện") -> 0 | G21: =D21+E21 -> 2
A22: UC19 | B22: =COUNTIF('Toàn bộ Test Case'!C:C,A22) -> 3 | C22: HR-013, HR-014, HR-015 | D22: =COUNTIFS('Toàn bộ Test Case'!C:C,A22,'Toàn bộ Test Case'!M:M,"Pass") -> 3 | E22: =COUNTIFS('Toàn bộ Test Case'!C:C,A22,'Toàn bộ Test Case'!M:M,"Fail") -> 0 | F22: =COUNTIFS('Toàn bộ Test Case'!C:C,A22,'Toàn bộ Test Case'!M:M,"Chưa thực hiện") -> 0 | G22: =D22+E22 -> 3
A23: UC20 | B23: =COUNTIF('Toàn bộ Test Case'!C:C,A23) -> 10 | C23: AI-001, AI-002, AI-003, AI-004, AI-005, AI-006, AI-007, AI-008, AI-009, AI-010 | D23: =COUNTIFS('Toàn bộ Test Case'!C:C,A23,'Toàn bộ Test Case'!M:M,"Pass") -> 8 | E23: =COUNTIFS('Toàn bộ Test Case'!C:C,A23,'Toàn bộ Test Case'!M:M,"Fail") -> 1 | F23: =COUNTIFS('Toàn bộ Test Case'!C:C,A23,'Toàn bộ Test Case'!M:M,"Chưa thực hiện") -> 1 | G23: =D23+E23 -> 9 | H23: AI-008 không đạt (PERF-03)
A24: UC21 | B24: =COUNTIF('Toàn bộ Test Case'!C:C,A24) -> 9 | C24: CHAT-001, CHAT-002, CHAT-003, CHAT-004, CHAT-005, CHAT-006, CHAT-007, CHAT-008, CHAT-009 | D24: =COUNTIFS('Toàn bộ Test Case'!C:C,A24,'Toàn bộ Test Case'!M:M,"Pass") -> 4 | E24: =COUNTIFS('Toàn bộ Test Case'!C:C,A24,'Toàn bộ Test Case'!M:M,"Fail") -> 1 | F24: =COUNTIFS('Toàn bộ Test Case'!C:C,A24,'Toàn bộ Test Case'!M:M,"Chưa thực hiện") -> 4 | G24: =D24+E24 -> 5 | H24: CHAT-009 không đạt (DEF-08)
A25: UC22 | B25: =COUNTIF('Toàn bộ Test Case'!C:C,A25) -> 2 | C25: CHAT-010, CHAT-011 | D25: =COUNTIFS('Toàn bộ Test Case'!C:C,A25,'Toàn bộ Test Case'!M:M,"Pass") -> 1 | E25: =COUNTIFS('Toàn bộ Test Case'!C:C,A25,'Toàn bộ Test Case'!M:M,"Fail") -> 0 | F25: =COUNTIFS('Toàn bộ Test Case'!C:C,A25,'Toàn bộ Test Case'!M:M,"Chưa thực hiện") -> 1 | G25: =D25+E25 -> 1
A26: UC23 | B26: =COUNTIF('Toàn bộ Test Case'!C:C,A26) -> 5 | C26: ADM-003, ADM-004, ADM-005, ADM-006, ADM-007 | D26: =COUNTIFS('Toàn bộ Test Case'!C:C,A26,'Toàn bộ Test Case'!M:M,"Pass") -> 4 | E26: =COUNTIFS('Toàn bộ Test Case'!C:C,A26,'Toàn bộ Test Case'!M:M,"Fail") -> 1 | F26: =COUNTIFS('Toàn bộ Test Case'!C:C,A26,'Toàn bộ Test Case'!M:M,"Chưa thực hiện") -> 0 | G26: =D26+E26 -> 5 | H26: ADM-005 không đạt (DEF-06)
A27: UC24 | B27: =COUNTIF('Toàn bộ Test Case'!C:C,A27) -> 1 | C27: ADM-008 | D27: =COUNTIFS('Toàn bộ Test Case'!C:C,A27,'Toàn bộ Test Case'!M:M,"Pass") -> 1 | E27: =COUNTIFS('Toàn bộ Test Case'!C:C,A27,'Toàn bộ Test Case'!M:M,"Fail") -> 0 | F27: =COUNTIFS('Toàn bộ Test Case'!C:C,A27,'Toàn bộ Test Case'!M:M,"Chưa thực hiện") -> 0 | G27: =D27+E27 -> 1
A28: UC25 | B28: =COUNTIF('Toàn bộ Test Case'!C:C,A28) -> 2 | C28: ADM-009, ADM-010 | D28: =COUNTIFS('Toàn bộ Test Case'!C:C,A28,'Toàn bộ Test Case'!M:M,"Pass") -> 2 | E28: =COUNTIFS('Toàn bộ Test Case'!C:C,A28,'Toàn bộ Test Case'!M:M,"Fail") -> 0 | F28: =COUNTIFS('Toàn bộ Test Case'!C:C,A28,'Toàn bộ Test Case'!M:M,"Chưa thực hiện") -> 0 | G28: =D28+E28 -> 2
A29: Tổng | B29: =SUM(B4:B28) -> 135 | D29: =SUM(D4:D28) -> 107 | E29: =SUM(E4:E28) -> 6 | F29: =SUM(F4:F28) -> 22 | G29: =SUM(G4:G28) -> 113
